Workbook

Sheet Supuestos
A1: SUPUESTOS DEL MODELO (celdas amarillas = editables)
A3: Datos del proyecto
A4: Plazas vehiculares techadas | B4: 28 | C4: und
A5: Plazas motos / mototaxis | B5: 7 | C5: und
A6: Área del terreno | B6: 820.2 | C6: m²
A7: Área pavimentada | B7: 713.8 | C7: m²
A8: Área techada | B8: 413.8 | C8: m²
A9: Acero estructural | B9: 6832 | C9: kg
A10: Tipo de piso (1 = afirmado, 2 = losa de concreto) | B10: 1
A11: Precio afirmado e=0.20 m | B11: 40 | C11: S/ por m²
A12: Precio losa de concreto e=0.15 m | B12: 130 | C12: S/ por m²
A13: Precio estructura metálica instalada | B13: 12 | C13: S/ por kg
A14: Gastos generales y dirección técnica | B14: 0.1 | C14: %
A15: Imprevistos | B15: 0.07 | C15: %
A16: Operación
A17: ¿Guardián contratado? (1 = sí, 0 = lo opera el propietario) | B17: 1
A18: Remuneración mínima vital | B18: 1130 | C18: S/ por mes
A19: Factor de cargas laborales (EsSalud + vacaciones) | B19: 1.1317
A20: Consumo eléctrico | B20: 10.9 | C20: kWh por día
A21: Tarifa eléctrica | B21: 0.8 | C21: S/ por kWh
A22: Agua y desagüe | B22: 35 | C22: S/ por mes
A23: Mantenimiento anual | B23: 0.01 | C23: % del CAPEX
A24: Predial y arbitrios | B24: 1200 | C24: S/ por año
A25: Seguro multirriesgo y RC | B25: 1800 | C25: S/ por año
A26: Cuota Nuevo RUS | B26: 50 | C26: S/ por mes
A27: Varios (tickets, internet) | B27: 100 | C27: S/ por mes
A28: Evaluación
A29: Ocupación relativa año 1 | B29: 0.6 | C29: %
A30: Ocupación relativa año 2 | B30: 0.85 | C30: %
A31: Crecimiento anual de tarifas y costos | B31: 0.03 | C31: %
A32: Tasa de descuento | B32: 0.1 | C32: %
A33: Mantenimiento mayor (año 10) | B33: 0.06 | C33: % del CAPEX

Sheet Inversion
A1: PRESUPUESTO REFERENCIAL DE INVERSIÓN (CAPEX) - S/ con IGV
A3: Grupo | B3: Partida | C3: Und. | D3: Cantidad | E3: P. unitario | F3: Parcial
A4: Obras preliminares | B4: Limpieza, retiro de capa orgánica e=0.20 m y eliminación | C4: m² | D4: 820.2 | E4: 8 | F4: =D4*E4
A5: Obras preliminares | B5: Trazo, nivelación y replanteo | C5: glb | D5: 1 | E5: 1500 | F5: =D5*E5
A6: Pavimento | B6: Pavimento (afirmado o losa según Supuestos) | C6: m² | D6: =Supuestos!$B$7 | E6: =IF(Supuestos!$B$10=1,Supuestos!$B$11,Supuestos!$B$12) | F6: =D6*E6
A7: Cerco y accesos | B7: Cerco de albañilería confinada h=2.40 m (frentes a calle) | C7: ml | D7: 41.8 | E7: 330 | F7: =D7*E7
A8: Cerco y accesos | B8: Cerco de albañilería h=2.40 m (fondo C-D) | C8: ml | D8: 30 | E8: 330 | F8: =D8*E8
A9: Cerco y accesos | B9: Portón metálico corredizo 3.00 x 2.40 m | C9: und | D9: 2 | E9: 4800 | F9: =D9*E9
A10: Cerco y accesos | B10: Puerta peatonal metálica 1.00 x 2.10 m | C10: und | D10: 2 | E10: 950 | F10: =D10*E10
A11: Estructura techada | B11: Zapata Z-1 + dado + pernos de anclaje | C11: und | D11: 13 | E11: 2022 | F11: =D11*E11
A12: Estructura techada | B12: Estructura metálica: suministro, fabricación, pintura y montaje | C12: kg | D12: =Supuestos!$B$9 | E12: =Supuestos!$B$13 | F12: =D12*E12
A13: Estructura techada | B13: Cobertura TR-4 0.40 mm prepintada + fascia y accesorios | C13: m² | D13: 438.6 | E13: 55 | F13: =D13*E13
A14: Estructura techada | B14: Canaleta galvanizada e=0.6 mm | C14: ml | D14: 72.6 | E14: 60 | F14: =D14*E14
A15: Estructura techada | B15: Bajadas pluviales PVC ø 4" | C15: und | D15: 13 | E15: 220 | F15: =D15*E15
A16: Drenaje | B16: Canaleta de piso con rejilla metálica y descarga a vía | C16: ml | D16: 40 | E16: 220 | F16: =D16*E16
A17: Instalaciones eléctricas | B17: Acometida, medidor y tablero general | C17: glb | D17: 1 | E17: 3800 | F17: =D17*E17
A18: Instalaciones eléctricas | B18: Luminaria LED hermética 40 W bajo techo | C18: und | D18: 14 | E18: 260 | F18: =D18*E18
A19: Instalaciones eléctricas | B19: Poste metálico 6 m con reflector LED 100 W | C19: und | D19: 3 | E19: 1800 | F19: =D19*E19
A20: Instalaciones eléctricas | B20: Cableado, tuberías y tomacorrientes | C20: glb | D20: 1 | E20: 3000 | F20: =D20*E20
A21: Instalaciones eléctricas | B21: Sistema CCTV (6 cámaras + grabador) | C21: glb | D21: 1 | E21: 4200 | F21: =D21*E21
A22: Servicios | B22: Garita, SS.HH. accesible y depósito (albañilería) | C22: m² | D22: 10.4 | E22: 1500 | F22: =D22*E22
A23: Servicios | B23: Instalaciones sanitarias (agua, desagüe y conexiones) | C23: glb | D23: 1 | E23: 3800 | F23: =D23*E23
A24: Señalización y seguridad | B24: Pintura de tráfico: líneas, numeración y flechas | C24: glb | D24: 1 | E24: 2800 | F24: =D24*E24
... A28: Estudios y licencias | B28: Topografía, EMS, expediente técnico firmado y licencias (edificación, funcionamiento, ITSE) | C28: glb | D28: 1 | E28: 13000 | F28: =D28*E28
E29: Subtotal | F29: =SUM(F4:F28)
E30: Gastos generales | F30: =F29*Supuestos!$B$14
E31: Imprevistos | F31: =(F29+F30)*Supuestos!$B$15
E32: TOTAL INVERSIÓN | F32: =F29+F30+F31
E33: Por plaza techada | F33: =Inversion!$F$32/Supuestos!$B$4

Sheet Escenarios
A1: ESCENARIOS DE DEMANDA Y RESULTADOS (año de operación estable)
B3: Pesimista | C3: Base | D3: Optimista
A4: Autos abonados mensuales (nocturno) | B4: 12 | C4: 18 | D4: 24
A5: Tarifa mensual por auto (S/) | B5: 100 | C5: 120 | D5: 140
A6: Autos de rotación por día | B6: 8 | C6: 12 | D6: 18
A7: Ticket promedio de rotación (S/) | B7: 4 | C7: 4.5 | D7: 5
A8: Motos / mototaxis abonados | B8: 4 | C8: 6 | D8: 7
A9: Tarifa mensual moto (S/) | B9: 35 | C9: 40 | D9: 45
A11: Ingreso mensual | B11: =B4*B5+B6*B7*30+B8*B9 | C11: =C4*C5+C6*C7*30+C8*C9 | D11: =D4*D5+D6*D7*30+D8*D9
A12: Ingreso anual | B12: =B11*12 | C12: =C11*12 | D12: =D11*12
A14: Costos de operación anuales
A15: Personal (1 guardián-cobrador) | B15: =Supuestos!$B$17*Supuestos!$B$18*Supuestos!$B$19*12 | C15: =Supuestos!$B$17*Supuestos!$B$18*Supuestos!$B$19*12 | D15: =Supuestos!$B$17*Supuestos!$B$18*Supuestos!$B$19*12
A16: Energía eléctrica | B16: =Supuestos!$B$20*30*Supuestos!$B$21*12 | C16: =Supuestos!$B$20*30*Supuestos!$B$21*12 | D16: =Supuestos!$B$20*30*Supuestos!$B$21*12
A17: Agua y desagüe | B17: =Supuestos!$B$22*12 | C17: =Supuestos!$B$22*12 | D17: =Supuestos!$B$22*12
A18: Mantenimiento | B18: =Supuestos!$B$23*Inversion!$F$32 | C18: =Supuestos!$B$23*Inversion!$F$32 | D18: =Supuestos!$B$23*Inversion!$F$32
A19: Predial y arbitrios | B19: =Supuestos!$B$24 | C19: =Supuestos!$B$24 | D19: =Supuestos!$B$24
A20: Seguro | B20: =Supuestos!$B$25 | C20: =Supuestos!$B$25 | D20: =Supuestos!$B$25
A21: Tributos (Nuevo RUS) | B21: =Supuestos!$B$26*12 | C21: =Supuestos!$B$26*12 | D21: =Supuestos!$B$26*12
A22: Varios | B22: =Supuestos!$B$27*12 | C22: =Supuestos!$B$27*12 | D22: =Supuestos!$B$27*12
A23: Total OPEX anual | B23: =SUM(B15:B22) | C23: =SUM(C15:C22) | D23: =SUM(D15:D22)
A25: Utilidad operativa anual (EBITDA) | B25: =B12-B23 | C25: =C12-C23 | D25: =D12-D23
A26: Inversión total (CAPEX) | B26: =Inversion!$F$32 | C26: =Inversion!$F$32 | D26: =Inversion!$F$32
A27: Recuperación simple (años) | B27: =IF(B25<=0,"No recupera",IF(B26/B25>30,"Más de 30",B26/B25)) | C27: =IF(C25<=0,"No recupera",IF(C26/C25>30,"Más de 30",C26/C25)) | D27: =IF(D25<=0,"No recupera",IF(D26/D25>30,"Más de 30",D26/D25))
A28: VAN a 20 años (tasa en Supuestos) | B28: =Flujo!B8+NPV(Supuestos!$B$32,Flujo!C8:V8) | C28: =Flujo!B15+NPV(Supuestos!$B$32,Flujo!C15:V15) | D28: =Flujo!B22+NPV(Supuestos!$B$32,Flujo!C22:V22)
A29: TIR a 20 años | B29: =IFERROR(IRR(Flujo!B8:V8),"Negativa") | C29: =IFERROR(IRR(Flujo!B15:V15),"Negativa") | D29: =IFERROR(IRR(Flujo!B22:V22),"Negativa")
A30: Nota: VAN y TIR usan el flujo de la hoja 'Flujo' (rampa de ocupación, crecimiento y mantenimiento mayor).

Sheet Flujo
A1: FLUJO DE CAJA ANUAL (20 años) - S/
A3: Año | B3: 0 | C3: 1 | D3: 2 | E3: 3 | F3: 4 | G3: 5 | H3: 6 | I3: 7 | J3: 8 | K3: 9 | L3: 10 | M3: 11 | N3: 12 | O3: 13 | P3: 14 | Q3: 15 | R3: 16 | S3: 17 | T3: 18 | U3: 19 | V3: 20
A4: Pesimista
A5: Ingresos | B5: 0 | C5: =Escenarios!$B$12*Supuestos!$B$29*(1+Supuestos!$B$31)^(1-1) | D5: =Escenarios!$B$12*Supuestos!$B$30*(1+Supuestos!$B$31)^(2-1) | E5: =Escenarios!$B$12*1*(1+Supuestos!$B$31)^(3-1) | F5: =Escenarios!$B$12*1*(1+Supuestos!$B$31)^(4-1) | G5: =Escenarios!$B$12*1*(1+Supuestos!$B$31)^(5-1) | H5: =Escenarios!$B$12*1*(1+Supuestos!$B$31)^(6-1) | I5: =Escenarios!$B$12*1*(1+Supuestos!$B$31)^(7-1) | J5: =Escenarios!$B$12*1*(1+Supuestos!$B$31)^(8-1) | K5: =Escenarios!$B$12*1*(1+Supuestos!$B$31)^(9-1) | L5: =Escenarios!$B$12*1*(1+Supuestos!$B$31)^(10-1) | M5: =Escenarios!$B$12*1*(1+Supuestos!$B$31)^(11-1) | N5: =Escenarios!$B$12*1*(1+Supuestos!$B$31)^(12-1) | O5: =Escenarios!$B$12*1*(1+Supuestos!$B$31)^(13-1) | P5: =Escenarios!$B$12*1*(1+Supuestos!$B$31)^(14-1) | Q5: =Escenarios!$B$12*1*(1+Supuestos!$B$31)^(15-1) | R5: =Escenarios!$B$12*1*(1+Supuestos!$B$31)^(16-1) | S5: =Escenarios!$B$12*1*(1+Supuestos!$B$31)^(17-1) | T5: =Escenarios!$B$12*1*(1+Supuestos!$B$31)^(18-1) | U5: =Escenarios!$B$12*1*(1+Supuestos!$B$31)^(19-1) | V5: =Escenarios!$B$12*1*(1+Supuestos!$B$31)^(20-1)
A6: OPEX | B6: 0 | C6: =Escenarios!$B$23*(1+Supuestos!$B$31)^(1-1) | D6: =Escenarios!$B$23*(1+Supuestos!$B$31)^(2-1) | E6: =Escenarios!$B$23*(1+Supuestos!$B$31)^(3-1) | F6: =Escenarios!$B$23*(1+Supuestos!$B$31)^(4-1) | G6: =Escenarios!$B$23*(1+Supuestos!$B$31)^(5-1) | H6: =Escenarios!$B$23*(1+Supuestos!$B$31)^(6-1) | I6: =Escenarios!$B$23*(1+Supuestos!$B$31)^(7-1) | J6: =Escenarios!$B$23*(1+Supuestos!$B$31)^(8-1) | K6: =Escenarios!$B$23*(1+Supuestos!$B$31)^(9-1) | L6: =Escenarios!$B$23*(1+Supuestos!$B$31)^(10-1) | M6: =Escenarios!$B$23*(1+Supuestos!$B$31)^(11-1) | N6: =Escenarios!$B$23*(1+Supuestos!$B$31)^(12-1) | O6: =Escenarios!$B$23*(1+Supuestos!$B$31)^(13-1) | P6: =Escenarios!$B$23*(1+Supuestos!$B$31)^(14-1) | Q6: =Escenarios!$B$23*(1+Supuestos!$B$31)^(15-1) | R6: =Escenarios!$B$23*(1+Supuestos!$B$31)^(16-1) | S6: =Escenarios!$B$23*(1+Supuestos!$B$31)^(17-1) | T6: =Escenarios!$B$23*(1+Supuestos!$B$31)^(18-1) | U6: =Escenarios!$B$23*(1+Supuestos!$B$31)^(19-1) | V6: =Escenarios!$B$23*(1+Supuestos!$B$31)^(20-1)
A7: Mantenimiento mayor | B7: 0 | C7: 0 | D7: 0 | E7: 0 | F7: 0 | G7: 0 | H7: 0 | I7: 0 | J7: 0 | K7: 0 | L7: =Supuestos!$B$33*Inversion!$F$32 | M7: 0 | N7: 0 | O7: 0 | P7: 0 | Q7: 0 | R7: 0 | S7: 0 | T7: 0 | U7: 0 | V7: 0
A8: Flujo neto | B8: =-Inversion!$F$32 | C8: =C5-C6-C7 | D8: =D5-D6-D7 | E8: =E5-E6-E7 | F8: =F5-F6-F7 | G8: =G5-G6-G7 | H8: =H5-H6-H7 | I8: =I5-I6-I7 | J8: =J5-J6-J7 | ... V8: =V5-V6-V7
A9: Flujo acumulado | B9: =B8 | C9: =B9+C8 | D9: =C9+D8 | E9: =D9+E8 | F9: =E9+F8 | G9: =F9+G8 | H9: =G9+H8 | I9: =H9+I8 | J9: =I9+J8 | ... V9: =U9+V8
A11: Base
A12: Ingresos | B12: 0 | C12: =Escenarios!$C$12*Supuestos!$B$29*(1+Supuestos!$B$31)^(1-1) | D12: =Escenarios!$C$12*Supuestos!$B$30*(1+Supuestos!$B$31)^(2-1) | E12: =Escenarios!$C$12*1*(1+Supuestos!$B$31)^(3-1) | F12: =Escenarios!$C$12*1*(1+Supuestos!$B$31)^(4-1) | G12: =Escenarios!$C$12*1*(1+Supuestos!$B$31)^(5-1) | H12: =Escenarios!$C$12*1*(1+Supuestos!$B$31)^(6-1) | I12: =Escenarios!$C$12*1*(1+Supuestos!$B$31)^(7-1) | J12: =Escenarios!$C$12*1*(1+Supuestos!$B$31)^(8-1) | K12: =Escenarios!$C$12*1*(1+Supuestos!$B$31)^(9-1) | L12: =Escenarios!$C$12*1*(1+Supuestos!$B$31)^(10-1) | M12: =Escenarios!$C$12*1*(1+Supuestos!$B$31)^(11-1) | N12: =Escenarios!$C$12*1*(1+Supuestos!$B$31)^(12-1) | O12: =Escenarios!$C$12*1*(1+Supuestos!$B$31)^(13-1) | P12: =Escenarios!$C$12*1*(1+Supuestos!$B$31)^(14-1) | Q12: =Escenarios!$C$12*1*(1+Supuestos!$B$31)^(15-1) | R12: =Escenarios!$C$12*1*(1+Supuestos!$B$31)^(16-1) | S12: =Escenarios!$C$12*1*(1+Supuestos!$B$31)^(17-1) | T12: =Escenarios!$C$12*1*(1+Supuestos!$B$31)^(18-1) | U12: =Escenarios!$C$12*1*(1+Supuestos!$B$31)^(19-1) | V12: =Escenarios!$C$12*1*(1+Supuestos!$B$31)^(20-1)
A13: OPEX | B13: 0 | C13: =Escenarios!$C$23*(1+Supuestos!$B$31)^(1-1) | D13: =Escenarios!$C$23*(1+Supuestos!$B$31)^(2-1) | E13: =Escenarios!$C$23*(1+Supuestos!$B$31)^(3-1) | F13: =Escenarios!$C$23*(1+Supuestos!$B$31)^(4-1) | G13: =Escenarios!$C$23*(1+Supuestos!$B$31)^(5-1) | H13: =Escenarios!$C$23*(1+Supuestos!$B$31)^(6-1) | I13: =Escenarios!$C$23*(1+Supuestos!$B$31)^(7-1) | J13: =Escenarios!$C$23*(1+Supuestos!$B$31)^(8-1) | K13: =Escenarios!$C$23*(1+Supuestos!$B$31)^(9-1) | L13: =Escenarios!$C$23*(1+Supuestos!$B$31)^(10-1) | M13: =Escenarios!$C$23*(1+Supuestos!$B$31)^(11-1) | N13: =Escenarios!$C$23*(1+Supuestos!$B$31)^(12-1) | O13: =Escenarios!$C$23*(1+Supuestos!$B$31)^(13-1) | P13: =Escenarios!$C$23*(1+Supuestos!$B$31)^(14-1) | Q13: =Escenarios!$C$23*(1+Supuestos!$B$31)^(15-1) | R13: =Escenarios!$C$23*(1+Supuestos!$B$31)^(16-1) | S13: =Escenarios!$C$23*(1+Supuestos!$B$31)^(17-1) | T13: =Escenarios!$C$23*(1+Supuestos!$B$31)^(18-1) | U13: =Escenarios!$C$23*(1+Supuestos!$B$31)^(19-1) | V13: =Escenarios!$C$23*(1+Supuestos!$B$31)^(20-1)
A14: Mantenimiento mayor | B14: 0 | C14: 0 | D14: 0 | E14: 0 | F14: 0 | G14: 0 | H14: 0 | I14: 0 | J14: 0 | K14: 0 | L14: =Supuestos!$B$33*Inversion!$F$32 | M14: 0 | N14: 0 | O14: 0 | P14: 0 | Q14: 0 | R14: 0 | S14: 0 | T14: 0 | U14: 0 | V14: 0
A15: Flujo neto | B15: =-Inversion!$F$32 | C15: =C12-C13-C14 | D15: =D12-D13-D14 | E15: =E12-E13-E14 | F15: =F12-F13-F14 | G15: =G12-G13-G14 | H15: =H12-H13-H14 | I15: =I12-I13-I14 | J15: =J12-J13-J14 | ... V15: =V12-V13-V14
A16: Flujo acumulado | B16: =B15 | C16: =B16+C15 | D16: =C16+D15 | E16: =D16+E15 | F16: =E16+F15 | G16: =F16+G15 | H16: =G16+H15 | I16: =H16+I15 | J16: =I16+J15 | ... V16: =U16+V15
A18: Optimista
A19: Ingresos | B19: 0 | C19: =Escenarios!$D$12*Supuestos!$B$29*(1+Supuestos!$B$31)^(1-1) | D19: =Escenarios!$D$12*Supuestos!$B$30*(1+Supuestos!$B$31)^(2-1) | E19: =Escenarios!$D$12*1*(1+Supuestos!$B$31)^(3-1) | F19: =Escenarios!$D$12*1*(1+Supuestos!$B$31)^(4-1) | G19: =Escenarios!$D$12*1*(1+Supuestos!$B$31)^(5-1) | H19: =Escenarios!$D$12*1*(1+Supuestos!$B$31)^(6-1) | I19: =Escenarios!$D$12*1*(1+Supuestos!$B$31)^(7-1) | J19: =Escenarios!$D$12*1*(1+Supuestos!$B$31)^(8-1) | K19: =Escenarios!$D$12*1*(1+Supuestos!$B$31)^(9-1) | L19: =Escenarios!$D$12*1*(1+Supuestos!$B$31)^(10-1) | M19: =Escenarios!$D$12*1*(1+Supuestos!$B$31)^(11-1) | N19: =Escenarios!$D$12*1*(1+Supuestos!$B$31)^(12-1) | O19: =Escenarios!$D$12*1*(1+Supuestos!$B$31)^(13-1) | P19: =Escenarios!$D$12*1*(1+Supuestos!$B$31)^(14-1) | Q19: =Escenarios!$D$12*1*(1+Supuestos!$B$31)^(15-1) | R19: =Escenarios!$D$12*1*(1+Supuestos!$B$31)^(16-1) | S19: =Escenarios!$D$12*1*(1+Supuestos!$B$31)^(17-1) | T19: =Escenarios!$D$12*1*(1+Supuestos!$B$31)^(18-1) | U19: =Escenarios!$D$12*1*(1+Supuestos!$B$31)^(19-1) | V19: =Escenarios!$D$12*1*(1+Supuestos!$B$31)^(20-1)
A20: OPEX | B20: 0 | C20: =Escenarios!$D$23*(1+Supuestos!$B$31)^(1-1) | D20: =Escenarios!$D$23*(1+Supuestos!$B$31)^(2-1) | E20: =Escenarios!$D$23*(1+Supuestos!$B$31)^(3-1) | F20: =Escenarios!$D$23*(1+Supuestos!$B$31)^(4-1) | G20: =Escenarios!$D$23*(1+Supuestos!$B$31)^(5-1) | H20: =Escenarios!$D$23*(1+Supuestos!$B$31)^(6-1) | I20: =Escenarios!$D$23*(1+Supuestos!$B$31)^(7-1) | J20: =Escenarios!$D$23*(1+Supuestos!$B$31)^(8-1) | K20: =Escenarios!$D$23*(1+Supuestos!$B$31)^(9-1) | L20: =Escenarios!$D$23*(1+Supuestos!$B$31)^(10-1) | M20: =Escenarios!$D$23*(1+Supuestos!$B$31)^(11-1) | N20: =Escenarios!$D$23*(1+Supuestos!$B$31)^(12-1) | O20: =Escenarios!$D$23*(1+Supuestos!$B$31)^(13-1) | P20: =Escenarios!$D$23*(1+Supuestos!$B$31)^(14-1) | Q20: =Escenarios!$D$23*(1+Supuestos!$B$31)^(15-1) | R20: =Escenarios!$D$23*(1+Supuestos!$B$31)^(16-1) | S20: =Escenarios!$D$23*(1+Supuestos!$B$31)^(17-1) | T20: =Escenarios!$D$23*(1+Supuestos!$B$31)^(18-1) | U20: =Escenarios!$D$23*(1+Supuestos!$B$31)^(19-1) | V20: =Escenarios!$D$23*(1+Supuestos!$B$31)^(20-1)
A21: Mantenimiento mayor | B21: 0 | C21: 0 | D21: 0 | E21: 0 | F21: 0 | G21: 0 | H21: 0 | I21: 0 | J21: 0 | K21: 0 | L21: =Supuestos!$B$33*Inversion!$F$32 | M21: 0 | N21: 0 | O21: 0 | P21: 0 | Q21: 0 | R21: 0 | S21: 0 | T21: 0 | U21: 0 | V21: 0
A22: Flujo neto | B22: =-Inversion!$F$32 | C22: =C19-C20-C21 | D22: =D19-D20-D21 | E22: =E19-E20-E21 | F22: =F19-F20-F21 | G22: =G19-G20-G21 | H22: =H19-H20-H21 | I22: =I19-I20-I21 | J22: =J19-J20-J21 | ... V22: =V19-V20-V21
A23: Flujo acumulado | B23: =B22 | C23: =B23+C22 | D23: =C23+D22 | E23: =D23+E22 | F23: =E23+F22 | G23: =F23+G22 | H23: =G23+H22 | I23: =H23+I22 | J23: =I23+J22 | ... V23: =U23+V22

Sheet Sensibilidad
A1: SENSIBILIDAD: utilidad operativa anual (S/) según autos abonados y tarifa mensual
A2: Rotación, motos y OPEX del escenario Base. Años de recuperación simple en la segunda tabla.
A4: Utilidad operativa anual
A5: Abonados \ Tarifa | B5: 80 | C5: 100 | D5: 120 | E5: 140 | F5: 160
A6: 8 | B6: =($A6*B$5*12+(Escenarios!$C$6*Escenarios!$C$7*30+Escenarios!$C$8*Escenarios!$C$9)*12-Escenarios!$C$23) | C6: =($A6*C$5*12+(Escenarios!$C$6*Escenarios!$C$7*30+Escenarios!$C$8*Escenarios!$C$9)*12-Escenarios!$C$23) | D6: =($A6*D$5*12+(Escenarios!$C$6*Escenarios!$C$7*30+Escenarios!$C$8*Escenarios!$C$9)*12-Escenarios!$C$23) | E6: =($A6*E$5*12+(Escenarios!$C$6*Escenarios!$C$7*30+Escenarios!$C$8*Escenarios!$C$9)*12-Escenarios!$C$23) | F6: =($A6*F$5*12+(Escenarios!$C$6*Escenarios!$C$7*30+Escenarios!$C$8*Escenarios!$C$9)*12-Escenarios!$C$23)
A7: 12 | B7: =($A7*B$5*12+(Escenarios!$C$6*Escenarios!$C$7*30+Escenarios!$C$8*Escenarios!$C$9)*12-Escenarios!$C$23) | C7: =($A7*C$5*12+(Escenarios!$C$6*Escenarios!$C$7*30+Escenarios!$C$8*Escenarios!$C$9)*12-Escenarios!$C$23) | D7: =($A7*D$5*12+(Escenarios!$C$6*Escenarios!$C$7*30+Escenarios!$C$8*Escenarios!$C$9)*12-Escenarios!$C$23) | E7: =($A7*E$5*12+(Escenarios!$C$6*Escenarios!$C$7*30+Escenarios!$C$8*Escenarios!$C$9)*12-Escenarios!$C$23) | F7: =($A7*F$5*12+(Escenarios!$C$6*Escenarios!$C$7*30+Escenarios!$C$8*Escenarios!$C$9)*12-Escenarios!$C$23)
A8: 16 | B8: =($A8*B$5*12+(Escenarios!$C$6*Escenarios!$C$7*30+Escenarios!$C$8*Escenarios!$C$9)*12-Escenarios!$C$23) | C8: =($A8*C$5*12+(Escenarios!$C$6*Escenarios!$C$7*30+Escenarios!$C$8*Escenarios!$C$9)*12-Escenarios!$C$23) | D8: =($A8*D$5*12+(Escenarios!$C$6*Escenarios!$C$7*30+Escenarios!$C$8*Escenarios!$C$9)*12-Escenarios!$C$23) | E8: =($A8*E$5*12+(Escenarios!$C$6*Escenarios!$C$7*30+Escenarios!$C$8*Escenarios!$C$9)*12-Escenarios!$C$23) | F8: =($A8*F$5*12+(Escenarios!$C$6*Escenarios!$C$7*30+Escenarios!$C$8*Escenarios!$C$9)*12-Escenarios!$C$23)
A9: 20 | B9: =($A9*B$5*12+(Escenarios!$C$6*Escenarios!$C$7*30+Escenarios!$C$8*Escenarios!$C$9)*12-Escenarios!$C$23) | C9: =($A9*C$5*12+(Escenarios!$C$6*Escenarios!$C$7*30+Escenarios!$C$8*Escenarios!$C$9)*12-Escenarios!$C$23) | D9: =($A9*D$5*12+(Escenarios!$C$6*Escenarios!$C$7*30+Escenarios!$C$8*Escenarios!$C$9)*12-Escenarios!$C$23) | E9: =($A9*E$5*12+(Escenarios!$C$6*Escenarios!$C$7*30+Escenarios!$C$8*Escenarios!$C$9)*12-Escenarios!$C$23) | F9: =($A9*F$5*12+(Escenarios!$C$6*Escenarios!$C$7*30+Escenarios!$C$8*Escenarios!$C$9)*12-Escenarios!$C$23)
A10: 24 | B10: =($A10*B$5*12+(Escenarios!$C$6*Escenarios!$C$7*30+Escenarios!$C$8*Escenarios!$C$9)*12-Escenarios!$C$23) | C10: =($A10*C$5*12+(Escenarios!$C$6*Escenarios!$C$7*30+Escenarios!$C$8*Escenarios!$C$9)*12-Escenarios!$C$23) | D10: =($A10*D$5*12+(Escenarios!$C$6*Escenarios!$C$7*30+Escenarios!$C$8*Escenarios!$C$9)*12-Escenarios!$C$23) | E10: =($A10*E$5*12+(Escenarios!$C$6*Escenarios!$C$7*30+Escenarios!$C$8*Escenarios!$C$9)*12-Escenarios!$C$23) | F10: =($A10*F$5*12+(Escenarios!$C$6*Escenarios!$C$7*30+Escenarios!$C$8*Escenarios!$C$9)*12-Escenarios!$C$23)
A11: 28 | B11: =($A11*B$5*12+(Escenarios!$C$6*Escenarios!$C$7*30+Escenarios!$C$8*Escenarios!$C$9)*12-Escenarios!$C$23) | C11: =($A11*C$5*12+(Escenarios!$C$6*Escenarios!$C$7*30+Escenarios!$C$8*Escenarios!$C$9)*12-Escenarios!$C$23) | D11: =($A11*D$5*12+(Escenarios!$C$6*Escenarios!$C$7*30+Escenarios!$C$8*Escenarios!$C$9)*12-Escenarios!$C$23) | E11: =($A11*E$5*12+(Escenarios!$C$6*Escenarios!$C$7*30+Escenarios!$C$8*Escenarios!$C$9)*12-Escenarios!$C$23) | F11: =($A11*F$5*12+(Escenarios!$C$6*Escenarios!$C$7*30+Escenarios!$C$8*Escenarios!$C$9)*12-Escenarios!$C$23)
A14: Años de recuperación
A15: Abonados \ Tarifa | B15: 80 | C15: 100 | D15: 120 | E15: 140 | F15: 160
A16: 8 | B16: =IF(($A16*B$15*12+(Escenarios!$C$6*Escenarios!$C$7*30+Escenarios!$C$8*Escenarios!$C$9)*12-Escenarios!$C$23)<=0,"No recupera",IF(Inversion!$F$32/($A16*B$15*12+(Escenarios!$C$6*Escenarios!$C$7*30+Escenarios!$C$8*Escenarios!$C$9)*12-Escenarios!$C$23)>30,"Más de 30",Inversion!$F$32/($A16*B$15*12+(Escenarios!$C$6*Escenarios!$C$7*30+Escenarios!$C$8*Escenarios!$C$9)*12-Escenarios!$C$23))) | C16: =IF(($A16*C$15*12+(Escenarios!$C$6*Escenarios!$C$7*30+Escenarios!$C$8*Escenarios!$C$9)*12-Escenarios!$C$23)<=0,"No recupera",IF(Inversion!$F$32/($A16*C$15*12+(Escenarios!$C$6*Escenarios!$C$7*30+Escenarios!$C$8*Escenarios!$C$9)*12-Escenarios!$C$23)>30,"Más de 30",Inversion!$F$32/($A16*C$15*12+(Escenarios!$C$6*Escenarios!$C$7*30+Escenarios!$C$8*Escenarios!$C$9)*12-Escenarios!$C$23))) | D16: =IF(($A16*D$15*12+(Escenarios!$C$6*Escenarios!$C$7*30+Escenarios!$C$8*Escenarios!$C$9)*12-Escenarios!$C$23)<=0,"No recupera",IF(Inversion!$F$32/($A16*D$15*12+(Escenarios!$C$6*Escenarios!$C$7*30+Escenarios!$C$8*Escenarios!$C$9)*12-Escenarios!$C$23)>30,"Más de 30",Inversion!$F$32/($A16*D$15*12+(Escenarios!$C$6*Escenarios!$C$7*30+Escenarios!$C$8*Escenarios!$C$9)*12-Escenarios!$C$23))) | E16: =IF(($A16*E$15*12+(Escenarios!$C$6*Escenarios!$C$7*30+Escenarios!$C$8*Escenarios!$C$9)*12-Escenarios!$C$23)<=0,"No recupera",IF(Inversion!$F$32/($A16*E$15*12+(Escenarios!$C$6*Escenarios!$C$7*30+Escenarios!$C$8*Escenarios!$C$9)*12-Escenarios!$C$23)>30,"Más de 30",Inversion!$F$32/($A16*E$15*12+(Escenarios!$C$6*Escenarios!$C$7*30+Escenarios!$C$8*Escenarios!$C$9)*12-Escenarios!$C$23))) | F16: =IF(($A16*F$15*12+(Escenarios!$C$6*Escenarios!$C$7*30+Escenarios!$C$8*Escenarios!$C$9)*12-Escenarios!$C$23)<=0,"No recupera",IF(Inversion!$F$32/($A16*F$15*12+(Escenarios!$C$6*Escenarios!$C$7*30+Escenarios!$C$8*Escenarios!$C$9)*12-Escenarios!$C$23)>30,"Más de 30",Inversion!$F$32/($A16*F$15*12+(Escenarios!$C$6*Escenarios!$C$7*30+Escenarios!$C$8*Escenarios!$C$9)*12-Escenarios!$C$23)))
A17: 12 | B17: =IF(($A17*B$15*12+(Escenarios!$C$6*Escenarios!$C$7*30+Escenarios!$C$8*Escenarios!$C$9)*12-Escenarios!$C$23)<=0,"No recupera",IF(Inversion!$F$32/($A17*B$15*12+(Escenarios!$C$6*Escenarios!$C$7*30+Escenarios!$C$8*Escenarios!$C$9)*12-Escenarios!$C$23)>30,"Más de 30",Inversion!$F$32/($A17*B$15*12+(Escenarios!$C$6*Escenarios!$C$7*30+Escenarios!$C$8*Escenarios!$C$9)*12-Escenarios!$C$23))) | C17: =IF(($A17*C$15*12+(Escenarios!$C$6*Escenarios!$C$7*30+Escenarios!$C$8*Escenarios!$C$9)*12-Escenarios!$C$23)<=0,"No recupera",IF(Inversion!$F$32/($A17*C$15*12+(Escenarios!$C$6*Escenarios!$C$7*30+Escenarios!$C$8*Escenarios!$C$9)*12-Escenarios!$C$23)>30,"Más de 30",Inversion!$F$32/($A17*C$15*12+(Escenarios!$C$6*Escenarios!$C$7*30+Escenarios!$C$8*Escenarios!$C$9)*12-Escenarios!$C$23))) | D17: =IF(($A17*D$15*12+(Escenarios!$C$6*Escenarios!$C$7*30+Escenarios!$C$8*Escenarios!$C$9)*12-Escenarios!$C$23)<=0,"No recupera",IF(Inversion!$F$32/($A17*D$15*12+(Escenarios!$C$6*Escenarios!$C$7*30+Escenarios!$C$8*Escenarios!$C$9)*12-Escenarios!$C$23)>30,"Más de 30",Inversion!$F$32/($A17*D$15*12+(Escenarios!$C$6*Escenarios!$C$7*30+Escenarios!$C$8*Escenarios!$C$9)*12-Escenarios!$C$23))) | E17: =IF(($A17*E$15*12+(Escenarios!$C$6*Escenarios!$C$7*30+Escenarios!$C$8*Escenarios!$C$9)*12-Escenarios!$C$23)<=0,"No recupera",IF(Inversion!$F$32/($A17*E$15*12+(Escenarios!$C$6*Escenarios!$C$7*30+Escenarios!$C$8*Escenarios!$C$9)*12-Escenarios!$C$23)>30,"Más de 30",Inversion!$F$32/($A17*E$15*12+(Escenarios!$C$6*Escenarios!$C$7*30+Escenarios!$C$8*Escenarios!$C$9)*12-Escenarios!$C$23))) | F17: =IF(($A17*F$15*12+(Escenarios!$C$6*Escenarios!$C$7*30+Escenarios!$C$8*Escenarios!$C$9)*12-Escenarios!$C$23)<=0,"No recupera",IF(Inversion!$F$32/($A17*F$15*12+(Escenarios!$C$6*Escenarios!$C$7*30+Escenarios!$C$8*Escenarios!$C$9)*12-Escenarios!$C$23)>30,"Más de 30",Inversion!$F$32/($A17*F$15*12+(Escenarios!$C$6*Escenarios!$C$7*30+Escenarios!$C$8*Escenarios!$C$9)*12-Escenarios!$C$23)))
A18: 16 | B18: =IF(($A18*B$15*12+(Escenarios!$C$6*Escenarios!$C$7*30+Escenarios!$C$8*Escenarios!$C$9)*12-Escenarios!$C$23)<=0,"No recupera",IF(Inversion!$F$32/($A18*B$15*12+(Escenarios!$C$6*Escenarios!$C$7*30+Escenarios!$C$8*Escenarios!$C$9)*12-Escenarios!$C$23)>30,"Más de 30",Inversion!$F$32/($A18*B$15*12+(Escenarios!$C$6*Escenarios!$C$7*30+Escenarios!$C$8*Escenarios!$C$9)*12-Escenarios!$C$23))) | C18: =IF(($A18*C$15*12+(Escenarios!$C$6*Escenarios!$C$7*30+Escenarios!$C$8*Escenarios!$C$9)*12-Escenarios!$C$23)<=0,"No recupera",IF(Inversion!$F$32/($A18*C$15*12+(Escenarios!$C$6*Escenarios!$C$7*30+Escenarios!$C$8*Escenarios!$C$9)*12-Escenarios!$C$23)>30,"Más de 30",Inversion!$F$32/($A18*C$15*12+(Escenarios!$C$6*Escenarios!$C$7*30+Escenarios!$C$8*Escenarios!$C$9)*12-Escenarios!$C$23))) | D18: =IF(($A18*D$15*12+(Escenarios!$C$6*Escenarios!$C$7*30+Escenarios!$C$8*Escenarios!$C$9)*12-Escenarios!$C$23)<=0,"No recupera",IF(Inversion!$F$32/($A18*D$15*12+(Escenarios!$C$6*Escenarios!$C$7*30+Escenarios!$C$8*Escenarios!$C$9)*12-Escenarios!$C$23)>30,"Más de 30",Inversion!$F$32/($A18*D$15*12+(Escenarios!$C$6*Escenarios!$C$7*30+Escenarios!$C$8*Escenarios!$C$9)*12-Escenarios!$C$23))) | E18: =IF(($A18*E$15*12+(Escenarios!$C$6*Escenarios!$C$7*30+Escenarios!$C$8*Escenarios!$C$9)*12-Escenarios!$C$23)<=0,"No recupera",IF(Inversion!$F$32/($A18*E$15*12+(Escenarios!$C$6*Escenarios!$C$7*30+Escenarios!$C$8*Escenarios!$C$9)*12-Escenarios!$C$23)>30,"Más de 30",Inversion!$F$32/($A18*E$15*12+(Escenarios!$C$6*Escenarios!$C$7*30+Escenarios!$C$8*Escenarios!$C$9)*12-Escenarios!$C$23))) | F18: =IF(($A18*F$15*12+(Escenarios!$C$6*Escenarios!$C$7*30+Escenarios!$C$8*Escenarios!$C$9)*12-Escenarios!$C$23)<=0,"No recupera",IF(Inversion!$F$32/($A18*F$15*12+(Escenarios!$C$6*Escenarios!$C$7*30+Escenarios!$C$8*Escenarios!$C$9)*12-Escenarios!$C$23)>30,"Más de 30",Inversion!$F$32/($A18*F$15*12+(Escenarios!$C$6*Escenarios!$C$7*30+Escenarios!$C$8*Escenarios!$C$9)*12-Escenarios!$C$23)))
A19: 20 | B19: =IF(($A19*B$15*12+(Escenarios!$C$6*Escenarios!$C$7*30+Escenarios!$C$8*Escenarios!$C$9)*12-Escenarios!$C$23)<=0,"No recupera",IF(Inversion!$F$32/($A19*B$15*12+(Escenarios!$C$6*Escenarios!$C$7*30+Escenarios!$C$8*Escenarios!$C$9)*12-Escenarios!$C$23)>30,"Más de 30",Inversion!$F$32/($A19*B$15*12+(Escenarios!$C$6*Escenarios!$C$7*30+Escenarios!$C$8*Escenarios!$C$9)*12-Escenarios!$C$23))) | C19: =IF(($A19*C$15*12+(Escenarios!$C$6*Escenarios!$C$7*30+Escenarios!$C$8*Escenarios!$C$9)*12-Escenarios!$C$23)<=0,"No recupera",IF(Inversion!$F$32/($A19*C$15*12+(Escenarios!$C$6*Escenarios!$C$7*30+Escenarios!$C$8*Escenarios!$C$9)*12-Escenarios!$C$23)>30,"Más de 30",Inversion!$F$32/($A19*C$15*12+(Escenarios!$C$6*Escenarios!$C$7*30+Escenarios!$C$8*Escenarios!$C$9)*12-Escenarios!$C$23))) | D19: =IF(($A19*D$15*12+(Escenarios!$C$6*Escenarios!$C$7*30+Escenarios!$C$8*Escenarios!$C$9)*12-Escenarios!$C$23)<=0,"No recupera",IF(Inversion!$F$32/($A19*D$15*12+(Escenarios!$C$6*Escenarios!$C$7*30+Escenarios!$C$8*Escenarios!$C$9)*12-Escenarios!$C$23)>30,"Más de 30",Inversion!$F$32/($A19*D$15*12+(Escenarios!$C$6*Escenarios!$C$7*30+Escenarios!$C$8*Escenarios!$C$9)*12-Escenarios!$C$23))) | E19: =IF(($A19*E$15*12+(Escenarios!$C$6*Escenarios!$C$7*30+Escenarios!$C$8*Escenarios!$C$9)*12-Escenarios!$C$23)<=0,"No recupera",IF(Inversion!$F$32/($A19*E$15*12+(Escenarios!$C$6*Escenarios!$C$7*30+Escenarios!$C$8*Escenarios!$C$9)*12-Escenarios!$C$23)>30,"Más de 30",Inversion!$F$32/($A19*E$15*12+(Escenarios!$C$6*Escenarios!$C$7*30+Escenarios!$C$8*Escenarios!$C$9)*12-Escenarios!$C$23))) | F19: =IF(($A19*F$15*12+(Escenarios!$C$6*Escenarios!$C$7*30+Escenarios!$C$8*Escenarios!$C$9)*12-Escenarios!$C$23)<=0,"No recupera",IF(Inversion!$F$32/($A19*F$15*12+(Escenarios!$C$6*Escenarios!$C$7*30+Escenarios!$C$8*Escenarios!$C$9)*12-Escenarios!$C$23)>30,"Más de 30",Inversion!$F$32/($A19*F$15*12+(Escenarios!$C$6*Escenarios!$C$7*30+Escenarios!$C$8*Escenarios!$C$9)*12-Escenarios!$C$23)))
A20: 24 | B20: =IF(($A20*B$15*12+(Escenarios!$C$6*Escenarios!$C$7*30+Escenarios!$C$8*Escenarios!$C$9)*12-Escenarios!$C$23)<=0,"No recupera",IF(Inversion!$F$32/($A20*B$15*12+(Escenarios!$C$6*Escenarios!$C$7*30+Escenarios!$C$8*Escenarios!$C$9)*12-Escenarios!$C$23)>30,"Más de 30",Inversion!$F$32/($A20*B$15*12+(Escenarios!$C$6*Escenarios!$C$7*30+Escenarios!$C$8*Escenarios!$C$9)*12-Escenarios!$C$23))) | C20: =IF(($A20*C$15*12+(Escenarios!$C$6*Escenarios!$C$7*30+Escenarios!$C$8*Escenarios!$C$9)*12-Escenarios!$C$23)<=0,"No recupera",IF(Inversion!$F$32/($A20*C$15*12+(Escenarios!$C$6*Escenarios!$C$7*30+Escenarios!$C$8*Escenarios!$C$9)*12-Escenarios!$C$23)>30,"Más de 30",Inversion!$F$32/($A20*C$15*12+(Escenarios!$C$6*Escenarios!$C$7*30+Escenarios!$C$8*Escenarios!$C$9)*12-Escenarios!$C$23))) | D20: =IF(($A20*D$15*12+(Escenarios!$C$6*Escenarios!$C$7*30+Escenarios!$C$8*Escenarios!$C$9)*12-Escenarios!$C$23)<=0,"No recupera",IF(Inversion!$F$32/($A20*D$15*12+(Escenarios!$C$6*Escenarios!$C$7*30+Escenarios!$C$8*Escenarios!$C$9)*12-Escenarios!$C$23)>30,"Más de 30",Inversion!$F$32/($A20*D$15*12+(Escenarios!$C$6*Escenarios!$C$7*30+Escenarios!$C$8*Escenarios!$C$9)*12-Escenarios!$C$23))) | E20: =IF(($A20*E$15*12+(Escenarios!$C$6*Escenarios!$C$7*30+Escenarios!$C$8*Escenarios!$C$9)*12-Escenarios!$C$23)<=0,"No recupera",IF(Inversion!$F$32/($A20*E$15*12+(Escenarios!$C$6*Escenarios!$C$7*30+Escenarios!$C$8*Escenarios!$C$9)*12-Escenarios!$C$23)>30,"Más de 30",Inversion!$F$32/($A20*E$15*12+(Escenarios!$C$6*Escenarios!$C$7*30+Escenarios!$C$8*Escenarios!$C$9)*12-Escenarios!$C$23))) | F20: =IF(($A20*F$15*12+(Escenarios!$C$6*Escenarios!$C$7*30+Escenarios!$C$8*Escenarios!$C$9)*12-Escenarios!$C$23)<=0,"No recupera",IF(Inversion!$F$32/($A20*F$15*12+(Escenarios!$C$6*Escenarios!$C$7*30+Escenarios!$C$8*Escenarios!$C$9)*12-Escenarios!$C$23)>30,"Más de 30",Inversion!$F$32/($A20*F$15*12+(Escenarios!$C$6*Escenarios!$C$7*30+Escenarios!$C$8*Escenarios!$C$9)*12-Escenarios!$C$23)))
A21: 28 | B21: =IF(($A21*B$15*12+(Escenarios!$C$6*Escenarios!$C$7*30+Escenarios!$C$8*Escenarios!$C$9)*12-Escenarios!$C$23)<=0,"No recupera",IF(Inversion!$F$32/($A21*B$15*12+(Escenarios!$C$6*Escenarios!$C$7*30+Escenarios!$C$8*Escenarios!$C$9)*12-Escenarios!$C$23)>30,"Más de 30",Inversion!$F$32/($A21*B$15*12+(Escenarios!$C$6*Escenarios!$C$7*30+Escenarios!$C$8*Escenarios!$C$9)*12-Escenarios!$C$23))) | C21: =IF(($A21*C$15*12+(Escenarios!$C$6*Escenarios!$C$7*30+Escenarios!$C$8*Escenarios!$C$9)*12-Escenarios!$C$23)<=0,"No recupera",IF(Inversion!$F$32/($A21*C$15*12+(Escenarios!$C$6*Escenarios!$C$7*30+Escenarios!$C$8*Escenarios!$C$9)*12-Escenarios!$C$23)>30,"Más de 30",Inversion!$F$32/($A21*C$15*12+(Escenarios!$C$6*Escenarios!$C$7*30+Escenarios!$C$8*Escenarios!$C$9)*12-Escenarios!$C$23))) | D21: =IF(($A21*D$15*12+(Escenarios!$C$6*Escenarios!$C$7*30+Escenarios!$C$8*Escenarios!$C$9)*12-Escenarios!$C$23)<=0,"No recupera",IF(Inversion!$F$32/($A21*D$15*12+(Escenarios!$C$6*Escenarios!$C$7*30+Escenarios!$C$8*Escenarios!$C$9)*12-Escenarios!$C$23)>30,"Más de 30",Inversion!$F$32/($A21*D$15*12+(Escenarios!$C$6*Escenarios!$C$7*30+Escenarios!$C$8*Escenarios!$C$9)*12-Escenarios!$C$23))) | E21: =IF(($A21*E$15*12+(Escenarios!$C$6*Escenarios!$C$7*30+Escenarios!$C$8*Escenarios!$C$9)*12-Escenarios!$C$23)<=0,"No recupera",IF(Inversion!$F$32/($A21*E$15*12+(Escenarios!$C$6*Escenarios!$C$7*30+Escenarios!$C$8*Escenarios!$C$9)*12-Escenarios!$C$23)>30,"Más de 30",Inversion!$F$32/($A21*E$15*12+(Escenarios!$C$6*Escenarios!$C$7*30+Escenarios!$C$8*Escenarios!$C$9)*12-Escenarios!$C$23))) | F21: =IF(($A21*F$15*12+(Escenarios!$C$6*Escenarios!$C$7*30+Escenarios!$C$8*Escenarios!$C$9)*12-Escenarios!$C$23)<=0,"No recupera",IF(Inversion!$F$32/($A21*F$15*12+(Escenarios!$C$6*Escenarios!$C$7*30+Escenarios!$C$8*Escenarios!$C$9)*12-Escenarios!$C$23)>30,"Más de 30",Inversion!$F$32/($A21*F$15*12+(Escenarios!$C$6*Escenarios!$C$7*30+Escenarios!$C$8*Escenarios!$C$9)*12-Escenarios!$C$23)))
