Workbook

Sheet Supuestos
A1: SUPUESTOS GENERALES (celdas amarillas = editables)
A3: Escenario (1 = pesimista, 2 = base, 3 = optimista) | B3: 2
A4: Tasa de descuento anual | B4: 0.1
A5: Crecimiento anual de rentas, tarifas y gastos | B5: 0.03
A6: Supervisión e imprevistos de obra | B6: 0.1
A7: Factor de costo de obra - pesimista | B7: 1.15
A8: Factor de costo de obra - base | B8: 1
A9: Factor de costo de obra - optimista | B9: 0.92
A10: Área del terreno (m²) | B10: 820.2
A11: Valor del terreno (S/ por m²) - pesimista | B11: 400
A12: Valor del terreno (S/ por m²) - base (requiere tasación) | B12: 600
A13: Valor del terreno (S/ por m²) - optimista | B13: 850
A14: Valorización anual del terreno - pesimista | B14: 0.03
... A19: Impuesto al alquiler (renta de 1.ª categoría, efectivo) | B19: 0.05
A21: Valor del terreno del escenario elegido (S/) | B21: =Supuestos!$B$10*CHOOSE(Supuestos!$B$3,Supuestos!$B$11,Supuestos!$B$12,Supuestos!$B$13)
A22: Factor de costo del escenario elegido | B22: =CHOOSE(Supuestos!$B$3,Supuestos!$B$7,Supuestos!$B$8,Supuestos!$B$9)
A23: Valorización del terreno del escenario elegido | B23: =CHOOSE(Supuestos!$B$3,Supuestos!$B$14,Supuestos!$B$15,Supuestos!$B$16)
A24: Depósito neto de impuestos | B24: =Supuestos!$B$17*(1-Supuestos!$B$18)
A26: Cómo usar: cambie el escenario o cualquier celda amarilla (aquí o en cada hoja de alternativa); la hoja «Comparación» se recalcula sola.

Sheet Comparación
A1: COMPARACIÓN DE ALTERNATIVAS (escenario elegido en «Supuestos»)
A3: Alt. | B3: Alternativa | C3: Inversión total | D3: VAN al 10 % | E3: TIR | F3: Recupera en el año | G3: Caja neta año 5 | H3: Rinde sobre (terreno + inversión) | I3: TIR contando el terreno | J3: Riesgo | K3: Futuro | L3: Gestión | M3: Capital
A4: L | B4: Ceder la esquina en derecho de superficie (el inquilino construye) | C4: ='L Esquina cedida'!$C$38 | D4: ='L Esquina cedida'!$C$39 | E4: ='L Esquina cedida'!$C$40 | F4: ='L Esquina cedida'!$C$41 | G4: ='L Esquina cedida'!$C$42 | H4: =G4/((1+Supuestos!$B$5)^4)/(C4+Supuestos!$B$21) | I4: ='L Esquina cedida'!$C$43 | J4: medio | K4: alta: al vencer el plazo la edificación queda para el propietario | L4: baja | M4: sin capital
A5: J | B5: Arrendar el lote completo a un operador | C5: ='J Arrendar el lote'!$C$38 | D5: ='J Arrendar el lote'!$C$39 | E5: ='J Arrendar el lote'!$C$40 | F5: ='J Arrendar el lote'!$C$41 | G5: ='J Arrendar el lote'!$C$42 | H5: =G5/((1+Supuestos!$B$5)^4)/(C5+Supuestos!$B$21) | I5: ='J Arrendar el lote'!$C$43 | J5: medio | K5: media: un contrato largo congela el lote (pactar salida anticipada con aviso) | L5: muy baja | M5: sin capital
A6: B | B6: Estacionamiento descubierto de bajo costo | C6: ='B Estac. descubierto'!$C$51 | D6: ='B Estac. descubierto'!$C$52 | E6: ='B Estac. descubierto'!$C$53 | F6: ='B Estac. descubierto'!$C$54 | G6: ='B Estac. descubierto'!$C$55 | H6: =G6/((1+Supuestos!$B$5)^4)/(C6+Supuestos!$B$21) | I6: ='B Estac. descubierto'!$C$56 | J6: medio | K6: alta: casi todo es reversible | L6: media (guardián, cobranza) | M6: propio
A7: C1 | B7: Local de esquina + cochera de abonados | C7: ='C1 Esquina + cochera'!$C$72 | D7: ='C1 Esquina + cochera'!$C$73 | E7: ='C1 Esquina + cochera'!$C$74 | F7: ='C1 Esquina + cochera'!$C$75 | G7: ='C1 Esquina + cochera'!$C$76 | H7: =G7/((1+Supuestos!$B$5)^4)/(C7+Supuestos!$B$21) | I7: ='C1 Esquina + cochera'!$C$77 | J7: medio | K7: alta: la esquina queda lista para crecer y el resto del frente sigue libre | L7: baja | M7: propio
A8: K | B8: Terminal o paradero de vans y colectivos | C8: ='K Terminal de vans'!$C$44 | D8: ='K Terminal de vans'!$C$45 | E8: ='K Terminal de vans'!$C$46 | F8: ='K Terminal de vans'!$C$47 | G8: ='K Terminal de vans'!$C$48 | H8: =G8/((1+Supuestos!$B$5)^4)/(C8+Supuestos!$B$21) | I8: ='K Terminal de vans'!$C$49 | J8: alto | K8: media | L8: alta (autorizaciones, empresas de transporte) | M8: propio
A9: C | B9: Locales en la esquina y el jirón + cochera de abonados | C9: ='C Locales + cochera'!$C$97 | D9: ='C Locales + cochera'!$C$98 | E9: ='C Locales + cochera'!$C$99 | F9: ='C Locales + cochera'!$C$100 | G9: ='C Locales + cochera'!$C$101 | H9: =G9/((1+Supuestos!$B$5)^4)/(C9+Supuestos!$B$21) | I9: ='C Locales + cochera'!$C$102 | J9: medio-alto | K9: alta: deja la estructura lista para crecer en altura | L9: baja (alquiler pasivo) | M9: propio
A10: A | B10: Estacionamiento techado (anteproyecto actual) | C10: ='A Estac. techado'!$C$40 | D10: ='A Estac. techado'!$C$41 | E10: ='A Estac. techado'!$C$42 | F10: ='A Estac. techado'!$C$43 | G10: ='A Estac. techado'!$C$44 | H10: =G10/((1+Supuestos!$B$5)^4)/(C10+Supuestos!$B$21) | I10: ='A Estac. techado'!$C$45 | J10: medio | K10: media: la estructura metálica se puede desmontar, pero ocupa todo el lote | L10: media (guardián, cobranza) | M10: propio
A11: F | B11: Cancha sintética techada (fulbito) | C11: ='F Cancha techada'!$C$51 | D11: ='F Cancha techada'!$C$52 | E11: ='F Cancha techada'!$C$53 | F11: ='F Cancha techada'!$C$54 | G11: ='F Cancha techada'!$C$55 | H11: =G11/((1+Supuestos!$B$5)^4)/(C11+Supuestos!$B$21) | I11: ='F Cancha techada'!$C$56 | J11: alto | K11: baja: ocupa todo el lote y tapa el frente comercial al jirón | L11: alta (horarios nocturnos, encargado) | M11: propio
A12: G | B12: Local de eventos (salón de recepciones) | C12: ='G Local de eventos'!$C$44 | D12: ='G Local de eventos'!$C$45 | E12: ='G Local de eventos'!$C$46 | F12: ='G Local de eventos'!$C$47 | G12: ='G Local de eventos'!$C$48 | H12: =G12/((1+Supuestos!$B$5)^4)/(C12+Supuestos!$B$21) | I12: ='G Local de eventos'!$C$49 | J12: alto | K12: media | L12: alta (agenda, limpieza, vecinos) | M12: propio
A13: E | B13: C + 1 piso de consultorios (año 2) | C13: ='E C + consultorios'!$C$123 | D13: ='E C + consultorios'!$C$124 | E13: ='E C + consultorios'!$C$125 | F13: ='E C + consultorios'!$C$126 | G13: ='E C + consultorios'!$C$127 | H13: =G13/((1+Supuestos!$B$5)^4)/(C13+Supuestos!$B$21) | I13: ='E C + consultorios'!$C$128 | J13: alto | K13: media | L13: media | M13: propio
A14: D | B14: C + 2 pisos de minidepartamentos (año 3) | C14: ='D C + minideptos'!$C$122 | D14: ='D C + minideptos'!$C$123 | E14: ='D C + minideptos'!$C$124 | F14: ='D C + minideptos'!$C$125 | G14: ='D C + minideptos'!$C$126 | H14: =G14/((1+Supuestos!$B$5)^4)/(C14+Supuestos!$B$21) | I14: ='D C + minideptos'!$C$127 | J14: alto | K14: media | L14: media (8 inquilinos) | M14: propio
A15: H | B15: Hostal de 16 habitaciones (3 pisos) | C15: ='H Hostal'!$C$42 | D15: ='H Hostal'!$C$43 | E15: ='H Hostal'!$C$44 | F15: ='H Hostal'!$C$45 | G15: ='H Hostal'!$C$46 | H15: =G15/((1+Supuestos!$B$5)^4)/(C15+Supuestos!$B$21) | I15: ='H Hostal'!$C$47 | J15: alto | K15: media | L15: muy alta (operación 24 h) | M15: propio
B17: Vender el terreno hoy (referencia) | C17: =Supuestos!$B$21 | D17: Precio de venta estimado; depositado al | E17: =Supuestos!$B$17 | F17: rendiría por año: | G17: =Supuestos!$B$21*Supuestos!$B$24 | H17: =Supuestos!$B$24 | I17: =Supuestos!$B$24
B19: Orden: por VAN en el escenario base. «Rinde sobre (terreno + inversión)» compara la caja del año 5 (a precios de hoy) con todo el capital comprometido, incluido el valor del terreno. «TIR contando el terreno» trata el lote como si se aportara hoy a valor de mercado y se recuperara valorizado en el año 20: si es menor que vender y depositar (fila de referencia), la alternativa no paga el terreno.

Sheet L Esquina cedida
A1: L. Ceder la esquina en derecho de superficie (el inquilino construye)
A2: Una cadena, caja, cooperativa o comercio construye su local en la esquina (build-to-suit o derecho de superficie a 10-20 años) y paga renta por el suelo. El fondo queda libre para arrendarlo o para una cochera si se prevenden abonos.
A4: Fase 1: Derecho de superficie en la esquina
D5: Inversión (calculada en su propio modelo, por factor de escenario) | E5: =0.0*Supuestos!$B$22
D6: Año de inversión (opera desde el año siguiente) | E6: 0
D7: Ingreso bruto potencial S/ por mes - pesimista | E7: 560
D8: Ingreso bruto potencial S/ por mes - base | E8: 800
D9: Ingreso bruto potencial S/ por mes - optimista | E9: 1200
D10: Ocupación cobrada - pesimista | E10: 0.95
D11: Ocupación cobrada - base | E11: 0.95
D12: Ocupación cobrada - optimista | E12: 0.95
D13: Gastos fijos S/ por año (personal, energía, mantenimiento, seguro, predial) | E13: 300
D14: Gastos variables (% del ingreso cobrado) | E14: 0
D15: Impuestos (% del ingreso cobrado) | E15: 0.05
D16: Ingreso relativo 1.er año de operación | E16: 0.5
D17: Ingreso relativo 2.º año de operación | E17: 1
D18: Vida útil para valor residual (años) | E18: 1
A20: FLUJO DE CAJA (S/ nominales)
A21: Concepto / año | C21: 0 | D21: 1 | E21: 2 | F21: 3 | G21: 4 | H21: 5 | I21: 6 | J21: 7 | K21: 8 | L21: 9 | M21: 10 | N21: 11 | O21: 12 | P21: 13 | Q21: 14 | R21: 15 | S21: 16 | T21: 17 | U21: 18 | V21: 19 | W21: 20
A22: Inversión - fase 1 | C22: =IF(C$21=$E$6,-$E$5*(1+Supuestos!$B$5)^MAX($E$6-1,0),0) | D22: =IF(D$21=$E$6,-$E$5*(1+Supuestos!$B$5)^MAX($E$6-1,0),0) | E22: =IF(E$21=$E$6,-$E$5*(1+Supuestos!$B$5)^MAX($E$6-1,0),0) | F22: =IF(F$21=$E$6,-$E$5*(1+Supuestos!$B$5)^MAX($E$6-1,0),0) | G22: =IF(G$21=$E$6,-$E$5*(1+Supuestos!$B$5)^MAX($E$6-1,0),0) | H22: =IF(H$21=$E$6,-$E$5*(1+Supuestos!$B$5)^MAX($E$6-1,0),0) | I22: =IF(I$21=$E$6,-$E$5*(1+Supuestos!$B$5)^MAX($E$6-1,0),0) | J22: =IF(J$21=$E$6,-$E$5*(1+Supuestos!$B$5)^MAX($E$6-1,0),0) | ... W22: =IF(W$21=$E$6,-$E$5*(1+Supuestos!$B$5)^MAX($E$6-1,0),0)
A23: Ingresos cobrados - fase 1 | C23: =IF((C$21-$E$6)>=1,CHOOSE(Supuestos!$B$3,$E$7,$E$8,$E$9)*12*CHOOSE(Supuestos!$B$3,$E$10,$E$11,$E$12)*IF((C$21-$E$6)=1,$E$16,IF((C$21-$E$6)=2,$E$17,1))*(1+Supuestos!$B$5)^MAX(C$21-1,0),0) | D23: =IF((D$21-$E$6)>=1,CHOOSE(Supuestos!$B$3,$E$7,$E$8,$E$9)*12*CHOOSE(Supuestos!$B$3,$E$10,$E$11,$E$12)*IF((D$21-$E$6)=1,$E$16,IF((D$21-$E$6)=2,$E$17,1))*(1+Supuestos!$B$5)^MAX(D$21-1,0),0) | E23: =IF((E$21-$E$6)>=1,CHOOSE(Supuestos!$B$3,$E$7,$E$8,$E$9)*12*CHOOSE(Supuestos!$B$3,$E$10,$E$11,$E$12)*IF((E$21-$E$6)=1,$E$16,IF((E$21-$E$6)=2,$E$17,1))*(1+Supuestos!$B$5)^MAX(E$21-1,0),0) | F23: =IF((F$21-$E$6)>=1,CHOOSE(Supuestos!$B$3,$E$7,$E$8,$E$9)*12*CHOOSE(Supuestos!$B$3,$E$10,$E$11,$E$12)*IF((F$21-$E$6)=1,$E$16,IF((F$21-$E$6)=2,$E$17,1))*(1+Supuestos!$B$5)^MAX(F$21-1,0),0) | G23: =IF((G$21-$E$6)>=1,CHOOSE(Supuestos!$B$3,$E$7,$E$8,$E$9)*12*CHOOSE(Supuestos!$B$3,$E$10,$E$11,$E$12)*IF((G$21-$E$6)=1,$E$16,IF((G$21-$E$6)=2,$E$17,1))*(1+Supuestos!$B$5)^MAX(G$21-1,0),0) | H23: =IF((H$21-$E$6)>=1,CHOOSE(Supuestos!$B$3,$E$7,$E$8,$E$9)*12*CHOOSE(Supuestos!$B$3,$E$10,$E$11,$E$12)*IF((H$21-$E$6)=1,$E$16,IF((H$21-$E$6)=2,$E$17,1))*(1+Supuestos!$B$5)^MAX(H$21-1,0),0) | I23: =IF((I$21-$E$6)>=1,CHOOSE(Supuestos!$B$3,$E$7,$E$8,$E$9)*12*CHOOSE(Supuestos!$B$3,$E$10,$E$11,$E$12)*IF((I$21-$E$6)=1,$E$16,IF((I$21-$E$6)=2,$E$17,1))*(1+Supuestos!$B$5)^MAX(I$21-1,0),0) | J23: =IF((J$21-$E$6)>=1,CHOOSE(Supuestos!$B$3,$E$7,$E$8,$E$9)*12*CHOOSE(Supuestos!$B$3,$E$10,$E$11,$E$12)*IF((J$21-$E$6)=1,$E$16,IF((J$21-$E$6)=2,$E$17,1))*(1+Supuestos!$B$5)^MAX(J$21-1,0),0) | ... W23: =IF((W$21-$E$6)>=1,CHOOSE(Supuestos!$B$3,$E$7,$E$8,$E$9)*12*CHOOSE(Supuestos!$B$3,$E$10,$E$11,$E$12)*IF((W$21-$E$6)=1,$E$16,IF((W$21-$E$6)=2,$E$17,1))*(1+Supuestos!$B$5)^MAX(W$21-1,0),0)
A24: Gastos - fase 1 | C24: =IF((C$21-$E$6)>=1,-$E$13*(1+Supuestos!$B$5)^MAX(C$21-1,0)-$E$14*C23,0) | D24: =IF((D$21-$E$6)>=1,-$E$13*(1+Supuestos!$B$5)^MAX(D$21-1,0)-$E$14*D23,0) | E24: =IF((E$21-$E$6)>=1,-$E$13*(1+Supuestos!$B$5)^MAX(E$21-1,0)-$E$14*E23,0) | F24: =IF((F$21-$E$6)>=1,-$E$13*(1+Supuestos!$B$5)^MAX(F$21-1,0)-$E$14*F23,0) | G24: =IF((G$21-$E$6)>=1,-$E$13*(1+Supuestos!$B$5)^MAX(G$21-1,0)-$E$14*G23,0) | H24: =IF((H$21-$E$6)>=1,-$E$13*(1+Supuestos!$B$5)^MAX(H$21-1,0)-$E$14*H23,0) | I24: =IF((I$21-$E$6)>=1,-$E$13*(1+Supuestos!$B$5)^MAX(I$21-1,0)-$E$14*I23,0) | J24: =IF((J$21-$E$6)>=1,-$E$13*(1+Supuestos!$B$5)^MAX(J$21-1,0)-$E$14*J23,0) | ... W24: =IF((W$21-$E$6)>=1,-$E$13*(1+Supuestos!$B$5)^MAX(W$21-1,0)-$E$14*W23,0)
A25: Impuestos - fase 1 | C25: =-$E$15*C23 | D25: =-$E$15*D23 | E25: =-$E$15*E23 | F25: =-$E$15*F23 | G25: =-$E$15*G23 | H25: =-$E$15*H23 | I25: =-$E$15*I23 | J25: =-$E$15*J23 | ... W25: =-$E$15*W23
A26: Reposiciones - fase 1 | C26: =0 | D26: =0 | E26: =0 | F26: =0 | G26: =0 | H26: =0 | I26: =0 | J26: =0 | ... W26: =0
A27: Valor residual (año 20) - fase 1 | C27: =IF(AND(C$21=20,$E$18>1),$E$5*(1+Supuestos!$B$5)^MAX($E$6-1,0)*MAX(0,1-(20-$E$6)/$E$18),0) | D27: =IF(AND(D$21=20,$E$18>1),$E$5*(1+Supuestos!$B$5)^MAX($E$6-1,0)*MAX(0,1-(20-$E$6)/$E$18),0) | E27: =IF(AND(E$21=20,$E$18>1),$E$5*(1+Supuestos!$B$5)^MAX($E$6-1,0)*MAX(0,1-(20-$E$6)/$E$18),0) | F27: =IF(AND(F$21=20,$E$18>1),$E$5*(1+Supuestos!$B$5)^MAX($E$6-1,0)*MAX(0,1-(20-$E$6)/$E$18),0) | G27: =IF(AND(G$21=20,$E$18>1),$E$5*(1+Supuestos!$B$5)^MAX($E$6-1,0)*MAX(0,1-(20-$E$6)/$E$18),0) | H27: =IF(AND(H$21=20,$E$18>1),$E$5*(1+Supuestos!$B$5)^MAX($E$6-1,0)*MAX(0,1-(20-$E$6)/$E$18),0) | I27: =IF(AND(I$21=20,$E$18>1),$E$5*(1+Supuestos!$B$5)^MAX($E$6-1,0)*MAX(0,1-(20-$E$6)/$E$18),0) | J27: =IF(AND(J$21=20,$E$18>1),$E$5*(1+Supuestos!$B$5)^MAX($E$6-1,0)*MAX(0,1-(20-$E$6)/$E$18),0) | ... W27: =IF(AND(W$21=20,$E$18>1),$E$5*(1+Supuestos!$B$5)^MAX($E$6-1,0)*MAX(0,1-(20-$E$6)/$E$18),0)
A28: Inversión | C28: =C22 | D28: =D22 | E28: =E22 | F28: =F22 | G28: =G22 | H28: =H22 | I28: =I22 | J28: =J22 | ... W28: =W22
A29: Ingresos cobrados | C29: =C23 | D29: =D23 | E29: =E23 | F29: =F23 | G29: =G23 | H29: =H23 | I29: =I23 | J29: =J23 | ... W29: =W23
A30: Gastos | C30: =C24 | D30: =D24 | E30: =E24 | F30: =F24 | G30: =G24 | H30: =H24 | I30: =I24 | J30: =J24 | ... W30: =W24
A31: Impuestos | C31: =C25 | D31: =D25 | E31: =E25 | F31: =F25 | G31: =G25 | H31: =H25 | I31: =I25 | J31: =J25 | ... W31: =W25
A32: Reposiciones | C32: =C26 | D32: =D26 | E32: =E26 | F32: =F26 | G32: =G26 | H32: =H26 | I32: =I26 | J32: =J26 | ... W32: =W26
A33: Valor residual (año 20) | C33: =C27 | D33: =D27 | E33: =E27 | F33: =F27 | G33: =G27 | H33: =H27 | I33: =I27 | J33: =J27 | ... W33: =W27
A34: FLUJO NETO | C34: =C28+C29+C30+C31+C32+C33 | D34: =D28+D29+D30+D31+D32+D33 | E34: =E28+E29+E30+E31+E32+E33 | F34: =F28+F29+F30+F31+F32+F33 | G34: =G28+G29+G30+G31+G32+G33 | H34: =H28+H29+H30+H31+H32+H33 | I34: =I28+I29+I30+I31+I32+I33 | J34: =J28+J29+J30+J31+J32+J33 | ... W34: =W28+W29+W30+W31+W32+W33
A35: Caja acumulada (sin valor residual) | C35: =C34-C33 | D35: =C35+D34-D33 | E35: =D35+E34-E33 | F35: =E35+F34-F33 | G35: =F35+G34-G33 | H35: =G35+H34-H33 | I35: =H35+I34-I33 | J35: =I35+J34-J33 | K35: =J35+K34-K33 | ... W35: =V35+W34-W33
A36: Flujo del propietario contando el terreno (lo aporta hoy y lo recupera valorizado) | C36: =C34-Supuestos!$B$21 | D36: =D34 | E36: =E34 | F36: =F34 | G36: =G34 | H36: =H34 | I36: =I34 | J36: =J34 | K36: =K34 | ... V36: =V34 | W36: =W34+Supuestos!$B$21*(1+Supuestos!$B$23)^20
A38: Inversión total | C38: =-SUM(C28:W28)
A39: VAN al 10% | C39: =C34+NPV(Supuestos!$B$4,D34:W34)
A40: TIR | C40: =IFERROR(IRR(C34:W34),IFERROR(IRR(C34:W34,-0.05),"no aplica"))
A41: Año en que se recupera la inversión (acumulado ≥ 0) | C41: =IF(-SUM(C28:W28)=0,"sin inversión",IFERROR(INDEX(C21:W21,MATCH(TRUE,INDEX(C35:W35>=0,0),0)),"no en 20 años"))
A42: Caja neta del año 5 sin inversiones (S/ nominales) | C42: =H34-H28
A43: TIR contando el terreno | C43: =IFERROR(IRR(C36:W36),"no aplica")

Sheet J Arrendar el lote
A1: J. Arrendar el lote completo a un operador
A2: Contrato de 3-10 años con reajuste anual y garantía (depósito de materiales, concesionario o taller de motos, paradero, feria); el inquilino hace sus mejoras.
A4: Fase 1: Arriendo del lote
D5: Inversión (calculada en su propio modelo, por factor de escenario) | E5: =0.0*Supuestos!$B$22
D6: Año de inversión (opera desde el año siguiente) | E6: 0
D7: Ingreso bruto potencial S/ por mes - pesimista | E7: 600
D8: Ingreso bruto potencial S/ por mes - base | E8: 1000
D9: Ingreso bruto potencial S/ por mes - optimista | E9: 1800
D10: Ocupación cobrada - pesimista | E10: 0.6
D11: Ocupación cobrada - base | E11: 0.75
D12: Ocupación cobrada - optimista | E12: 0.9
D13: Gastos fijos S/ por año (personal, energía, mantenimiento, seguro, predial) | E13: 400
D14: Gastos variables (% del ingreso cobrado) | E14: 0
D15: Impuestos (% del ingreso cobrado) | E15: 0.05
D16: Ingreso relativo 1.er año de operación | E16: 0.5
D17: Ingreso relativo 2.º año de operación | E17: 1
D18: Vida útil para valor residual (años) | E18: 1
A20: FLUJO DE CAJA (S/ nominales)
A21: Concepto / año | C21: 0 | D21: 1 | E21: 2 | F21: 3 | G21: 4 | H21: 5 | I21: 6 | J21: 7 | K21: 8 | L21: 9 | M21: 10 | N21: 11 | O21: 12 | P21: 13 | Q21: 14 | R21: 15 | S21: 16 | T21: 17 | U21: 18 | V21: 19 | W21: 20
A22: Inversión - fase 1 | C22: =IF(C$21=$E$6,-$E$5*(1+Supuestos!$B$5)^MAX($E$6-1,0),0) | D22: =IF(D$21=$E$6,-$E$5*(1+Supuestos!$B$5)^MAX($E$6-1,0),0) | E22: =IF(E$21=$E$6,-$E$5*(1+Supuestos!$B$5)^MAX($E$6-1,0),0) | F22: =IF(F$21=$E$6,-$E$5*(1+Supuestos!$B$5)^MAX($E$6-1,0),0) | G22: =IF(G$21=$E$6,-$E$5*(1+Supuestos!$B$5)^MAX($E$6-1,0),0) | H22: =IF(H$21=$E$6,-$E$5*(1+Supuestos!$B$5)^MAX($E$6-1,0),0) | I22: =IF(I$21=$E$6,-$E$5*(1+Supuestos!$B$5)^MAX($E$6-1,0),0) | J22: =IF(J$21=$E$6,-$E$5*(1+Supuestos!$B$5)^MAX($E$6-1,0),0) | ... W22: =IF(W$21=$E$6,-$E$5*(1+Supuestos!$B$5)^MAX($E$6-1,0),0)
A23: Ingresos cobrados - fase 1 | C23: =IF((C$21-$E$6)>=1,CHOOSE(Supuestos!$B$3,$E$7,$E$8,$E$9)*12*CHOOSE(Supuestos!$B$3,$E$10,$E$11,$E$12)*IF((C$21-$E$6)=1,$E$16,IF((C$21-$E$6)=2,$E$17,1))*(1+Supuestos!$B$5)^MAX(C$21-1,0),0) | D23: =IF((D$21-$E$6)>=1,CHOOSE(Supuestos!$B$3,$E$7,$E$8,$E$9)*12*CHOOSE(Supuestos!$B$3,$E$10,$E$11,$E$12)*IF((D$21-$E$6)=1,$E$16,IF((D$21-$E$6)=2,$E$17,1))*(1+Supuestos!$B$5)^MAX(D$21-1,0),0) | E23: =IF((E$21-$E$6)>=1,CHOOSE(Supuestos!$B$3,$E$7,$E$8,$E$9)*12*CHOOSE(Supuestos!$B$3,$E$10,$E$11,$E$12)*IF((E$21-$E$6)=1,$E$16,IF((E$21-$E$6)=2,$E$17,1))*(1+Supuestos!$B$5)^MAX(E$21-1,0),0) | F23: =IF((F$21-$E$6)>=1,CHOOSE(Supuestos!$B$3,$E$7,$E$8,$E$9)*12*CHOOSE(Supuestos!$B$3,$E$10,$E$11,$E$12)*IF((F$21-$E$6)=1,$E$16,IF((F$21-$E$6)=2,$E$17,1))*(1+Supuestos!$B$5)^MAX(F$21-1,0),0) | G23: =IF((G$21-$E$6)>=1,CHOOSE(Supuestos!$B$3,$E$7,$E$8,$E$9)*12*CHOOSE(Supuestos!$B$3,$E$10,$E$11,$E$12)*IF((G$21-$E$6)=1,$E$16,IF((G$21-$E$6)=2,$E$17,1))*(1+Supuestos!$B$5)^MAX(G$21-1,0),0) | H23: =IF((H$21-$E$6)>=1,CHOOSE(Supuestos!$B$3,$E$7,$E$8,$E$9)*12*CHOOSE(Supuestos!$B$3,$E$10,$E$11,$E$12)*IF((H$21-$E$6)=1,$E$16,IF((H$21-$E$6)=2,$E$17,1))*(1+Supuestos!$B$5)^MAX(H$21-1,0),0) | I23: =IF((I$21-$E$6)>=1,CHOOSE(Supuestos!$B$3,$E$7,$E$8,$E$9)*12*CHOOSE(Supuestos!$B$3,$E$10,$E$11,$E$12)*IF((I$21-$E$6)=1,$E$16,IF((I$21-$E$6)=2,$E$17,1))*(1+Supuestos!$B$5)^MAX(I$21-1,0),0) | J23: =IF((J$21-$E$6)>=1,CHOOSE(Supuestos!$B$3,$E$7,$E$8,$E$9)*12*CHOOSE(Supuestos!$B$3,$E$10,$E$11,$E$12)*IF((J$21-$E$6)=1,$E$16,IF((J$21-$E$6)=2,$E$17,1))*(1+Supuestos!$B$5)^MAX(J$21-1,0),0) | ... W23: =IF((W$21-$E$6)>=1,CHOOSE(Supuestos!$B$3,$E$7,$E$8,$E$9)*12*CHOOSE(Supuestos!$B$3,$E$10,$E$11,$E$12)*IF((W$21-$E$6)=1,$E$16,IF((W$21-$E$6)=2,$E$17,1))*(1+Supuestos!$B$5)^MAX(W$21-1,0),0)
A24: Gastos - fase 1 | C24: =IF((C$21-$E$6)>=1,-$E$13*(1+Supuestos!$B$5)^MAX(C$21-1,0)-$E$14*C23,0) | D24: =IF((D$21-$E$6)>=1,-$E$13*(1+Supuestos!$B$5)^MAX(D$21-1,0)-$E$14*D23,0) | E24: =IF((E$21-$E$6)>=1,-$E$13*(1+Supuestos!$B$5)^MAX(E$21-1,0)-$E$14*E23,0) | F24: =IF((F$21-$E$6)>=1,-$E$13*(1+Supuestos!$B$5)^MAX(F$21-1,0)-$E$14*F23,0) | G24: =IF((G$21-$E$6)>=1,-$E$13*(1+Supuestos!$B$5)^MAX(G$21-1,0)-$E$14*G23,0) | H24: =IF((H$21-$E$6)>=1,-$E$13*(1+Supuestos!$B$5)^MAX(H$21-1,0)-$E$14*H23,0) | I24: =IF((I$21-$E$6)>=1,-$E$13*(1+Supuestos!$B$5)^MAX(I$21-1,0)-$E$14*I23,0) | J24: =IF((J$21-$E$6)>=1,-$E$13*(1+Supuestos!$B$5)^MAX(J$21-1,0)-$E$14*J23,0) | ... W24: =IF((W$21-$E$6)>=1,-$E$13*(1+Supuestos!$B$5)^MAX(W$21-1,0)-$E$14*W23,0)
A25: Impuestos - fase 1 | C25: =-$E$15*C23 | D25: =-$E$15*D23 | E25: =-$E$15*E23 | F25: =-$E$15*F23 | G25: =-$E$15*G23 | H25: =-$E$15*H23 | I25: =-$E$15*I23 | J25: =-$E$15*J23 | ... W25: =-$E$15*W23
A26: Reposiciones - fase 1 | C26: =0 | D26: =0 | E26: =0 | F26: =0 | G26: =0 | H26: =0 | I26: =0 | J26: =0 | ... W26: =0
A27: Valor residual (año 20) - fase 1 | C27: =IF(AND(C$21=20,$E$18>1),$E$5*(1+Supuestos!$B$5)^MAX($E$6-1,0)*MAX(0,1-(20-$E$6)/$E$18),0) | D27: =IF(AND(D$21=20,$E$18>1),$E$5*(1+Supuestos!$B$5)^MAX($E$6-1,0)*MAX(0,1-(20-$E$6)/$E$18),0) | E27: =IF(AND(E$21=20,$E$18>1),$E$5*(1+Supuestos!$B$5)^MAX($E$6-1,0)*MAX(0,1-(20-$E$6)/$E$18),0) | F27: =IF(AND(F$21=20,$E$18>1),$E$5*(1+Supuestos!$B$5)^MAX($E$6-1,0)*MAX(0,1-(20-$E$6)/$E$18),0) | G27: =IF(AND(G$21=20,$E$18>1),$E$5*(1+Supuestos!$B$5)^MAX($E$6-1,0)*MAX(0,1-(20-$E$6)/$E$18),0) | H27: =IF(AND(H$21=20,$E$18>1),$E$5*(1+Supuestos!$B$5)^MAX($E$6-1,0)*MAX(0,1-(20-$E$6)/$E$18),0) | I27: =IF(AND(I$21=20,$E$18>1),$E$5*(1+Supuestos!$B$5)^MAX($E$6-1,0)*MAX(0,1-(20-$E$6)/$E$18),0) | J27: =IF(AND(J$21=20,$E$18>1),$E$5*(1+Supuestos!$B$5)^MAX($E$6-1,0)*MAX(0,1-(20-$E$6)/$E$18),0) | ... W27: =IF(AND(W$21=20,$E$18>1),$E$5*(1+Supuestos!$B$5)^MAX($E$6-1,0)*MAX(0,1-(20-$E$6)/$E$18),0)
A28: Inversión | C28: =C22 | D28: =D22 | E28: =E22 | F28: =F22 | G28: =G22 | H28: =H22 | I28: =I22 | J28: =J22 | ... W28: =W22
A29: Ingresos cobrados | C29: =C23 | D29: =D23 | E29: =E23 | F29: =F23 | G29: =G23 | H29: =H23 | I29: =I23 | J29: =J23 | ... W29: =W23
A30: Gastos | C30: =C24 | D30: =D24 | E30: =E24 | F30: =F24 | G30: =G24 | H30: =H24 | I30: =I24 | J30: =J24 | ... W30: =W24
A31: Impuestos | C31: =C25 | D31: =D25 | E31: =E25 | F31: =F25 | G31: =G25 | H31: =H25 | I31: =I25 | J31: =J25 | ... W31: =W25
A32: Reposiciones | C32: =C26 | D32: =D26 | E32: =E26 | F32: =F26 | G32: =G26 | H32: =H26 | I32: =I26 | J32: =J26 | ... W32: =W26
A33: Valor residual (año 20) | C33: =C27 | D33: =D27 | E33: =E27 | F33: =F27 | G33: =G27 | H33: =H27 | I33: =I27 | J33: =J27 | ... W33: =W27
A34: FLUJO NETO | C34: =C28+C29+C30+C31+C32+C33 | D34: =D28+D29+D30+D31+D32+D33 | E34: =E28+E29+E30+E31+E32+E33 | F34: =F28+F29+F30+F31+F32+F33 | G34: =G28+G29+G30+G31+G32+G33 | H34: =H28+H29+H30+H31+H32+H33 | I34: =I28+I29+I30+I31+I32+I33 | J34: =J28+J29+J30+J31+J32+J33 | ... W34: =W28+W29+W30+W31+W32+W33
A35: Caja acumulada (sin valor residual) | C35: =C34-C33 | D35: =C35+D34-D33 | E35: =D35+E34-E33 | F35: =E35+F34-F33 | G35: =F35+G34-G33 | H35: =G35+H34-H33 | I35: =H35+I34-I33 | J35: =I35+J34-J33 | K35: =J35+K34-K33 | ... W35: =V35+W34-W33
A36: Flujo del propietario contando el terreno (lo aporta hoy y lo recupera valorizado) | C36: =C34-Supuestos!$B$21 | D36: =D34 | E36: =E34 | F36: =F34 | G36: =G34 | H36: =H34 | I36: =I34 | J36: =J34 | K36: =K34 | ... V36: =V34 | W36: =W34+Supuestos!$B$21*(1+Supuestos!$B$23)^20
A38: Inversión total | C38: =-SUM(C28:W28)
A39: VAN al 10% | C39: =C34+NPV(Supuestos!$B$4,D34:W34)
A40: TIR | C40: =IFERROR(IRR(C34:W34),IFERROR(IRR(C34:W34,-0.05),"no aplica"))
A41: Año en que se recupera la inversión (acumulado ≥ 0) | C41: =IF(-SUM(C28:W28)=0,"sin inversión",IFERROR(INDEX(C21:W21,MATCH(TRUE,INDEX(C35:W35>=0,0),0)),"no en 20 años"))
A42: Caja neta del año 5 sin inversiones (S/ nominales) | C42: =H34-H28
A43: TIR contando el terreno | C43: =IFERROR(IRR(C36:W36),"no aplica")

Sheet B Estac. descubierto
A1: B. Estacionamiento descubierto de bajo costo
A2: Afirmado, cerco de malla, caseta y portones; 28 plazas a la intemperie, con guardián. Demanda base: 10 abonados a S/ 85, 7 autos de rotación al día a S/ 3.50 y 4 motos a S/ 35.
A4: Fase 1: Estacionamiento descubierto
A5: Partida | B5: Und. | C5: Cantidad | D5: P. unitario | E5: Parcial
A6: Afirmado compactado e=0.20 m con bombeo | B6: m² | C6: 680 | D6: 40 | E6: =C6*D6
A7: Cerco de malla galvanizada h=2.0 m en frentes | B7: ml | C7: 44 | D7: 120 | E7: =C7*D7
A8: Portones de malla 3.0 m (ingreso y salida) | B8: und | C8: 2 | D8: 2200 | E8: =C8*D8
A9: Caseta prefabricada de control con SS.HH. básico | B9: und | C9: 1 | D9: 9000 | E9: =C9*D9
A10: Postes con reflector LED | B10: und | C10: 3 | D10: 1800 | E10: =C10*D10
A11: Cuneta de drenaje y descarga a la vía | B11: ml | C11: 25 | D11: 180 | E11: =C11*D11
A12: Señalización, topellantas y numeración | B12: glb | C12: 1 | D12: 4000 | E12: =C12*D12
A13: Licencia de funcionamiento, ITSE y trámites | B13: glb | C13: 1 | D13: 3500 | E13: =C13*D13
D14: Inversión (con imprevistos y factor de escenario) | E14: =SUM(E6:E13)*(1+Supuestos!$B$6)*Supuestos!$B$22
D15: Año de inversión (opera desde el año siguiente) | E15: 0
D16: Ingreso bruto potencial S/ por mes - pesimista | E16: 1140
D17: Ingreso bruto potencial S/ por mes - base | E17: 1725
D18: Ingreso bruto potencial S/ por mes - optimista | E18: 2555
D19: Ocupación cobrada - pesimista | E19: 1
D20: Ocupación cobrada - base | E20: 1
D21: Ocupación cobrada - optimista | E21: 1
D22: Gastos fijos S/ por año (personal, energía, mantenimiento, seguro, predial) | E22: 22545.4
D23: Gastos variables (% del ingreso cobrado) | E23: 0
D24: Impuestos (% del ingreso cobrado) | E24: 0
D25: Ingreso relativo 1.er año de operación | E25: 0.6
D26: Ingreso relativo 2.º año de operación | E26: 0.85
... D31: Reposición 2: monto a precios de hoy | E31: 28600
A33: FLUJO DE CAJA (S/ nominales)
A34: Concepto / año | C34: 0 | D34: 1 | E34: 2 | F34: 3 | G34: 4 | H34: 5 | I34: 6 | J34: 7 | K34: 8 | L34: 9 | M34: 10 | N34: 11 | O34: 12 | P34: 13 | Q34: 14 | R34: 15 | S34: 16 | T34: 17 | U34: 18 | V34: 19 | W34: 20
A35: Inversión - fase 1 | C35: =IF(C$34=$E$15,-$E$14*(1+Supuestos!$B$5)^MAX($E$15-1,0),0) | D35: =IF(D$34=$E$15,-$E$14*(1+Supuestos!$B$5)^MAX($E$15-1,0),0) | E35: =IF(E$34=$E$15,-$E$14*(1+Supuestos!$B$5)^MAX($E$15-1,0),0) | F35: =IF(F$34=$E$15,-$E$14*(1+Supuestos!$B$5)^MAX($E$15-1,0),0) | G35: =IF(G$34=$E$15,-$E$14*(1+Supuestos!$B$5)^MAX($E$15-1,0),0) | H35: =IF(H$34=$E$15,-$E$14*(1+Supuestos!$B$5)^MAX($E$15-1,0),0) | I35: =IF(I$34=$E$15,-$E$14*(1+Supuestos!$B$5)^MAX($E$15-1,0),0) | J35: =IF(J$34=$E$15,-$E$14*(1+Supuestos!$B$5)^MAX($E$15-1,0),0) | ... W35: =IF(W$34=$E$15,-$E$14*(1+Supuestos!$B$5)^MAX($E$15-1,0),0)
A36: Ingresos cobrados - fase 1 | C36: =IF((C$34-$E$15)>=1,CHOOSE(Supuestos!$B$3,$E$16,$E$17,$E$18)*12*CHOOSE(Supuestos!$B$3,$E$19,$E$20,$E$21)*IF((C$34-$E$15)=1,$E$25,IF((C$34-$E$15)=2,$E$26,1))*(1+Supuestos!$B$5)^MAX(C$34-1,0),0) | D36: =IF((D$34-$E$15)>=1,CHOOSE(Supuestos!$B$3,$E$16,$E$17,$E$18)*12*CHOOSE(Supuestos!$B$3,$E$19,$E$20,$E$21)*IF((D$34-$E$15)=1,$E$25,IF((D$34-$E$15)=2,$E$26,1))*(1+Supuestos!$B$5)^MAX(D$34-1,0),0) | E36: =IF((E$34-$E$15)>=1,CHOOSE(Supuestos!$B$3,$E$16,$E$17,$E$18)*12*CHOOSE(Supuestos!$B$3,$E$19,$E$20,$E$21)*IF((E$34-$E$15)=1,$E$25,IF((E$34-$E$15)=2,$E$26,1))*(1+Supuestos!$B$5)^MAX(E$34-1,0),0) | F36: =IF((F$34-$E$15)>=1,CHOOSE(Supuestos!$B$3,$E$16,$E$17,$E$18)*12*CHOOSE(Supuestos!$B$3,$E$19,$E$20,$E$21)*IF((F$34-$E$15)=1,$E$25,IF((F$34-$E$15)=2,$E$26,1))*(1+Supuestos!$B$5)^MAX(F$34-1,0),0) | G36: =IF((G$34-$E$15)>=1,CHOOSE(Supuestos!$B$3,$E$16,$E$17,$E$18)*12*CHOOSE(Supuestos!$B$3,$E$19,$E$20,$E$21)*IF((G$34-$E$15)=1,$E$25,IF((G$34-$E$15)=2,$E$26,1))*(1+Supuestos!$B$5)^MAX(G$34-1,0),0) | H36: =IF((H$34-$E$15)>=1,CHOOSE(Supuestos!$B$3,$E$16,$E$17,$E$18)*12*CHOOSE(Supuestos!$B$3,$E$19,$E$20,$E$21)*IF((H$34-$E$15)=1,$E$25,IF((H$34-$E$15)=2,$E$26,1))*(1+Supuestos!$B$5)^MAX(H$34-1,0),0) | I36: =IF((I$34-$E$15)>=1,CHOOSE(Supuestos!$B$3,$E$16,$E$17,$E$18)*12*CHOOSE(Supuestos!$B$3,$E$19,$E$20,$E$21)*IF((I$34-$E$15)=1,$E$25,IF((I$34-$E$15)=2,$E$26,1))*(1+Supuestos!$B$5)^MAX(I$34-1,0),0) | J36: =IF((J$34-$E$15)>=1,CHOOSE(Supuestos!$B$3,$E$16,$E$17,$E$18)*12*CHOOSE(Supuestos!$B$3,$E$19,$E$20,$E$21)*IF((J$34-$E$15)=1,$E$25,IF((J$34-$E$15)=2,$E$26,1))*(1+Supuestos!$B$5)^MAX(J$34-1,0),0) | ... W36: =IF((W$34-$E$15)>=1,CHOOSE(Supuestos!$B$3,$E$16,$E$17,$E$18)*12*CHOOSE(Supuestos!$B$3,$E$19,$E$20,$E$21)*IF((W$34-$E$15)=1,$E$25,IF((W$34-$E$15)=2,$E$26,1))*(1+Supuestos!$B$5)^MAX(W$34-1,0),0)
A37: Gastos - fase 1 | C37: =IF((C$34-$E$15)>=1,-$E$22*(1+Supuestos!$B$5)^MAX(C$34-1,0)-$E$23*C36,0) | D37: =IF((D$34-$E$15)>=1,-$E$22*(1+Supuestos!$B$5)^MAX(D$34-1,0)-$E$23*D36,0) | E37: =IF((E$34-$E$15)>=1,-$E$22*(1+Supuestos!$B$5)^MAX(E$34-1,0)-$E$23*E36,0) | F37: =IF((F$34-$E$15)>=1,-$E$22*(1+Supuestos!$B$5)^MAX(F$34-1,0)-$E$23*F36,0) | G37: =IF((G$34-$E$15)>=1,-$E$22*(1+Supuestos!$B$5)^MAX(G$34-1,0)-$E$23*G36,0) | H37: =IF((H$34-$E$15)>=1,-$E$22*(1+Supuestos!$B$5)^MAX(H$34-1,0)-$E$23*H36,0) | I37: =IF((I$34-$E$15)>=1,-$E$22*(1+Supuestos!$B$5)^MAX(I$34-1,0)-$E$23*I36,0) | J37: =IF((J$34-$E$15)>=1,-$E$22*(1+Supuestos!$B$5)^MAX(J$34-1,0)-$E$23*J36,0) | ... W37: =IF((W$34-$E$15)>=1,-$E$22*(1+Supuestos!$B$5)^MAX(W$34-1,0)-$E$23*W36,0)
A38: Impuestos - fase 1 | C38: =-$E$24*C36 | D38: =-$E$24*D36 | E38: =-$E$24*E36 | F38: =-$E$24*F36 | G38: =-$E$24*G36 | H38: =-$E$24*H36 | I38: =-$E$24*I36 | J38: =-$E$24*J36 | ... W38: =-$E$24*W36
A39: Reposiciones - fase 1 | C39: =IF((C$34-$E$15)=$E$28,-$E$29*(1+Supuestos!$B$5)^MAX(C$34-1,0)*Supuestos!$B$22,0)+IF((C$34-$E$15)=$E$30,-$E$31*(1+Supuestos!$B$5)^MAX(C$34-1,0)*Supuestos!$B$22,0) | D39: =IF((D$34-$E$15)=$E$28,-$E$29*(1+Supuestos!$B$5)^MAX(D$34-1,0)*Supuestos!$B$22,0)+IF((D$34-$E$15)=$E$30,-$E$31*(1+Supuestos!$B$5)^MAX(D$34-1,0)*Supuestos!$B$22,0) | E39: =IF((E$34-$E$15)=$E$28,-$E$29*(1+Supuestos!$B$5)^MAX(E$34-1,0)*Supuestos!$B$22,0)+IF((E$34-$E$15)=$E$30,-$E$31*(1+Supuestos!$B$5)^MAX(E$34-1,0)*Supuestos!$B$22,0) | F39: =IF((F$34-$E$15)=$E$28,-$E$29*(1+Supuestos!$B$5)^MAX(F$34-1,0)*Supuestos!$B$22,0)+IF((F$34-$E$15)=$E$30,-$E$31*(1+Supuestos!$B$5)^MAX(F$34-1,0)*Supuestos!$B$22,0) | G39: =IF((G$34-$E$15)=$E$28,-$E$29*(1+Supuestos!$B$5)^MAX(G$34-1,0)*Supuestos!$B$22,0)+IF((G$34-$E$15)=$E$30,-$E$31*(1+Supuestos!$B$5)^MAX(G$34-1,0)*Supuestos!$B$22,0) | H39: =IF((H$34-$E$15)=$E$28,-$E$29*(1+Supuestos!$B$5)^MAX(H$34-1,0)*Supuestos!$B$22,0)+IF((H$34-$E$15)=$E$30,-$E$31*(1+Supuestos!$B$5)^MAX(H$34-1,0)*Supuestos!$B$22,0) | I39: =IF((I$34-$E$15)=$E$28,-$E$29*(1+Supuestos!$B$5)^MAX(I$34-1,0)*Supuestos!$B$22,0)+IF((I$34-$E$15)=$E$30,-$E$31*(1+Supuestos!$B$5)^MAX(I$34-1,0)*Supuestos!$B$22,0) | J39: =IF((J$34-$E$15)=$E$28,-$E$29*(1+Supuestos!$B$5)^MAX(J$34-1,0)*Supuestos!$B$22,0)+IF((J$34-$E$15)=$E$30,-$E$31*(1+Supuestos!$B$5)^MAX(J$34-1,0)*Supuestos!$B$22,0) | ... W39: =IF((W$34-$E$15)=$E$28,-$E$29*(1+Supuestos!$B$5)^MAX(W$34-1,0)*Supuestos!$B$22,0)+IF((W$34-$E$15)=$E$30,-$E$31*(1+Supuestos!$B$5)^MAX(W$34-1,0)*Supuestos!$B$22,0)
A40: Valor residual (año 20) - fase 1 | C40: =IF(AND(C$34=20,$E$27>1),$E$14*(1+Supuestos!$B$5)^MAX($E$15-1,0)*MAX(0,1-(20-$E$15)/$E$27),0) | D40: =IF(AND(D$34=20,$E$27>1),$E$14*(1+Supuestos!$B$5)^MAX($E$15-1,0)*MAX(0,1-(20-$E$15)/$E$27),0) | E40: =IF(AND(E$34=20,$E$27>1),$E$14*(1+Supuestos!$B$5)^MAX($E$15-1,0)*MAX(0,1-(20-$E$15)/$E$27),0) | F40: =IF(AND(F$34=20,$E$27>1),$E$14*(1+Supuestos!$B$5)^MAX($E$15-1,0)*MAX(0,1-(20-$E$15)/$E$27),0) | G40: =IF(AND(G$34=20,$E$27>1),$E$14*(1+Supuestos!$B$5)^MAX($E$15-1,0)*MAX(0,1-(20-$E$15)/$E$27),0) | H40: =IF(AND(H$34=20,$E$27>1),$E$14*(1+Supuestos!$B$5)^MAX($E$15-1,0)*MAX(0,1-(20-$E$15)/$E$27),0) | I40: =IF(AND(I$34=20,$E$27>1),$E$14*(1+Supuestos!$B$5)^MAX($E$15-1,0)*MAX(0,1-(20-$E$15)/$E$27),0) | J40: =IF(AND(J$34=20,$E$27>1),$E$14*(1+Supuestos!$B$5)^MAX($E$15-1,0)*MAX(0,1-(20-$E$15)/$E$27),0) | ... W40: =IF(AND(W$34=20,$E$27>1),$E$14*(1+Supuestos!$B$5)^MAX($E$15-1,0)*MAX(0,1-(20-$E$15)/$E$27),0)
A41: Inversión | C41: =C35 | D41: =D35 | E41: =E35 | F41: =F35 | G41: =G35 | H41: =H35 | I41: =I35 | J41: =J35 | ... W41: =W35
A42: Ingresos cobrados | C42: =C36 | D42: =D36 | E42: =E36 | F42: =F36 | G42: =G36 | H42: =H36 | I42: =I36 | J42: =J36 | ... W42: =W36
A43: Gastos | C43: =C37 | D43: =D37 | E43: =E37 | F43: =F37 | G43: =G37 | H43: =H37 | I43: =I37 | J43: =J37 | ... W43: =W37
A44: Impuestos | C44: =C38 | D44: =D38 | E44: =E38 | F44: =F38 | G44: =G38 | H44: =H38 | I44: =I38 | J44: =J38 | ... W44: =W38
A45: Reposiciones | C45: =C39 | D45: =D39 | E45: =E39 | F45: =F39 | G45: =G39 | H45: =H39 | I45: =I39 | J45: =J39 | ... W45: =W39
A46: Valor residual (año 20) | C46: =C40 | D46: =D40 | E46: =E40 | F46: =F40 | G46: =G40 | H46: =H40 | I46: =I40 | J46: =J40 | ... W46: =W40
A47: FLUJO NETO | C47: =C41+C42+C43+C44+C45+C46 | D47: =D41+D42+D43+D44+D45+D46 | E47: =E41+E42+E43+E44+E45+E46 | F47: =F41+F42+F43+F44+F45+F46 | G47: =G41+G42+G43+G44+G45+G46 | H47: =H41+H42+H43+H44+H45+H46 | I47: =I41+I42+I43+I44+I45+I46 | J47: =J41+J42+J43+J44+J45+J46 | ... W47: =W41+W42+W43+W44+W45+W46
A48: Caja acumulada (sin valor residual) | C48: =C47-C46 | D48: =C48+D47-D46 | E48: =D48+E47-E46 | F48: =E48+F47-F46 | G48: =F48+G47-G46 | H48: =G48+H47-H46 | I48: =H48+I47-I46 | J48: =I48+J47-J46 | K48: =J48+K47-K46 | ... W48: =V48+W47-W46
A49: Flujo del propietario contando el terreno (lo aporta hoy y lo recupera valorizado) | C49: =C47-Supuestos!$B$21 | D49: =D47 | E49: =E47 | F49: =F47 | G49: =G47 | H49: =H47 | I49: =I47 | J49: =J47 | K49: =K47 | ... V49: =V47 | W49: =W47+Supuestos!$B$21*(1+Supuestos!$B$23)^20
A51: Inversión total | C51: =-SUM(C41:W41)
A52: VAN al 10% | C52: =C47+NPV(Supuestos!$B$4,D47:W47)
A53: TIR | C53: =IFERROR(IRR(C47:W47),IFERROR(IRR(C47:W47,-0.05),"no aplica"))
A54: Año en que se recupera la inversión (acumulado ≥ 0) | C54: =IF(-SUM(C41:W41)=0,"sin inversión",IFERROR(INDEX(C34:W34,MATCH(TRUE,INDEX(C48:W48>=0,0),0)),"no en 20 años"))
A55: Caja neta del año 5 sin inversiones (S/ nominales) | C55: =H47-H41
A56: TIR contando el terreno | C56: =IFERROR(IRR(C49:W49),"no aplica")

Sheet C1 Esquina + cochera
A1: C1. Local de esquina + cochera de abonados
A2: Solo el local ancla de 100 m² en la esquina (estructura para 3 pisos) y la cochera del fondo; los 3 locales del jirón quedan para una etapa posterior.
A4: Fase 1: Local de esquina (100 m²)
A5: Partida | B5: Und. | C5: Cantidad | D5: P. unitario | E5: Parcial
A6: Local de esquina de 100 m² en pórticos de C.A. diseñados para 3 pisos, puertas enrollables y SS.HH. | B6: m² | C6: 100 | D6: 1500 | E6: =C6*D6
A7: Estudio de suelos, proyecto y licencia | B7: glb | C7: 1 | D7: 20000 | E7: =C7*D7
D8: Inversión (con imprevistos y factor de escenario) | E8: =SUM(E6:E7)*(1+Supuestos!$B$6)*Supuestos!$B$22
D9: Año de inversión (opera desde el año siguiente) | E9: 0
D10: Ingreso bruto potencial S/ por mes - pesimista | E10: 1000
D11: Ingreso bruto potencial S/ por mes - base | E11: 1300
D12: Ingreso bruto potencial S/ por mes - optimista | E12: 2000
D13: Ocupación cobrada - pesimista | E13: 0.7
D14: Ocupación cobrada - base | E14: 0.8
D15: Ocupación cobrada - optimista | E15: 0.9
D16: Gastos fijos S/ por año (personal, energía, mantenimiento, seguro, predial) | E16: 2500
D17: Gastos variables (% del ingreso cobrado) | E17: 0
D18: Impuestos (% del ingreso cobrado) | E18: 0.05
D19: Ingreso relativo 1.er año de operación | E19: 0.5
D20: Ingreso relativo 2.º año de operación | E20: 0.8
D21: Vida útil para valor residual (años) | E21: 50
A23: Fase 2: Cochera de abonados (fondo, descubierta)
A24: Partida | B24: Und. | C24: Cantidad | D24: P. unitario | E24: Parcial
A25: Afirmado compactado e=0.20 m con bombeo | B25: m² | C25: 540 | D25: 40 | E25: =C25*D25
A26: Drenaje del patio | B26: ml | C26: 20 | D26: 220 | E26: =C26*D26
A27: Portón telescópico automatizado de 6.5 m con 40 controles + puerta peatonal | B27: glb | C27: 1 | D27: 15500 | E27: =C27*D27
A28: Cerco de albañilería en el fondo C-D | B28: ml | C28: 30 | D28: 330 | E28: =C28*D28
A29: Iluminación LED y CCTV de 4 cámaras | B29: glb | C29: 1 | D29: 7500 | E29: =C29*D29
A30: Señalización, numeración y topellantas | B30: glb | C30: 1 | D30: 2400 | E30: =C30*D30
D31: Inversión (con imprevistos y factor de escenario) | E31: =SUM(E25:E30)*(1+Supuestos!$B$6)*Supuestos!$B$22
D32: Año de inversión (opera desde el año siguiente) | E32: 0
D33: Ingreso bruto potencial S/ por mes - pesimista | E33: 480
D34: Ingreso bruto potencial S/ por mes - base | E34: 900
D35: Ingreso bruto potencial S/ por mes - optimista | E35: 1440
D36: Ocupación cobrada - pesimista | E36: 0.6
D37: Ocupación cobrada - base | E37: 0.7
D38: Ocupación cobrada - optimista | E38: 0.8
D39: Gastos fijos S/ por año (personal, energía, mantenimiento, seguro, predial) | E39: 3200
D40: Gastos variables (% del ingreso cobrado) | E40: 0
D41: Impuestos (% del ingreso cobrado) | E41: 0
D42: Ingreso relativo 1.er año de operación | E42: 0.6
D43: Ingreso relativo 2.º año de operación | E43: 0.85
... D46: Reposición 1: monto a precios de hoy | E46: 33330
A48: FLUJO DE CAJA (S/ nominales)
A49: Concepto / año | C49: 0 | D49: 1 | E49: 2 | F49: 3 | G49: 4 | H49: 5 | I49: 6 | J49: 7 | K49: 8 | L49: 9 | M49: 10 | N49: 11 | O49: 12 | P49: 13 | Q49: 14 | R49: 15 | S49: 16 | T49: 17 | U49: 18 | V49: 19 | W49: 20
A50: Inversión - fase 1 | C50: =IF(C$49=$E$9,-$E$8*(1+Supuestos!$B$5)^MAX($E$9-1,0),0) | D50: =IF(D$49=$E$9,-$E$8*(1+Supuestos!$B$5)^MAX($E$9-1,0),0) | E50: =IF(E$49=$E$9,-$E$8*(1+Supuestos!$B$5)^MAX($E$9-1,0),0) | F50: =IF(F$49=$E$9,-$E$8*(1+Supuestos!$B$5)^MAX($E$9-1,0),0) | G50: =IF(G$49=$E$9,-$E$8*(1+Supuestos!$B$5)^MAX($E$9-1,0),0) | H50: =IF(H$49=$E$9,-$E$8*(1+Supuestos!$B$5)^MAX($E$9-1,0),0) | I50: =IF(I$49=$E$9,-$E$8*(1+Supuestos!$B$5)^MAX($E$9-1,0),0) | J50: =IF(J$49=$E$9,-$E$8*(1+Supuestos!$B$5)^MAX($E$9-1,0),0) | ... W50: =IF(W$49=$E$9,-$E$8*(1+Supuestos!$B$5)^MAX($E$9-1,0),0)
A51: Ingresos cobrados - fase 1 | C51: =IF((C$49-$E$9)>=1,CHOOSE(Supuestos!$B$3,$E$10,$E$11,$E$12)*12*CHOOSE(Supuestos!$B$3,$E$13,$E$14,$E$15)*IF((C$49-$E$9)=1,$E$19,IF((C$49-$E$9)=2,$E$20,1))*(1+Supuestos!$B$5)^MAX(C$49-1,0),0) | D51: =IF((D$49-$E$9)>=1,CHOOSE(Supuestos!$B$3,$E$10,$E$11,$E$12)*12*CHOOSE(Supuestos!$B$3,$E$13,$E$14,$E$15)*IF((D$49-$E$9)=1,$E$19,IF((D$49-$E$9)=2,$E$20,1))*(1+Supuestos!$B$5)^MAX(D$49-1,0),0) | E51: =IF((E$49-$E$9)>=1,CHOOSE(Supuestos!$B$3,$E$10,$E$11,$E$12)*12*CHOOSE(Supuestos!$B$3,$E$13,$E$14,$E$15)*IF((E$49-$E$9)=1,$E$19,IF((E$49-$E$9)=2,$E$20,1))*(1+Supuestos!$B$5)^MAX(E$49-1,0),0) | F51: =IF((F$49-$E$9)>=1,CHOOSE(Supuestos!$B$3,$E$10,$E$11,$E$12)*12*CHOOSE(Supuestos!$B$3,$E$13,$E$14,$E$15)*IF((F$49-$E$9)=1,$E$19,IF((F$49-$E$9)=2,$E$20,1))*(1+Supuestos!$B$5)^MAX(F$49-1,0),0) | G51: =IF((G$49-$E$9)>=1,CHOOSE(Supuestos!$B$3,$E$10,$E$11,$E$12)*12*CHOOSE(Supuestos!$B$3,$E$13,$E$14,$E$15)*IF((G$49-$E$9)=1,$E$19,IF((G$49-$E$9)=2,$E$20,1))*(1+Supuestos!$B$5)^MAX(G$49-1,0),0) | H51: =IF((H$49-$E$9)>=1,CHOOSE(Supuestos!$B$3,$E$10,$E$11,$E$12)*12*CHOOSE(Supuestos!$B$3,$E$13,$E$14,$E$15)*IF((H$49-$E$9)=1,$E$19,IF((H$49-$E$9)=2,$E$20,1))*(1+Supuestos!$B$5)^MAX(H$49-1,0),0) | I51: =IF((I$49-$E$9)>=1,CHOOSE(Supuestos!$B$3,$E$10,$E$11,$E$12)*12*CHOOSE(Supuestos!$B$3,$E$13,$E$14,$E$15)*IF((I$49-$E$9)=1,$E$19,IF((I$49-$E$9)=2,$E$20,1))*(1+Supuestos!$B$5)^MAX(I$49-1,0),0) | J51: =IF((J$49-$E$9)>=1,CHOOSE(Supuestos!$B$3,$E$10,$E$11,$E$12)*12*CHOOSE(Supuestos!$B$3,$E$13,$E$14,$E$15)*IF((J$49-$E$9)=1,$E$19,IF((J$49-$E$9)=2,$E$20,1))*(1+Supuestos!$B$5)^MAX(J$49-1,0),0) | ... W51: =IF((W$49-$E$9)>=1,CHOOSE(Supuestos!$B$3,$E$10,$E$11,$E$12)*12*CHOOSE(Supuestos!$B$3,$E$13,$E$14,$E$15)*IF((W$49-$E$9)=1,$E$19,IF((W$49-$E$9)=2,$E$20,1))*(1+Supuestos!$B$5)^MAX(W$49-1,0),0)
A52: Gastos - fase 1 | C52: =IF((C$49-$E$9)>=1,-$E$16*(1+Supuestos!$B$5)^MAX(C$49-1,0)-$E$17*C51,0) | D52: =IF((D$49-$E$9)>=1,-$E$16*(1+Supuestos!$B$5)^MAX(D$49-1,0)-$E$17*D51,0) | E52: =IF((E$49-$E$9)>=1,-$E$16*(1+Supuestos!$B$5)^MAX(E$49-1,0)-$E$17*E51,0) | F52: =IF((F$49-$E$9)>=1,-$E$16*(1+Supuestos!$B$5)^MAX(F$49-1,0)-$E$17*F51,0) | G52: =IF((G$49-$E$9)>=1,-$E$16*(1+Supuestos!$B$5)^MAX(G$49-1,0)-$E$17*G51,0) | H52: =IF((H$49-$E$9)>=1,-$E$16*(1+Supuestos!$B$5)^MAX(H$49-1,0)-$E$17*H51,0) | I52: =IF((I$49-$E$9)>=1,-$E$16*(1+Supuestos!$B$5)^MAX(I$49-1,0)-$E$17*I51,0) | J52: =IF((J$49-$E$9)>=1,-$E$16*(1+Supuestos!$B$5)^MAX(J$49-1,0)-$E$17*J51,0) | ... W52: =IF((W$49-$E$9)>=1,-$E$16*(1+Supuestos!$B$5)^MAX(W$49-1,0)-$E$17*W51,0)
A53: Impuestos - fase 1 | C53: =-$E$18*C51 | D53: =-$E$18*D51 | E53: =-$E$18*E51 | F53: =-$E$18*F51 | G53: =-$E$18*G51 | H53: =-$E$18*H51 | I53: =-$E$18*I51 | J53: =-$E$18*J51 | ... W53: =-$E$18*W51
A54: Reposiciones - fase 1 | C54: =0 | D54: =0 | E54: =0 | F54: =0 | G54: =0 | H54: =0 | I54: =0 | J54: =0 | ... W54: =0
A55: Valor residual (año 20) - fase 1 | C55: =IF(AND(C$49=20,$E$21>1),$E$8*(1+Supuestos!$B$5)^MAX($E$9-1,0)*MAX(0,1-(20-$E$9)/$E$21),0) | D55: =IF(AND(D$49=20,$E$21>1),$E$8*(1+Supuestos!$B$5)^MAX($E$9-1,0)*MAX(0,1-(20-$E$9)/$E$21),0) | E55: =IF(AND(E$49=20,$E$21>1),$E$8*(1+Supuestos!$B$5)^MAX($E$9-1,0)*MAX(0,1-(20-$E$9)/$E$21),0) | F55: =IF(AND(F$49=20,$E$21>1),$E$8*(1+Supuestos!$B$5)^MAX($E$9-1,0)*MAX(0,1-(20-$E$9)/$E$21),0) | G55: =IF(AND(G$49=20,$E$21>1),$E$8*(1+Supuestos!$B$5)^MAX($E$9-1,0)*MAX(0,1-(20-$E$9)/$E$21),0) | H55: =IF(AND(H$49=20,$E$21>1),$E$8*(1+Supuestos!$B$5)^MAX($E$9-1,0)*MAX(0,1-(20-$E$9)/$E$21),0) | I55: =IF(AND(I$49=20,$E$21>1),$E$8*(1+Supuestos!$B$5)^MAX($E$9-1,0)*MAX(0,1-(20-$E$9)/$E$21),0) | J55: =IF(AND(J$49=20,$E$21>1),$E$8*(1+Supuestos!$B$5)^MAX($E$9-1,0)*MAX(0,1-(20-$E$9)/$E$21),0) | ... W55: =IF(AND(W$49=20,$E$21>1),$E$8*(1+Supuestos!$B$5)^MAX($E$9-1,0)*MAX(0,1-(20-$E$9)/$E$21),0)
A56: Inversión - fase 2 | C56: =IF(C$49=$E$32,-$E$31*(1+Supuestos!$B$5)^MAX($E$32-1,0),0) | D56: =IF(D$49=$E$32,-$E$31*(1+Supuestos!$B$5)^MAX($E$32-1,0),0) | E56: =IF(E$49=$E$32,-$E$31*(1+Supuestos!$B$5)^MAX($E$32-1,0),0) | F56: =IF(F$49=$E$32,-$E$31*(1+Supuestos!$B$5)^MAX($E$32-1,0),0) | G56: =IF(G$49=$E$32,-$E$31*(1+Supuestos!$B$5)^MAX($E$32-1,0),0) | H56: =IF(H$49=$E$32,-$E$31*(1+Supuestos!$B$5)^MAX($E$32-1,0),0) | I56: =IF(I$49=$E$32,-$E$31*(1+Supuestos!$B$5)^MAX($E$32-1,0),0) | J56: =IF(J$49=$E$32,-$E$31*(1+Supuestos!$B$5)^MAX($E$32-1,0),0) | ... W56: =IF(W$49=$E$32,-$E$31*(1+Supuestos!$B$5)^MAX($E$32-1,0),0)
A57: Ingresos cobrados - fase 2 | C57: =IF((C$49-$E$32)>=1,CHOOSE(Supuestos!$B$3,$E$33,$E$34,$E$35)*12*CHOOSE(Supuestos!$B$3,$E$36,$E$37,$E$38)*IF((C$49-$E$32)=1,$E$42,IF((C$49-$E$32)=2,$E$43,1))*(1+Supuestos!$B$5)^MAX(C$49-1,0),0) | D57: =IF((D$49-$E$32)>=1,CHOOSE(Supuestos!$B$3,$E$33,$E$34,$E$35)*12*CHOOSE(Supuestos!$B$3,$E$36,$E$37,$E$38)*IF((D$49-$E$32)=1,$E$42,IF((D$49-$E$32)=2,$E$43,1))*(1+Supuestos!$B$5)^MAX(D$49-1,0),0) | E57: =IF((E$49-$E$32)>=1,CHOOSE(Supuestos!$B$3,$E$33,$E$34,$E$35)*12*CHOOSE(Supuestos!$B$3,$E$36,$E$37,$E$38)*IF((E$49-$E$32)=1,$E$42,IF((E$49-$E$32)=2,$E$43,1))*(1+Supuestos!$B$5)^MAX(E$49-1,0),0) | F57: =IF((F$49-$E$32)>=1,CHOOSE(Supuestos!$B$3,$E$33,$E$34,$E$35)*12*CHOOSE(Supuestos!$B$3,$E$36,$E$37,$E$38)*IF((F$49-$E$32)=1,$E$42,IF((F$49-$E$32)=2,$E$43,1))*(1+Supuestos!$B$5)^MAX(F$49-1,0),0) | G57: =IF((G$49-$E$32)>=1,CHOOSE(Supuestos!$B$3,$E$33,$E$34,$E$35)*12*CHOOSE(Supuestos!$B$3,$E$36,$E$37,$E$38)*IF((G$49-$E$32)=1,$E$42,IF((G$49-$E$32)=2,$E$43,1))*(1+Supuestos!$B$5)^MAX(G$49-1,0),0) | H57: =IF((H$49-$E$32)>=1,CHOOSE(Supuestos!$B$3,$E$33,$E$34,$E$35)*12*CHOOSE(Supuestos!$B$3,$E$36,$E$37,$E$38)*IF((H$49-$E$32)=1,$E$42,IF((H$49-$E$32)=2,$E$43,1))*(1+Supuestos!$B$5)^MAX(H$49-1,0),0) | I57: =IF((I$49-$E$32)>=1,CHOOSE(Supuestos!$B$3,$E$33,$E$34,$E$35)*12*CHOOSE(Supuestos!$B$3,$E$36,$E$37,$E$38)*IF((I$49-$E$32)=1,$E$42,IF((I$49-$E$32)=2,$E$43,1))*(1+Supuestos!$B$5)^MAX(I$49-1,0),0) | J57: =IF((J$49-$E$32)>=1,CHOOSE(Supuestos!$B$3,$E$33,$E$34,$E$35)*12*CHOOSE(Supuestos!$B$3,$E$36,$E$37,$E$38)*IF((J$49-$E$32)=1,$E$42,IF((J$49-$E$32)=2,$E$43,1))*(1+Supuestos!$B$5)^MAX(J$49-1,0),0) | ... W57: =IF((W$49-$E$32)>=1,CHOOSE(Supuestos!$B$3,$E$33,$E$34,$E$35)*12*CHOOSE(Supuestos!$B$3,$E$36,$E$37,$E$38)*IF((W$49-$E$32)=1,$E$42,IF((W$49-$E$32)=2,$E$43,1))*(1+Supuestos!$B$5)^MAX(W$49-1,0),0)
A58: Gastos - fase 2 | C58: =IF((C$49-$E$32)>=1,-$E$39*(1+Supuestos!$B$5)^MAX(C$49-1,0)-$E$40*C57,0) | D58: =IF((D$49-$E$32)>=1,-$E$39*(1+Supuestos!$B$5)^MAX(D$49-1,0)-$E$40*D57,0) | E58: =IF((E$49-$E$32)>=1,-$E$39*(1+Supuestos!$B$5)^MAX(E$49-1,0)-$E$40*E57,0) | F58: =IF((F$49-$E$32)>=1,-$E$39*(1+Supuestos!$B$5)^MAX(F$49-1,0)-$E$40*F57,0) | G58: =IF((G$49-$E$32)>=1,-$E$39*(1+Supuestos!$B$5)^MAX(G$49-1,0)-$E$40*G57,0) | H58: =IF((H$49-$E$32)>=1,-$E$39*(1+Supuestos!$B$5)^MAX(H$49-1,0)-$E$40*H57,0) | I58: =IF((I$49-$E$32)>=1,-$E$39*(1+Supuestos!$B$5)^MAX(I$49-1,0)-$E$40*I57,0) | J58: =IF((J$49-$E$32)>=1,-$E$39*(1+Supuestos!$B$5)^MAX(J$49-1,0)-$E$40*J57,0) | ... W58: =IF((W$49-$E$32)>=1,-$E$39*(1+Supuestos!$B$5)^MAX(W$49-1,0)-$E$40*W57,0)
A59: Impuestos - fase 2 | C59: =-$E$41*C57 | D59: =-$E$41*D57 | E59: =-$E$41*E57 | F59: =-$E$41*F57 | G59: =-$E$41*G57 | H59: =-$E$41*H57 | I59: =-$E$41*I57 | J59: =-$E$41*J57 | ... W59: =-$E$41*W57
A60: Reposiciones - fase 2 | C60: =IF((C$49-$E$32)=$E$45,-$E$46*(1+Supuestos!$B$5)^MAX(C$49-1,0)*Supuestos!$B$22,0) | D60: =IF((D$49-$E$32)=$E$45,-$E$46*(1+Supuestos!$B$5)^MAX(D$49-1,0)*Supuestos!$B$22,0) | E60: =IF((E$49-$E$32)=$E$45,-$E$46*(1+Supuestos!$B$5)^MAX(E$49-1,0)*Supuestos!$B$22,0) | F60: =IF((F$49-$E$32)=$E$45,-$E$46*(1+Supuestos!$B$5)^MAX(F$49-1,0)*Supuestos!$B$22,0) | G60: =IF((G$49-$E$32)=$E$45,-$E$46*(1+Supuestos!$B$5)^MAX(G$49-1,0)*Supuestos!$B$22,0) | H60: =IF((H$49-$E$32)=$E$45,-$E$46*(1+Supuestos!$B$5)^MAX(H$49-1,0)*Supuestos!$B$22,0) | I60: =IF((I$49-$E$32)=$E$45,-$E$46*(1+Supuestos!$B$5)^MAX(I$49-1,0)*Supuestos!$B$22,0) | J60: =IF((J$49-$E$32)=$E$45,-$E$46*(1+Supuestos!$B$5)^MAX(J$49-1,0)*Supuestos!$B$22,0) | ... W60: =IF((W$49-$E$32)=$E$45,-$E$46*(1+Supuestos!$B$5)^MAX(W$49-1,0)*Supuestos!$B$22,0)
A61: Valor residual (año 20) - fase 2 | C61: =IF(AND(C$49=20,$E$44>1),$E$31*(1+Supuestos!$B$5)^MAX($E$32-1,0)*MAX(0,1-(20-$E$32)/$E$44),0) | D61: =IF(AND(D$49=20,$E$44>1),$E$31*(1+Supuestos!$B$5)^MAX($E$32-1,0)*MAX(0,1-(20-$E$32)/$E$44),0) | E61: =IF(AND(E$49=20,$E$44>1),$E$31*(1+Supuestos!$B$5)^MAX($E$32-1,0)*MAX(0,1-(20-$E$32)/$E$44),0) | F61: =IF(AND(F$49=20,$E$44>1),$E$31*(1+Supuestos!$B$5)^MAX($E$32-1,0)*MAX(0,1-(20-$E$32)/$E$44),0) | G61: =IF(AND(G$49=20,$E$44>1),$E$31*(1+Supuestos!$B$5)^MAX($E$32-1,0)*MAX(0,1-(20-$E$32)/$E$44),0) | H61: =IF(AND(H$49=20,$E$44>1),$E$31*(1+Supuestos!$B$5)^MAX($E$32-1,0)*MAX(0,1-(20-$E$32)/$E$44),0) | I61: =IF(AND(I$49=20,$E$44>1),$E$31*(1+Supuestos!$B$5)^MAX($E$32-1,0)*MAX(0,1-(20-$E$32)/$E$44),0) | J61: =IF(AND(J$49=20,$E$44>1),$E$31*(1+Supuestos!$B$5)^MAX($E$32-1,0)*MAX(0,1-(20-$E$32)/$E$44),0) | ... W61: =IF(AND(W$49=20,$E$44>1),$E$31*(1+Supuestos!$B$5)^MAX($E$32-1,0)*MAX(0,1-(20-$E$32)/$E$44),0)
A62: Inversión | C62: =C50+C56 | D62: =D50+D56 | E62: =E50+E56 | F62: =F50+F56 | G62: =G50+G56 | H62: =H50+H56 | I62: =I50+I56 | J62: =J50+J56 | ... W62: =W50+W56
A63: Ingresos cobrados | C63: =C51+C57 | D63: =D51+D57 | E63: =E51+E57 | F63: =F51+F57 | G63: =G51+G57 | H63: =H51+H57 | I63: =I51+I57 | J63: =J51+J57 | ... W63: =W51+W57
A64: Gastos | C64: =C52+C58 | D64: =D52+D58 | E64: =E52+E58 | F64: =F52+F58 | G64: =G52+G58 | H64: =H52+H58 | I64: =I52+I58 | J64: =J52+J58 | ... W64: =W52+W58
A65: Impuestos | C65: =C53+C59 | D65: =D53+D59 | E65: =E53+E59 | F65: =F53+F59 | G65: =G53+G59 | H65: =H53+H59 | I65: =I53+I59 | J65: =J53+J59 | ... W65: =W53+W59
A66: Reposiciones | C66: =C54+C60 | D66: =D54+D60 | E66: =E54+E60 | F66: =F54+F60 | G66: =G54+G60 | H66: =H54+H60 | I66: =I54+I60 | J66: =J54+J60 | ... W66: =W54+W60
A67: Valor residual (año 20) | C67: =C55+C61 | D67: =D55+D61 | E67: =E55+E61 | F67: =F55+F61 | G67: =G55+G61 | H67: =H55+H61 | I67: =I55+I61 | J67: =J55+J61 | ... W67: =W55+W61
A68: FLUJO NETO | C68: =C62+C63+C64+C65+C66+C67 | D68: =D62+D63+D64+D65+D66+D67 | E68: =E62+E63+E64+E65+E66+E67 | F68: =F62+F63+F64+F65+F66+F67 | G68: =G62+G63+G64+G65+G66+G67 | H68: =H62+H63+H64+H65+H66+H67 | I68: =I62+I63+I64+I65+I66+I67 | J68: =J62+J63+J64+J65+J66+J67 | ... W68: =W62+W63+W64+W65+W66+W67
A69: Caja acumulada (sin valor residual) | C69: =C68-C67 | D69: =C69+D68-D67 | E69: =D69+E68-E67 | F69: =E69+F68-F67 | G69: =F69+G68-G67 | H69: =G69+H68-H67 | I69: =H69+I68-I67 | J69: =I69+J68-J67 | K69: =J69+K68-K67 | ... W69: =V69+W68-W67
A70: Flujo del propietario contando el terreno (lo aporta hoy y lo recupera valorizado) | C70: =C68-Supuestos!$B$21 | D70: =D68 | E70: =E68 | F70: =F68 | G70: =G68 | H70: =H68 | I70: =I68 | J70: =J68 | K70: =K68 | ... V70: =V68 | W70: =W68+Supuestos!$B$21*(1+Supuestos!$B$23)^20
A72: Inversión total | C72: =-SUM(C62:W62)
A73: VAN al 10% | C73: =C68+NPV(Supuestos!$B$4,D68:W68)
A74: TIR | C74: =IFERROR(IRR(C68:W68),IFERROR(IRR(C68:W68,-0.05),"no aplica"))
A75: Año en que se recupera la inversión (acumulado ≥ 0) | C75: =IF(-SUM(C62:W62)=0,"sin inversión",IFERROR(INDEX(C49:W49,MATCH(TRUE,INDEX(C69:W69>=0,0),0)),"no en 20 años"))
A76: Caja neta del año 5 sin inversiones (S/ nominales) | C76: =H68-H62
A77: TIR contando el terreno | C77: =IFERROR(IRR(C70:W70),"no aplica")

Sheet K Terminal de vans
A1: K. Terminal o paradero de vans y colectivos
A2: Patio de maniobras de concreto, andenes techados, 4 boleterías, sala de espera y SS.HH.
A4: Fase 1: Terminal de vans
A5: Partida | B5: Und. | C5: Cantidad | D5: P. unitario | E5: Parcial
A6: Pavimento de concreto para patio de maniobras | B6: m² | C6: 480 | D6: 130 | E6: =C6*D6
A7: Techado metálico de andenes | B7: m² | C7: 150 | D7: 400 | E7: =C7*D7
A8: Sala de espera, 4 boleterías y SS.HH. | B8: m² | C8: 120 | D8: 1300 | E8: =C8*D8
A9: Cerco, portones y señalización | B9: glb | C9: 1 | D9: 20000 | E9: =C9*D9
A10: Estudio de impacto vial, habilitación técnica MTC y licencias (Modalidad D) | B10: glb | C10: 1 | D10: 25000 | E10: =C10*D10
D11: Inversión (con imprevistos y factor de escenario) | E11: =SUM(E6:E10)*(1+Supuestos!$B$6)*Supuestos!$B$22
D12: Año de inversión (opera desde el año siguiente) | E12: 0
D13: Ingreso bruto potencial S/ por mes - pesimista | E13: 2680
D14: Ingreso bruto potencial S/ por mes - base | E14: 4800
D15: Ingreso bruto potencial S/ por mes - optimista | E15: 7400
D16: Ocupación cobrada - pesimista | E16: 1
D17: Ocupación cobrada - base | E17: 1
D18: Ocupación cobrada - optimista | E18: 1
D19: Gastos fijos S/ por año (personal, energía, mantenimiento, seguro, predial) | E19: 33945.4
D20: Gastos variables (% del ingreso cobrado) | E20: 0
D21: Impuestos (% del ingreso cobrado) | E21: 0.03
D22: Ingreso relativo 1.er año de operación | E22: 0.6
D23: Ingreso relativo 2.º año de operación | E23: 0.85
D24: Vida útil para valor residual (años) | E24: 40
A26: FLUJO DE CAJA (S/ nominales)
A27: Concepto / año | C27: 0 | D27: 1 | E27: 2 | F27: 3 | G27: 4 | H27: 5 | I27: 6 | J27: 7 | K27: 8 | L27: 9 | M27: 10 | N27: 11 | O27: 12 | P27: 13 | Q27: 14 | R27: 15 | S27: 16 | T27: 17 | U27: 18 | V27: 19 | W27: 20
A28: Inversión - fase 1 | C28: =IF(C$27=$E$12,-$E$11*(1+Supuestos!$B$5)^MAX($E$12-1,0),0) | D28: =IF(D$27=$E$12,-$E$11*(1+Supuestos!$B$5)^MAX($E$12-1,0),0) | E28: =IF(E$27=$E$12,-$E$11*(1+Supuestos!$B$5)^MAX($E$12-1,0),0) | F28: =IF(F$27=$E$12,-$E$11*(1+Supuestos!$B$5)^MAX($E$12-1,0),0) | G28: =IF(G$27=$E$12,-$E$11*(1+Supuestos!$B$5)^MAX($E$12-1,0),0) | H28: =IF(H$27=$E$12,-$E$11*(1+Supuestos!$B$5)^MAX($E$12-1,0),0) | I28: =IF(I$27=$E$12,-$E$11*(1+Supuestos!$B$5)^MAX($E$12-1,0),0) | J28: =IF(J$27=$E$12,-$E$11*(1+Supuestos!$B$5)^MAX($E$12-1,0),0) | ... W28: =IF(W$27=$E$12,-$E$11*(1+Supuestos!$B$5)^MAX($E$12-1,0),0)
A29: Ingresos cobrados - fase 1 | C29: =IF((C$27-$E$12)>=1,CHOOSE(Supuestos!$B$3,$E$13,$E$14,$E$15)*12*CHOOSE(Supuestos!$B$3,$E$16,$E$17,$E$18)*IF((C$27-$E$12)=1,$E$22,IF((C$27-$E$12)=2,$E$23,1))*(1+Supuestos!$B$5)^MAX(C$27-1,0),0) | D29: =IF((D$27-$E$12)>=1,CHOOSE(Supuestos!$B$3,$E$13,$E$14,$E$15)*12*CHOOSE(Supuestos!$B$3,$E$16,$E$17,$E$18)*IF((D$27-$E$12)=1,$E$22,IF((D$27-$E$12)=2,$E$23,1))*(1+Supuestos!$B$5)^MAX(D$27-1,0),0) | E29: =IF((E$27-$E$12)>=1,CHOOSE(Supuestos!$B$3,$E$13,$E$14,$E$15)*12*CHOOSE(Supuestos!$B$3,$E$16,$E$17,$E$18)*IF((E$27-$E$12)=1,$E$22,IF((E$27-$E$12)=2,$E$23,1))*(1+Supuestos!$B$5)^MAX(E$27-1,0),0) | F29: =IF((F$27-$E$12)>=1,CHOOSE(Supuestos!$B$3,$E$13,$E$14,$E$15)*12*CHOOSE(Supuestos!$B$3,$E$16,$E$17,$E$18)*IF((F$27-$E$12)=1,$E$22,IF((F$27-$E$12)=2,$E$23,1))*(1+Supuestos!$B$5)^MAX(F$27-1,0),0) | G29: =IF((G$27-$E$12)>=1,CHOOSE(Supuestos!$B$3,$E$13,$E$14,$E$15)*12*CHOOSE(Supuestos!$B$3,$E$16,$E$17,$E$18)*IF((G$27-$E$12)=1,$E$22,IF((G$27-$E$12)=2,$E$23,1))*(1+Supuestos!$B$5)^MAX(G$27-1,0),0) | H29: =IF((H$27-$E$12)>=1,CHOOSE(Supuestos!$B$3,$E$13,$E$14,$E$15)*12*CHOOSE(Supuestos!$B$3,$E$16,$E$17,$E$18)*IF((H$27-$E$12)=1,$E$22,IF((H$27-$E$12)=2,$E$23,1))*(1+Supuestos!$B$5)^MAX(H$27-1,0),0) | I29: =IF((I$27-$E$12)>=1,CHOOSE(Supuestos!$B$3,$E$13,$E$14,$E$15)*12*CHOOSE(Supuestos!$B$3,$E$16,$E$17,$E$18)*IF((I$27-$E$12)=1,$E$22,IF((I$27-$E$12)=2,$E$23,1))*(1+Supuestos!$B$5)^MAX(I$27-1,0),0) | J29: =IF((J$27-$E$12)>=1,CHOOSE(Supuestos!$B$3,$E$13,$E$14,$E$15)*12*CHOOSE(Supuestos!$B$3,$E$16,$E$17,$E$18)*IF((J$27-$E$12)=1,$E$22,IF((J$27-$E$12)=2,$E$23,1))*(1+Supuestos!$B$5)^MAX(J$27-1,0),0) | ... W29: =IF((W$27-$E$12)>=1,CHOOSE(Supuestos!$B$3,$E$13,$E$14,$E$15)*12*CHOOSE(Supuestos!$B$3,$E$16,$E$17,$E$18)*IF((W$27-$E$12)=1,$E$22,IF((W$27-$E$12)=2,$E$23,1))*(1+Supuestos!$B$5)^MAX(W$27-1,0),0)
A30: Gastos - fase 1 | C30: =IF((C$27-$E$12)>=1,-$E$19*(1+Supuestos!$B$5)^MAX(C$27-1,0)-$E$20*C29,0) | D30: =IF((D$27-$E$12)>=1,-$E$19*(1+Supuestos!$B$5)^MAX(D$27-1,0)-$E$20*D29,0) | E30: =IF((E$27-$E$12)>=1,-$E$19*(1+Supuestos!$B$5)^MAX(E$27-1,0)-$E$20*E29,0) | F30: =IF((F$27-$E$12)>=1,-$E$19*(1+Supuestos!$B$5)^MAX(F$27-1,0)-$E$20*F29,0) | G30: =IF((G$27-$E$12)>=1,-$E$19*(1+Supuestos!$B$5)^MAX(G$27-1,0)-$E$20*G29,0) | H30: =IF((H$27-$E$12)>=1,-$E$19*(1+Supuestos!$B$5)^MAX(H$27-1,0)-$E$20*H29,0) | I30: =IF((I$27-$E$12)>=1,-$E$19*(1+Supuestos!$B$5)^MAX(I$27-1,0)-$E$20*I29,0) | J30: =IF((J$27-$E$12)>=1,-$E$19*(1+Supuestos!$B$5)^MAX(J$27-1,0)-$E$20*J29,0) | ... W30: =IF((W$27-$E$12)>=1,-$E$19*(1+Supuestos!$B$5)^MAX(W$27-1,0)-$E$20*W29,0)
A31: Impuestos - fase 1 | C31: =-$E$21*C29 | D31: =-$E$21*D29 | E31: =-$E$21*E29 | F31: =-$E$21*F29 | G31: =-$E$21*G29 | H31: =-$E$21*H29 | I31: =-$E$21*I29 | J31: =-$E$21*J29 | ... W31: =-$E$21*W29
A32: Reposiciones - fase 1 | C32: =0 | D32: =0 | E32: =0 | F32: =0 | G32: =0 | H32: =0 | I32: =0 | J32: =0 | ... W32: =0
A33: Valor residual (año 20) - fase 1 | C33: =IF(AND(C$27=20,$E$24>1),$E$11*(1+Supuestos!$B$5)^MAX($E$12-1,0)*MAX(0,1-(20-$E$12)/$E$24),0) | D33: =IF(AND(D$27=20,$E$24>1),$E$11*(1+Supuestos!$B$5)^MAX($E$12-1,0)*MAX(0,1-(20-$E$12)/$E$24),0) | E33: =IF(AND(E$27=20,$E$24>1),$E$11*(1+Supuestos!$B$5)^MAX($E$12-1,0)*MAX(0,1-(20-$E$12)/$E$24),0) | F33: =IF(AND(F$27=20,$E$24>1),$E$11*(1+Supuestos!$B$5)^MAX($E$12-1,0)*MAX(0,1-(20-$E$12)/$E$24),0) | G33: =IF(AND(G$27=20,$E$24>1),$E$11*(1+Supuestos!$B$5)^MAX($E$12-1,0)*MAX(0,1-(20-$E$12)/$E$24),0) | H33: =IF(AND(H$27=20,$E$24>1),$E$11*(1+Supuestos!$B$5)^MAX($E$12-1,0)*MAX(0,1-(20-$E$12)/$E$24),0) | I33: =IF(AND(I$27=20,$E$24>1),$E$11*(1+Supuestos!$B$5)^MAX($E$12-1,0)*MAX(0,1-(20-$E$12)/$E$24),0) | J33: =IF(AND(J$27=20,$E$24>1),$E$11*(1+Supuestos!$B$5)^MAX($E$12-1,0)*MAX(0,1-(20-$E$12)/$E$24),0) | ... W33: =IF(AND(W$27=20,$E$24>1),$E$11*(1+Supuestos!$B$5)^MAX($E$12-1,0)*MAX(0,1-(20-$E$12)/$E$24),0)
A34: Inversión | C34: =C28 | D34: =D28 | E34: =E28 | F34: =F28 | G34: =G28 | H34: =H28 | I34: =I28 | J34: =J28 | ... W34: =W28
A35: Ingresos cobrados | C35: =C29 | D35: =D29 | E35: =E29 | F35: =F29 | G35: =G29 | H35: =H29 | I35: =I29 | J35: =J29 | ... W35: =W29
A36: Gastos | C36: =C30 | D36: =D30 | E36: =E30 | F36: =F30 | G36: =G30 | H36: =H30 | I36: =I30 | J36: =J30 | ... W36: =W30
A37: Impuestos | C37: =C31 | D37: =D31 | E37: =E31 | F37: =F31 | G37: =G31 | H37: =H31 | I37: =I31 | J37: =J31 | ... W37: =W31
A38: Reposiciones | C38: =C32 | D38: =D32 | E38: =E32 | F38: =F32 | G38: =G32 | H38: =H32 | I38: =I32 | J38: =J32 | ... W38: =W32
A39: Valor residual (año 20) | C39: =C33 | D39: =D33 | E39: =E33 | F39: =F33 | G39: =G33 | H39: =H33 | I39: =I33 | J39: =J33 | ... W39: =W33
A40: FLUJO NETO | C40: =C34+C35+C36+C37+C38+C39 | D40: =D34+D35+D36+D37+D38+D39 | E40: =E34+E35+E36+E37+E38+E39 | F40: =F34+F35+F36+F37+F38+F39 | G40: =G34+G35+G36+G37+G38+G39 | H40: =H34+H35+H36+H37+H38+H39 | I40: =I34+I35+I36+I37+I38+I39 | J40: =J34+J35+J36+J37+J38+J39 | ... W40: =W34+W35+W36+W37+W38+W39
A41: Caja acumulada (sin valor residual) | C41: =C40-C39 | D41: =C41+D40-D39 | E41: =D41+E40-E39 | F41: =E41+F40-F39 | G41: =F41+G40-G39 | H41: =G41+H40-H39 | I41: =H41+I40-I39 | J41: =I41+J40-J39 | K41: =J41+K40-K39 | ... W41: =V41+W40-W39
A42: Flujo del propietario contando el terreno (lo aporta hoy y lo recupera valorizado) | C42: =C40-Supuestos!$B$21 | D42: =D40 | E42: =E40 | F42: =F40 | G42: =G40 | H42: =H40 | I42: =I40 | J42: =J40 | K42: =K40 | ... V42: =V40 | W42: =W40+Supuestos!$B$21*(1+Supuestos!$B$23)^20
A44: Inversión total | C44: =-SUM(C34:W34)
A45: VAN al 10% | C45: =C40+NPV(Supuestos!$B$4,D40:W40)
A46: TIR | C46: =IFERROR(IRR(C40:W40),IFERROR(IRR(C40:W40,-0.05),"no aplica"))
A47: Año en que se recupera la inversión (acumulado ≥ 0) | C47: =IF(-SUM(C34:W34)=0,"sin inversión",IFERROR(INDEX(C27:W27,MATCH(TRUE,INDEX(C41:W41>=0,0),0)),"no en 20 años"))
A48: Caja neta del año 5 sin inversiones (S/ nominales) | C48: =H40-H34
A49: TIR contando el terreno | C49: =IFERROR(IRR(C42:W42),"no aplica")

Sheet C Locales + cochera
A1: C. Locales en la esquina y el jirón + cochera de abonados
A2: Franja comercial de 8 m de fondo sobre el jirón y la esquina (ancla de 100 m² + 3 locales de 39-48 m²), estructura para 2 pisos más y 12 plazas de abonados atrás (las otras 6 quedan para los locales), con ingreso y salida por la calle lateral.
A4: Fase 1: Local de esquina (100 m²)
A5: Partida | B5: Und. | C5: Cantidad | D5: P. unitario | E5: Parcial
A6: Local de esquina de 100 m² en pórticos de C.A. diseñados para 3 pisos, puertas enrollables y SS.HH. | B6: m² | C6: 100 | D6: 1500 | E6: =C6*D6
A7: Estudio de suelos, proyecto y licencia | B7: glb | C7: 1 | D7: 20000 | E7: =C7*D7
D8: Inversión (con imprevistos y factor de escenario) | E8: =SUM(E6:E7)*(1+Supuestos!$B$6)*Supuestos!$B$22
D9: Año de inversión (opera desde el año siguiente) | E9: 0
D10: Ingreso bruto potencial S/ por mes - pesimista | E10: 1000
D11: Ingreso bruto potencial S/ por mes - base | E11: 1300
D12: Ingreso bruto potencial S/ por mes - optimista | E12: 2000
D13: Ocupación cobrada - pesimista | E13: 0.7
D14: Ocupación cobrada - base | E14: 0.8
D15: Ocupación cobrada - optimista | E15: 0.9
D16: Gastos fijos S/ por año (personal, energía, mantenimiento, seguro, predial) | E16: 2500
D17: Gastos variables (% del ingreso cobrado) | E17: 0
D18: Impuestos (% del ingreso cobrado) | E18: 0.05
D19: Ingreso relativo 1.er año de operación | E19: 0.5
D20: Ingreso relativo 2.º año de operación | E20: 0.8
D21: Vida útil para valor residual (años) | E21: 50
A23: Fase 2: 3 locales al jirón + núcleo de escalera
A24: Partida | B24: Und. | C24: Cantidad | D24: P. unitario | E24: Parcial
A25: 3 locales de 39-48 m² (134.7 m²) y núcleo de escalera, SS.HH. y depósito de 26 m² junto a B, en pórticos de C.A. diseñados para 3 pisos | B25: m² | C25: 160.6 | D25: 1500 | E25: =C25*D25
A26: Ampliación del proyecto y licencia | B26: glb | C26: 1 | D26: 12000 | E26: =C26*D26
D27: Inversión (con imprevistos y factor de escenario) | E27: =SUM(E25:E26)*(1+Supuestos!$B$6)*Supuestos!$B$22
D28: Año de inversión (opera desde el año siguiente) | E28: 0
D29: Ingreso bruto potencial S/ por mes - pesimista | E29: 1616.4
D30: Ingreso bruto potencial S/ por mes - base | E30: 2020.5
D31: Ingreso bruto potencial S/ por mes - optimista | E31: 2424.6
D32: Ocupación cobrada - pesimista | E32: 0.7
D33: Ocupación cobrada - base | E33: 0.8
D34: Ocupación cobrada - optimista | E34: 0.9
D35: Gastos fijos S/ por año (personal, energía, mantenimiento, seguro, predial) | E35: 3600
D36: Gastos variables (% del ingreso cobrado) | E36: 0
D37: Impuestos (% del ingreso cobrado) | E37: 0.05
D38: Ingreso relativo 1.er año de operación | E38: 0.5
D39: Ingreso relativo 2.º año de operación | E39: 0.8
D40: Vida útil para valor residual (años) | E40: 50
A42: Fase 3: Cochera de abonados (fondo, descubierta)
A43: Partida | B43: Und. | C43: Cantidad | D43: P. unitario | E43: Parcial
A44: Afirmado compactado e=0.20 m con bombeo | B44: m² | C44: 540 | D44: 40 | E44: =C44*D44
A45: Drenaje del patio | B45: ml | C45: 20 | D45: 220 | E45: =C45*D45
A46: Portón telescópico automatizado de 6.5 m con 40 controles + puerta peatonal | B46: glb | C46: 1 | D46: 15500 | E46: =C46*D46
A47: Cerco de albañilería en el fondo C-D | B47: ml | C47: 30 | D47: 330 | E47: =C47*D47
A48: Iluminación LED y CCTV de 4 cámaras | B48: glb | C48: 1 | D48: 7500 | E48: =C48*D48
A49: Señalización, numeración y topellantas | B49: glb | C49: 1 | D49: 2400 | E49: =C49*D49
D50: Inversión (con imprevistos y factor de escenario) | E50: =SUM(E44:E49)*(1+Supuestos!$B$6)*Supuestos!$B$22
D51: Año de inversión (opera desde el año siguiente) | E51: 0
D52: Ingreso bruto potencial S/ por mes - pesimista | E52: 480
D53: Ingreso bruto potencial S/ por mes - base | E53: 900
D54: Ingreso bruto potencial S/ por mes - optimista | E54: 1080
D55: Ocupación cobrada - pesimista | E55: 0.6
D56: Ocupación cobrada - base | E56: 0.7
D57: Ocupación cobrada - optimista | E57: 0.8
D58: Gastos fijos S/ por año (personal, energía, mantenimiento, seguro, predial) | E58: 3200
D59: Gastos variables (% del ingreso cobrado) | E59: 0
D60: Impuestos (% del ingreso cobrado) | E60: 0
D61: Ingreso relativo 1.er año de operación | E61: 0.6
D62: Ingreso relativo 2.º año de operación | E62: 0.85
... D65: Reposición 1: monto a precios de hoy | E65: 33330
A67: FLUJO DE CAJA (S/ nominales)
A68: Concepto / año | C68: 0 | D68: 1 | E68: 2 | F68: 3 | G68: 4 | H68: 5 | I68: 6 | J68: 7 | K68: 8 | L68: 9 | M68: 10 | N68: 11 | O68: 12 | P68: 13 | Q68: 14 | R68: 15 | S68: 16 | T68: 17 | U68: 18 | V68: 19 | W68: 20
A69: Inversión - fase 1 | C69: =IF(C$68=$E$9,-$E$8*(1+Supuestos!$B$5)^MAX($E$9-1,0),0) | D69: =IF(D$68=$E$9,-$E$8*(1+Supuestos!$B$5)^MAX($E$9-1,0),0) | E69: =IF(E$68=$E$9,-$E$8*(1+Supuestos!$B$5)^MAX($E$9-1,0),0) | F69: =IF(F$68=$E$9,-$E$8*(1+Supuestos!$B$5)^MAX($E$9-1,0),0) | G69: =IF(G$68=$E$9,-$E$8*(1+Supuestos!$B$5)^MAX($E$9-1,0),0) | H69: =IF(H$68=$E$9,-$E$8*(1+Supuestos!$B$5)^MAX($E$9-1,0),0) | I69: =IF(I$68=$E$9,-$E$8*(1+Supuestos!$B$5)^MAX($E$9-1,0),0) | J69: =IF(J$68=$E$9,-$E$8*(1+Supuestos!$B$5)^MAX($E$9-1,0),0) | ... W69: =IF(W$68=$E$9,-$E$8*(1+Supuestos!$B$5)^MAX($E$9-1,0),0)
A70: Ingresos cobrados - fase 1 | C70: =IF((C$68-$E$9)>=1,CHOOSE(Supuestos!$B$3,$E$10,$E$11,$E$12)*12*CHOOSE(Supuestos!$B$3,$E$13,$E$14,$E$15)*IF((C$68-$E$9)=1,$E$19,IF((C$68-$E$9)=2,$E$20,1))*(1+Supuestos!$B$5)^MAX(C$68-1,0),0) | D70: =IF((D$68-$E$9)>=1,CHOOSE(Supuestos!$B$3,$E$10,$E$11,$E$12)*12*CHOOSE(Supuestos!$B$3,$E$13,$E$14,$E$15)*IF((D$68-$E$9)=1,$E$19,IF((D$68-$E$9)=2,$E$20,1))*(1+Supuestos!$B$5)^MAX(D$68-1,0),0) | E70: =IF((E$68-$E$9)>=1,CHOOSE(Supuestos!$B$3,$E$10,$E$11,$E$12)*12*CHOOSE(Supuestos!$B$3,$E$13,$E$14,$E$15)*IF((E$68-$E$9)=1,$E$19,IF((E$68-$E$9)=2,$E$20,1))*(1+Supuestos!$B$5)^MAX(E$68-1,0),0) | F70: =IF((F$68-$E$9)>=1,CHOOSE(Supuestos!$B$3,$E$10,$E$11,$E$12)*12*CHOOSE(Supuestos!$B$3,$E$13,$E$14,$E$15)*IF((F$68-$E$9)=1,$E$19,IF((F$68-$E$9)=2,$E$20,1))*(1+Supuestos!$B$5)^MAX(F$68-1,0),0) | G70: =IF((G$68-$E$9)>=1,CHOOSE(Supuestos!$B$3,$E$10,$E$11,$E$12)*12*CHOOSE(Supuestos!$B$3,$E$13,$E$14,$E$15)*IF((G$68-$E$9)=1,$E$19,IF((G$68-$E$9)=2,$E$20,1))*(1+Supuestos!$B$5)^MAX(G$68-1,0),0) | H70: =IF((H$68-$E$9)>=1,CHOOSE(Supuestos!$B$3,$E$10,$E$11,$E$12)*12*CHOOSE(Supuestos!$B$3,$E$13,$E$14,$E$15)*IF((H$68-$E$9)=1,$E$19,IF((H$68-$E$9)=2,$E$20,1))*(1+Supuestos!$B$5)^MAX(H$68-1,0),0) | I70: =IF((I$68-$E$9)>=1,CHOOSE(Supuestos!$B$3,$E$10,$E$11,$E$12)*12*CHOOSE(Supuestos!$B$3,$E$13,$E$14,$E$15)*IF((I$68-$E$9)=1,$E$19,IF((I$68-$E$9)=2,$E$20,1))*(1+Supuestos!$B$5)^MAX(I$68-1,0),0) | J70: =IF((J$68-$E$9)>=1,CHOOSE(Supuestos!$B$3,$E$10,$E$11,$E$12)*12*CHOOSE(Supuestos!$B$3,$E$13,$E$14,$E$15)*IF((J$68-$E$9)=1,$E$19,IF((J$68-$E$9)=2,$E$20,1))*(1+Supuestos!$B$5)^MAX(J$68-1,0),0) | ... W70: =IF((W$68-$E$9)>=1,CHOOSE(Supuestos!$B$3,$E$10,$E$11,$E$12)*12*CHOOSE(Supuestos!$B$3,$E$13,$E$14,$E$15)*IF((W$68-$E$9)=1,$E$19,IF((W$68-$E$9)=2,$E$20,1))*(1+Supuestos!$B$5)^MAX(W$68-1,0),0)
A71: Gastos - fase 1 | C71: =IF((C$68-$E$9)>=1,-$E$16*(1+Supuestos!$B$5)^MAX(C$68-1,0)-$E$17*C70,0) | D71: =IF((D$68-$E$9)>=1,-$E$16*(1+Supuestos!$B$5)^MAX(D$68-1,0)-$E$17*D70,0) | E71: =IF((E$68-$E$9)>=1,-$E$16*(1+Supuestos!$B$5)^MAX(E$68-1,0)-$E$17*E70,0) | F71: =IF((F$68-$E$9)>=1,-$E$16*(1+Supuestos!$B$5)^MAX(F$68-1,0)-$E$17*F70,0) | G71: =IF((G$68-$E$9)>=1,-$E$16*(1+Supuestos!$B$5)^MAX(G$68-1,0)-$E$17*G70,0) | H71: =IF((H$68-$E$9)>=1,-$E$16*(1+Supuestos!$B$5)^MAX(H$68-1,0)-$E$17*H70,0) | I71: =IF((I$68-$E$9)>=1,-$E$16*(1+Supuestos!$B$5)^MAX(I$68-1,0)-$E$17*I70,0) | J71: =IF((J$68-$E$9)>=1,-$E$16*(1+Supuestos!$B$5)^MAX(J$68-1,0)-$E$17*J70,0) | ... W71: =IF((W$68-$E$9)>=1,-$E$16*(1+Supuestos!$B$5)^MAX(W$68-1,0)-$E$17*W70,0)
A72: Impuestos - fase 1 | C72: =-$E$18*C70 | D72: =-$E$18*D70 | E72: =-$E$18*E70 | F72: =-$E$18*F70 | G72: =-$E$18*G70 | H72: =-$E$18*H70 | I72: =-$E$18*I70 | J72: =-$E$18*J70 | ... W72: =-$E$18*W70
A73: Reposiciones - fase 1 | C73: =0 | D73: =0 | E73: =0 | F73: =0 | G73: =0 | H73: =0 | I73: =0 | J73: =0 | ... W73: =0
A74: Valor residual (año 20) - fase 1 | C74: =IF(AND(C$68=20,$E$21>1),$E$8*(1+Supuestos!$B$5)^MAX($E$9-1,0)*MAX(0,1-(20-$E$9)/$E$21),0) | D74: =IF(AND(D$68=20,$E$21>1),$E$8*(1+Supuestos!$B$5)^MAX($E$9-1,0)*MAX(0,1-(20-$E$9)/$E$21),0) | E74: =IF(AND(E$68=20,$E$21>1),$E$8*(1+Supuestos!$B$5)^MAX($E$9-1,0)*MAX(0,1-(20-$E$9)/$E$21),0) | F74: =IF(AND(F$68=20,$E$21>1),$E$8*(1+Supuestos!$B$5)^MAX($E$9-1,0)*MAX(0,1-(20-$E$9)/$E$21),0) | G74: =IF(AND(G$68=20,$E$21>1),$E$8*(1+Supuestos!$B$5)^MAX($E$9-1,0)*MAX(0,1-(20-$E$9)/$E$21),0) | H74: =IF(AND(H$68=20,$E$21>1),$E$8*(1+Supuestos!$B$5)^MAX($E$9-1,0)*MAX(0,1-(20-$E$9)/$E$21),0) | I74: =IF(AND(I$68=20,$E$21>1),$E$8*(1+Supuestos!$B$5)^MAX($E$9-1,0)*MAX(0,1-(20-$E$9)/$E$21),0) | J74: =IF(AND(J$68=20,$E$21>1),$E$8*(1+Supuestos!$B$5)^MAX($E$9-1,0)*MAX(0,1-(20-$E$9)/$E$21),0) | ... W74: =IF(AND(W$68=20,$E$21>1),$E$8*(1+Supuestos!$B$5)^MAX($E$9-1,0)*MAX(0,1-(20-$E$9)/$E$21),0)
A75: Inversión - fase 2 | C75: =IF(C$68=$E$28,-$E$27*(1+Supuestos!$B$5)^MAX($E$28-1,0),0) | D75: =IF(D$68=$E$28,-$E$27*(1+Supuestos!$B$5)^MAX($E$28-1,0),0) | E75: =IF(E$68=$E$28,-$E$27*(1+Supuestos!$B$5)^MAX($E$28-1,0),0) | F75: =IF(F$68=$E$28,-$E$27*(1+Supuestos!$B$5)^MAX($E$28-1,0),0) | G75: =IF(G$68=$E$28,-$E$27*(1+Supuestos!$B$5)^MAX($E$28-1,0),0) | H75: =IF(H$68=$E$28,-$E$27*(1+Supuestos!$B$5)^MAX($E$28-1,0),0) | I75: =IF(I$68=$E$28,-$E$27*(1+Supuestos!$B$5)^MAX($E$28-1,0),0) | J75: =IF(J$68=$E$28,-$E$27*(1+Supuestos!$B$5)^MAX($E$28-1,0),0) | ... W75: =IF(W$68=$E$28,-$E$27*(1+Supuestos!$B$5)^MAX($E$28-1,0),0)
A76: Ingresos cobrados - fase 2 | C76: =IF((C$68-$E$28)>=1,CHOOSE(Supuestos!$B$3,$E$29,$E$30,$E$31)*12*CHOOSE(Supuestos!$B$3,$E$32,$E$33,$E$34)*IF((C$68-$E$28)=1,$E$38,IF((C$68-$E$28)=2,$E$39,1))*(1+Supuestos!$B$5)^MAX(C$68-1,0),0) | D76: =IF((D$68-$E$28)>=1,CHOOSE(Supuestos!$B$3,$E$29,$E$30,$E$31)*12*CHOOSE(Supuestos!$B$3,$E$32,$E$33,$E$34)*IF((D$68-$E$28)=1,$E$38,IF((D$68-$E$28)=2,$E$39,1))*(1+Supuestos!$B$5)^MAX(D$68-1,0),0) | E76: =IF((E$68-$E$28)>=1,CHOOSE(Supuestos!$B$3,$E$29,$E$30,$E$31)*12*CHOOSE(Supuestos!$B$3,$E$32,$E$33,$E$34)*IF((E$68-$E$28)=1,$E$38,IF((E$68-$E$28)=2,$E$39,1))*(1+Supuestos!$B$5)^MAX(E$68-1,0),0) | F76: =IF((F$68-$E$28)>=1,CHOOSE(Supuestos!$B$3,$E$29,$E$30,$E$31)*12*CHOOSE(Supuestos!$B$3,$E$32,$E$33,$E$34)*IF((F$68-$E$28)=1,$E$38,IF((F$68-$E$28)=2,$E$39,1))*(1+Supuestos!$B$5)^MAX(F$68-1,0),0) | G76: =IF((G$68-$E$28)>=1,CHOOSE(Supuestos!$B$3,$E$29,$E$30,$E$31)*12*CHOOSE(Supuestos!$B$3,$E$32,$E$33,$E$34)*IF((G$68-$E$28)=1,$E$38,IF((G$68-$E$28)=2,$E$39,1))*(1+Supuestos!$B$5)^MAX(G$68-1,0),0) | H76: =IF((H$68-$E$28)>=1,CHOOSE(Supuestos!$B$3,$E$29,$E$30,$E$31)*12*CHOOSE(Supuestos!$B$3,$E$32,$E$33,$E$34)*IF((H$68-$E$28)=1,$E$38,IF((H$68-$E$28)=2,$E$39,1))*(1+Supuestos!$B$5)^MAX(H$68-1,0),0) | I76: =IF((I$68-$E$28)>=1,CHOOSE(Supuestos!$B$3,$E$29,$E$30,$E$31)*12*CHOOSE(Supuestos!$B$3,$E$32,$E$33,$E$34)*IF((I$68-$E$28)=1,$E$38,IF((I$68-$E$28)=2,$E$39,1))*(1+Supuestos!$B$5)^MAX(I$68-1,0),0) | J76: =IF((J$68-$E$28)>=1,CHOOSE(Supuestos!$B$3,$E$29,$E$30,$E$31)*12*CHOOSE(Supuestos!$B$3,$E$32,$E$33,$E$34)*IF((J$68-$E$28)=1,$E$38,IF((J$68-$E$28)=2,$E$39,1))*(1+Supuestos!$B$5)^MAX(J$68-1,0),0) | ... W76: =IF((W$68-$E$28)>=1,CHOOSE(Supuestos!$B$3,$E$29,$E$30,$E$31)*12*CHOOSE(Supuestos!$B$3,$E$32,$E$33,$E$34)*IF((W$68-$E$28)=1,$E$38,IF((W$68-$E$28)=2,$E$39,1))*(1+Supuestos!$B$5)^MAX(W$68-1,0),0)
A77: Gastos - fase 2 | C77: =IF((C$68-$E$28)>=1,-$E$35*(1+Supuestos!$B$5)^MAX(C$68-1,0)-$E$36*C76,0) | D77: =IF((D$68-$E$28)>=1,-$E$35*(1+Supuestos!$B$5)^MAX(D$68-1,0)-$E$36*D76,0) | E77: =IF((E$68-$E$28)>=1,-$E$35*(1+Supuestos!$B$5)^MAX(E$68-1,0)-$E$36*E76,0) | F77: =IF((F$68-$E$28)>=1,-$E$35*(1+Supuestos!$B$5)^MAX(F$68-1,0)-$E$36*F76,0) | G77: =IF((G$68-$E$28)>=1,-$E$35*(1+Supuestos!$B$5)^MAX(G$68-1,0)-$E$36*G76,0) | H77: =IF((H$68-$E$28)>=1,-$E$35*(1+Supuestos!$B$5)^MAX(H$68-1,0)-$E$36*H76,0) | I77: =IF((I$68-$E$28)>=1,-$E$35*(1+Supuestos!$B$5)^MAX(I$68-1,0)-$E$36*I76,0) | J77: =IF((J$68-$E$28)>=1,-$E$35*(1+Supuestos!$B$5)^MAX(J$68-1,0)-$E$36*J76,0) | ... W77: =IF((W$68-$E$28)>=1,-$E$35*(1+Supuestos!$B$5)^MAX(W$68-1,0)-$E$36*W76,0)
A78: Impuestos - fase 2 | C78: =-$E$37*C76 | D78: =-$E$37*D76 | E78: =-$E$37*E76 | F78: =-$E$37*F76 | G78: =-$E$37*G76 | H78: =-$E$37*H76 | I78: =-$E$37*I76 | J78: =-$E$37*J76 | ... W78: =-$E$37*W76
A79: Reposiciones - fase 2 | C79: =0 | D79: =0 | E79: =0 | F79: =0 | G79: =0 | H79: =0 | I79: =0 | J79: =0 | ... W79: =0
A80: Valor residual (año 20) - fase 2 | C80: =IF(AND(C$68=20,$E$40>1),$E$27*(1+Supuestos!$B$5)^MAX($E$28-1,0)*MAX(0,1-(20-$E$28)/$E$40),0) | D80: =IF(AND(D$68=20,$E$40>1),$E$27*(1+Supuestos!$B$5)^MAX($E$28-1,0)*MAX(0,1-(20-$E$28)/$E$40),0) | E80: =IF(AND(E$68=20,$E$40>1),$E$27*(1+Supuestos!$B$5)^MAX($E$28-1,0)*MAX(0,1-(20-$E$28)/$E$40),0) | F80: =IF(AND(F$68=20,$E$40>1),$E$27*(1+Supuestos!$B$5)^MAX($E$28-1,0)*MAX(0,1-(20-$E$28)/$E$40),0) | G80: =IF(AND(G$68=20,$E$40>1),$E$27*(1+Supuestos!$B$5)^MAX($E$28-1,0)*MAX(0,1-(20-$E$28)/$E$40),0) | H80: =IF(AND(H$68=20,$E$40>1),$E$27*(1+Supuestos!$B$5)^MAX($E$28-1,0)*MAX(0,1-(20-$E$28)/$E$40),0) | I80: =IF(AND(I$68=20,$E$40>1),$E$27*(1+Supuestos!$B$5)^MAX($E$28-1,0)*MAX(0,1-(20-$E$28)/$E$40),0) | J80: =IF(AND(J$68=20,$E$40>1),$E$27*(1+Supuestos!$B$5)^MAX($E$28-1,0)*MAX(0,1-(20-$E$28)/$E$40),0) | ... W80: =IF(AND(W$68=20,$E$40>1),$E$27*(1+Supuestos!$B$5)^MAX($E$28-1,0)*MAX(0,1-(20-$E$28)/$E$40),0)
A81: Inversión - fase 3 | C81: =IF(C$68=$E$51,-$E$50*(1+Supuestos!$B$5)^MAX($E$51-1,0),0) | D81: =IF(D$68=$E$51,-$E$50*(1+Supuestos!$B$5)^MAX($E$51-1,0),0) | E81: =IF(E$68=$E$51,-$E$50*(1+Supuestos!$B$5)^MAX($E$51-1,0),0) | F81: =IF(F$68=$E$51,-$E$50*(1+Supuestos!$B$5)^MAX($E$51-1,0),0) | G81: =IF(G$68=$E$51,-$E$50*(1+Supuestos!$B$5)^MAX($E$51-1,0),0) | H81: =IF(H$68=$E$51,-$E$50*(1+Supuestos!$B$5)^MAX($E$51-1,0),0) | I81: =IF(I$68=$E$51,-$E$50*(1+Supuestos!$B$5)^MAX($E$51-1,0),0) | J81: =IF(J$68=$E$51,-$E$50*(1+Supuestos!$B$5)^MAX($E$51-1,0),0) | ... W81: =IF(W$68=$E$51,-$E$50*(1+Supuestos!$B$5)^MAX($E$51-1,0),0)
A82: Ingresos cobrados - fase 3 | C82: =IF((C$68-$E$51)>=1,CHOOSE(Supuestos!$B$3,$E$52,$E$53,$E$54)*12*CHOOSE(Supuestos!$B$3,$E$55,$E$56,$E$57)*IF((C$68-$E$51)=1,$E$61,IF((C$68-$E$51)=2,$E$62,1))*(1+Supuestos!$B$5)^MAX(C$68-1,0),0) | D82: =IF((D$68-$E$51)>=1,CHOOSE(Supuestos!$B$3,$E$52,$E$53,$E$54)*12*CHOOSE(Supuestos!$B$3,$E$55,$E$56,$E$57)*IF((D$68-$E$51)=1,$E$61,IF((D$68-$E$51)=2,$E$62,1))*(1+Supuestos!$B$5)^MAX(D$68-1,0),0) | E82: =IF((E$68-$E$51)>=1,CHOOSE(Supuestos!$B$3,$E$52,$E$53,$E$54)*12*CHOOSE(Supuestos!$B$3,$E$55,$E$56,$E$57)*IF((E$68-$E$51)=1,$E$61,IF((E$68-$E$51)=2,$E$62,1))*(1+Supuestos!$B$5)^MAX(E$68-1,0),0) | F82: =IF((F$68-$E$51)>=1,CHOOSE(Supuestos!$B$3,$E$52,$E$53,$E$54)*12*CHOOSE(Supuestos!$B$3,$E$55,$E$56,$E$57)*IF((F$68-$E$51)=1,$E$61,IF((F$68-$E$51)=2,$E$62,1))*(1+Supuestos!$B$5)^MAX(F$68-1,0),0) | G82: =IF((G$68-$E$51)>=1,CHOOSE(Supuestos!$B$3,$E$52,$E$53,$E$54)*12*CHOOSE(Supuestos!$B$3,$E$55,$E$56,$E$57)*IF((G$68-$E$51)=1,$E$61,IF((G$68-$E$51)=2,$E$62,1))*(1+Supuestos!$B$5)^MAX(G$68-1,0),0) | H82: =IF((H$68-$E$51)>=1,CHOOSE(Supuestos!$B$3,$E$52,$E$53,$E$54)*12*CHOOSE(Supuestos!$B$3,$E$55,$E$56,$E$57)*IF((H$68-$E$51)=1,$E$61,IF((H$68-$E$51)=2,$E$62,1))*(1+Supuestos!$B$5)^MAX(H$68-1,0),0) | I82: =IF((I$68-$E$51)>=1,CHOOSE(Supuestos!$B$3,$E$52,$E$53,$E$54)*12*CHOOSE(Supuestos!$B$3,$E$55,$E$56,$E$57)*IF((I$68-$E$51)=1,$E$61,IF((I$68-$E$51)=2,$E$62,1))*(1+Supuestos!$B$5)^MAX(I$68-1,0),0) | J82: =IF((J$68-$E$51)>=1,CHOOSE(Supuestos!$B$3,$E$52,$E$53,$E$54)*12*CHOOSE(Supuestos!$B$3,$E$55,$E$56,$E$57)*IF((J$68-$E$51)=1,$E$61,IF((J$68-$E$51)=2,$E$62,1))*(1+Supuestos!$B$5)^MAX(J$68-1,0),0) | ... W82: =IF((W$68-$E$51)>=1,CHOOSE(Supuestos!$B$3,$E$52,$E$53,$E$54)*12*CHOOSE(Supuestos!$B$3,$E$55,$E$56,$E$57)*IF((W$68-$E$51)=1,$E$61,IF((W$68-$E$51)=2,$E$62,1))*(1+Supuestos!$B$5)^MAX(W$68-1,0),0)
A83: Gastos - fase 3 | C83: =IF((C$68-$E$51)>=1,-$E$58*(1+Supuestos!$B$5)^MAX(C$68-1,0)-$E$59*C82,0) | D83: =IF((D$68-$E$51)>=1,-$E$58*(1+Supuestos!$B$5)^MAX(D$68-1,0)-$E$59*D82,0) | E83: =IF((E$68-$E$51)>=1,-$E$58*(1+Supuestos!$B$5)^MAX(E$68-1,0)-$E$59*E82,0) | F83: =IF((F$68-$E$51)>=1,-$E$58*(1+Supuestos!$B$5)^MAX(F$68-1,0)-$E$59*F82,0) | G83: =IF((G$68-$E$51)>=1,-$E$58*(1+Supuestos!$B$5)^MAX(G$68-1,0)-$E$59*G82,0) | H83: =IF((H$68-$E$51)>=1,-$E$58*(1+Supuestos!$B$5)^MAX(H$68-1,0)-$E$59*H82,0) | I83: =IF((I$68-$E$51)>=1,-$E$58*(1+Supuestos!$B$5)^MAX(I$68-1,0)-$E$59*I82,0) | J83: =IF((J$68-$E$51)>=1,-$E$58*(1+Supuestos!$B$5)^MAX(J$68-1,0)-$E$59*J82,0) | ... W83: =IF((W$68-$E$51)>=1,-$E$58*(1+Supuestos!$B$5)^MAX(W$68-1,0)-$E$59*W82,0)
A84: Impuestos - fase 3 | C84: =-$E$60*C82 | D84: =-$E$60*D82 | E84: =-$E$60*E82 | F84: =-$E$60*F82 | G84: =-$E$60*G82 | H84: =-$E$60*H82 | I84: =-$E$60*I82 | J84: =-$E$60*J82 | ... W84: =-$E$60*W82
A85: Reposiciones - fase 3 | C85: =IF((C$68-$E$51)=$E$64,-$E$65*(1+Supuestos!$B$5)^MAX(C$68-1,0)*Supuestos!$B$22,0) | D85: =IF((D$68-$E$51)=$E$64,-$E$65*(1+Supuestos!$B$5)^MAX(D$68-1,0)*Supuestos!$B$22,0) | E85: =IF((E$68-$E$51)=$E$64,-$E$65*(1+Supuestos!$B$5)^MAX(E$68-1,0)*Supuestos!$B$22,0) | F85: =IF((F$68-$E$51)=$E$64,-$E$65*(1+Supuestos!$B$5)^MAX(F$68-1,0)*Supuestos!$B$22,0) | G85: =IF((G$68-$E$51)=$E$64,-$E$65*(1+Supuestos!$B$5)^MAX(G$68-1,0)*Supuestos!$B$22,0) | H85: =IF((H$68-$E$51)=$E$64,-$E$65*(1+Supuestos!$B$5)^MAX(H$68-1,0)*Supuestos!$B$22,0) | I85: =IF((I$68-$E$51)=$E$64,-$E$65*(1+Supuestos!$B$5)^MAX(I$68-1,0)*Supuestos!$B$22,0) | J85: =IF((J$68-$E$51)=$E$64,-$E$65*(1+Supuestos!$B$5)^MAX(J$68-1,0)*Supuestos!$B$22,0) | ... W85: =IF((W$68-$E$51)=$E$64,-$E$65*(1+Supuestos!$B$5)^MAX(W$68-1,0)*Supuestos!$B$22,0)
A86: Valor residual (año 20) - fase 3 | C86: =IF(AND(C$68=20,$E$63>1),$E$50*(1+Supuestos!$B$5)^MAX($E$51-1,0)*MAX(0,1-(20-$E$51)/$E$63),0) | D86: =IF(AND(D$68=20,$E$63>1),$E$50*(1+Supuestos!$B$5)^MAX($E$51-1,0)*MAX(0,1-(20-$E$51)/$E$63),0) | E86: =IF(AND(E$68=20,$E$63>1),$E$50*(1+Supuestos!$B$5)^MAX($E$51-1,0)*MAX(0,1-(20-$E$51)/$E$63),0) | F86: =IF(AND(F$68=20,$E$63>1),$E$50*(1+Supuestos!$B$5)^MAX($E$51-1,0)*MAX(0,1-(20-$E$51)/$E$63),0) | G86: =IF(AND(G$68=20,$E$63>1),$E$50*(1+Supuestos!$B$5)^MAX($E$51-1,0)*MAX(0,1-(20-$E$51)/$E$63),0) | H86: =IF(AND(H$68=20,$E$63>1),$E$50*(1+Supuestos!$B$5)^MAX($E$51-1,0)*MAX(0,1-(20-$E$51)/$E$63),0) | I86: =IF(AND(I$68=20,$E$63>1),$E$50*(1+Supuestos!$B$5)^MAX($E$51-1,0)*MAX(0,1-(20-$E$51)/$E$63),0) | J86: =IF(AND(J$68=20,$E$63>1),$E$50*(1+Supuestos!$B$5)^MAX($E$51-1,0)*MAX(0,1-(20-$E$51)/$E$63),0) | ... W86: =IF(AND(W$68=20,$E$63>1),$E$50*(1+Supuestos!$B$5)^MAX($E$51-1,0)*MAX(0,1-(20-$E$51)/$E$63),0)
A87: Inversión | C87: =C69+C75+C81 | D87: =D69+D75+D81 | E87: =E69+E75+E81 | F87: =F69+F75+F81 | G87: =G69+G75+G81 | H87: =H69+H75+H81 | I87: =I69+I75+I81 | J87: =J69+J75+J81 | ... W87: =W69+W75+W81
A88: Ingresos cobrados | C88: =C70+C76+C82 | D88: =D70+D76+D82 | E88: =E70+E76+E82 | F88: =F70+F76+F82 | G88: =G70+G76+G82 | H88: =H70+H76+H82 | I88: =I70+I76+I82 | J88: =J70+J76+J82 | ... W88: =W70+W76+W82
A89: Gastos | C89: =C71+C77+C83 | D89: =D71+D77+D83 | E89: =E71+E77+E83 | F89: =F71+F77+F83 | G89: =G71+G77+G83 | H89: =H71+H77+H83 | I89: =I71+I77+I83 | J89: =J71+J77+J83 | ... W89: =W71+W77+W83
A90: Impuestos | C90: =C72+C78+C84 | D90: =D72+D78+D84 | E90: =E72+E78+E84 | F90: =F72+F78+F84 | G90: =G72+G78+G84 | H90: =H72+H78+H84 | I90: =I72+I78+I84 | J90: =J72+J78+J84 | ... W90: =W72+W78+W84
A91: Reposiciones | C91: =C73+C79+C85 | D91: =D73+D79+D85 | E91: =E73+E79+E85 | F91: =F73+F79+F85 | G91: =G73+G79+G85 | H91: =H73+H79+H85 | I91: =I73+I79+I85 | J91: =J73+J79+J85 | ... W91: =W73+W79+W85
A92: Valor residual (año 20) | C92: =C74+C80+C86 | D92: =D74+D80+D86 | E92: =E74+E80+E86 | F92: =F74+F80+F86 | G92: =G74+G80+G86 | H92: =H74+H80+H86 | I92: =I74+I80+I86 | J92: =J74+J80+J86 | ... W92: =W74+W80+W86
A93: FLUJO NETO | C93: =C87+C88+C89+C90+C91+C92 | D93: =D87+D88+D89+D90+D91+D92 | E93: =E87+E88+E89+E90+E91+E92 | F93: =F87+F88+F89+F90+F91+F92 | G93: =G87+G88+G89+G90+G91+G92 | H93: =H87+H88+H89+H90+H91+H92 | I93: =I87+I88+I89+I90+I91+I92 | J93: =J87+J88+J89+J90+J91+J92 | ... W93: =W87+W88+W89+W90+W91+W92
A94: Caja acumulada (sin valor residual) | C94: =C93-C92 | D94: =C94+D93-D92 | E94: =D94+E93-E92 | F94: =E94+F93-F92 | G94: =F94+G93-G92 | H94: =G94+H93-H92 | I94: =H94+I93-I92 | J94: =I94+J93-J92 | K94: =J94+K93-K92 | ... W94: =V94+W93-W92
A95: Flujo del propietario contando el terreno (lo aporta hoy y lo recupera valorizado) | C95: =C93-Supuestos!$B$21 | D95: =D93 | E95: =E93 | F95: =F93 | G95: =G93 | H95: =H93 | I95: =I93 | J95: =J93 | K95: =K93 | ... V95: =V93 | W95: =W93+Supuestos!$B$21*(1+Supuestos!$B$23)^20
A97: Inversión total | C97: =-SUM(C87:W87)
A98: VAN al 10% | C98: =C93+NPV(Supuestos!$B$4,D93:W93)
A99: TIR | C99: =IFERROR(IRR(C93:W93),IFERROR(IRR(C93:W93,-0.05),"no aplica"))
A100: Año en que se recupera la inversión (acumulado ≥ 0) | C100: =IF(-SUM(C87:W87)=0,"sin inversión",IFERROR(INDEX(C68:W68,MATCH(TRUE,INDEX(C94:W94>=0,0),0)),"no en 20 años"))
A101: Caja neta del año 5 sin inversiones (S/ nominales) | C101: =H93-H87
A102: TIR contando el terreno | C102: =IFERROR(IRR(C95:W95),"no aplica")

Sheet A Estac. techado
A1: A. Estacionamiento techado (anteproyecto actual)
A2: 28 plazas techadas con estructura metálica, 5 motos y 2 mototaxis; guardián contratado.
A4: Fase 1: Estacionamiento techado
D5: Inversión (calculada en su propio modelo, por factor de escenario) | E5: =308524.26*Supuestos!$B$22
D6: Año de inversión (opera desde el año siguiente) | E6: 0
D7: Ingreso bruto potencial S/ por mes - pesimista | E7: 1890
D8: Ingreso bruto potencial S/ por mes - base | E8: 2855
D9: Ingreso bruto potencial S/ por mes - optimista | E9: 4330
D10: Ocupación cobrada - pesimista | E10: 1
D11: Ocupación cobrada - base | E11: 1
D12: Ocupación cobrada - optimista | E12: 1
D13: Gastos fijos S/ por año (personal, energía, mantenimiento, seguro, predial) | E13: 27005.81
D14: Gastos variables (% del ingreso cobrado) | E14: 0
D15: Impuestos (% del ingreso cobrado) | E15: 0
D16: Ingreso relativo 1.er año de operación | E16: 0.6
D17: Ingreso relativo 2.º año de operación | E17: 0.85
... D20: Reposición 1: monto a precios de hoy | E20: 18511.456
A22: FLUJO DE CAJA (S/ nominales)
A23: Concepto / año | C23: 0 | D23: 1 | E23: 2 | F23: 3 | G23: 4 | H23: 5 | I23: 6 | J23: 7 | K23: 8 | L23: 9 | M23: 10 | N23: 11 | O23: 12 | P23: 13 | Q23: 14 | R23: 15 | S23: 16 | T23: 17 | U23: 18 | V23: 19 | W23: 20
A24: Inversión - fase 1 | C24: =IF(C$23=$E$6,-$E$5*(1+Supuestos!$B$5)^MAX($E$6-1,0),0) | D24: =IF(D$23=$E$6,-$E$5*(1+Supuestos!$B$5)^MAX($E$6-1,0),0) | E24: =IF(E$23=$E$6,-$E$5*(1+Supuestos!$B$5)^MAX($E$6-1,0),0) | F24: =IF(F$23=$E$6,-$E$5*(1+Supuestos!$B$5)^MAX($E$6-1,0),0) | G24: =IF(G$23=$E$6,-$E$5*(1+Supuestos!$B$5)^MAX($E$6-1,0),0) | H24: =IF(H$23=$E$6,-$E$5*(1+Supuestos!$B$5)^MAX($E$6-1,0),0) | I24: =IF(I$23=$E$6,-$E$5*(1+Supuestos!$B$5)^MAX($E$6-1,0),0) | J24: =IF(J$23=$E$6,-$E$5*(1+Supuestos!$B$5)^MAX($E$6-1,0),0) | ... W24: =IF(W$23=$E$6,-$E$5*(1+Supuestos!$B$5)^MAX($E$6-1,0),0)
A25: Ingresos cobrados - fase 1 | C25: =IF((C$23-$E$6)>=1,CHOOSE(Supuestos!$B$3,$E$7,$E$8,$E$9)*12*CHOOSE(Supuestos!$B$3,$E$10,$E$11,$E$12)*IF((C$23-$E$6)=1,$E$16,IF((C$23-$E$6)=2,$E$17,1))*(1+Supuestos!$B$5)^MAX(C$23-1,0),0) | D25: =IF((D$23-$E$6)>=1,CHOOSE(Supuestos!$B$3,$E$7,$E$8,$E$9)*12*CHOOSE(Supuestos!$B$3,$E$10,$E$11,$E$12)*IF((D$23-$E$6)=1,$E$16,IF((D$23-$E$6)=2,$E$17,1))*(1+Supuestos!$B$5)^MAX(D$23-1,0),0) | E25: =IF((E$23-$E$6)>=1,CHOOSE(Supuestos!$B$3,$E$7,$E$8,$E$9)*12*CHOOSE(Supuestos!$B$3,$E$10,$E$11,$E$12)*IF((E$23-$E$6)=1,$E$16,IF((E$23-$E$6)=2,$E$17,1))*(1+Supuestos!$B$5)^MAX(E$23-1,0),0) | F25: =IF((F$23-$E$6)>=1,CHOOSE(Supuestos!$B$3,$E$7,$E$8,$E$9)*12*CHOOSE(Supuestos!$B$3,$E$10,$E$11,$E$12)*IF((F$23-$E$6)=1,$E$16,IF((F$23-$E$6)=2,$E$17,1))*(1+Supuestos!$B$5)^MAX(F$23-1,0),0) | G25: =IF((G$23-$E$6)>=1,CHOOSE(Supuestos!$B$3,$E$7,$E$8,$E$9)*12*CHOOSE(Supuestos!$B$3,$E$10,$E$11,$E$12)*IF((G$23-$E$6)=1,$E$16,IF((G$23-$E$6)=2,$E$17,1))*(1+Supuestos!$B$5)^MAX(G$23-1,0),0) | H25: =IF((H$23-$E$6)>=1,CHOOSE(Supuestos!$B$3,$E$7,$E$8,$E$9)*12*CHOOSE(Supuestos!$B$3,$E$10,$E$11,$E$12)*IF((H$23-$E$6)=1,$E$16,IF((H$23-$E$6)=2,$E$17,1))*(1+Supuestos!$B$5)^MAX(H$23-1,0),0) | I25: =IF((I$23-$E$6)>=1,CHOOSE(Supuestos!$B$3,$E$7,$E$8,$E$9)*12*CHOOSE(Supuestos!$B$3,$E$10,$E$11,$E$12)*IF((I$23-$E$6)=1,$E$16,IF((I$23-$E$6)=2,$E$17,1))*(1+Supuestos!$B$5)^MAX(I$23-1,0),0) | J25: =IF((J$23-$E$6)>=1,CHOOSE(Supuestos!$B$3,$E$7,$E$8,$E$9)*12*CHOOSE(Supuestos!$B$3,$E$10,$E$11,$E$12)*IF((J$23-$E$6)=1,$E$16,IF((J$23-$E$6)=2,$E$17,1))*(1+Supuestos!$B$5)^MAX(J$23-1,0),0) | ... W25: =IF((W$23-$E$6)>=1,CHOOSE(Supuestos!$B$3,$E$7,$E$8,$E$9)*12*CHOOSE(Supuestos!$B$3,$E$10,$E$11,$E$12)*IF((W$23-$E$6)=1,$E$16,IF((W$23-$E$6)=2,$E$17,1))*(1+Supuestos!$B$5)^MAX(W$23-1,0),0)
A26: Gastos - fase 1 | C26: =IF((C$23-$E$6)>=1,-$E$13*(1+Supuestos!$B$5)^MAX(C$23-1,0)-$E$14*C25,0) | D26: =IF((D$23-$E$6)>=1,-$E$13*(1+Supuestos!$B$5)^MAX(D$23-1,0)-$E$14*D25,0) | E26: =IF((E$23-$E$6)>=1,-$E$13*(1+Supuestos!$B$5)^MAX(E$23-1,0)-$E$14*E25,0) | F26: =IF((F$23-$E$6)>=1,-$E$13*(1+Supuestos!$B$5)^MAX(F$23-1,0)-$E$14*F25,0) | G26: =IF((G$23-$E$6)>=1,-$E$13*(1+Supuestos!$B$5)^MAX(G$23-1,0)-$E$14*G25,0) | H26: =IF((H$23-$E$6)>=1,-$E$13*(1+Supuestos!$B$5)^MAX(H$23-1,0)-$E$14*H25,0) | I26: =IF((I$23-$E$6)>=1,-$E$13*(1+Supuestos!$B$5)^MAX(I$23-1,0)-$E$14*I25,0) | J26: =IF((J$23-$E$6)>=1,-$E$13*(1+Supuestos!$B$5)^MAX(J$23-1,0)-$E$14*J25,0) | ... W26: =IF((W$23-$E$6)>=1,-$E$13*(1+Supuestos!$B$5)^MAX(W$23-1,0)-$E$14*W25,0)
A27: Impuestos - fase 1 | C27: =-$E$15*C25 | D27: =-$E$15*D25 | E27: =-$E$15*E25 | F27: =-$E$15*F25 | G27: =-$E$15*G25 | H27: =-$E$15*H25 | I27: =-$E$15*I25 | J27: =-$E$15*J25 | ... W27: =-$E$15*W25
A28: Reposiciones - fase 1 | C28: =IF((C$23-$E$6)=$E$19,-$E$20*(1+Supuestos!$B$5)^MAX(C$23-1,0)*Supuestos!$B$22,0) | D28: =IF((D$23-$E$6)=$E$19,-$E$20*(1+Supuestos!$B$5)^MAX(D$23-1,0)*Supuestos!$B$22,0) | E28: =IF((E$23-$E$6)=$E$19,-$E$20*(1+Supuestos!$B$5)^MAX(E$23-1,0)*Supuestos!$B$22,0) | F28: =IF((F$23-$E$6)=$E$19,-$E$20*(1+Supuestos!$B$5)^MAX(F$23-1,0)*Supuestos!$B$22,0) | G28: =IF((G$23-$E$6)=$E$19,-$E$20*(1+Supuestos!$B$5)^MAX(G$23-1,0)*Supuestos!$B$22,0) | H28: =IF((H$23-$E$6)=$E$19,-$E$20*(1+Supuestos!$B$5)^MAX(H$23-1,0)*Supuestos!$B$22,0) | I28: =IF((I$23-$E$6)=$E$19,-$E$20*(1+Supuestos!$B$5)^MAX(I$23-1,0)*Supuestos!$B$22,0) | J28: =IF((J$23-$E$6)=$E$19,-$E$20*(1+Supuestos!$B$5)^MAX(J$23-1,0)*Supuestos!$B$22,0) | ... W28: =IF((W$23-$E$6)=$E$19,-$E$20*(1+Supuestos!$B$5)^MAX(W$23-1,0)*Supuestos!$B$22,0)
A29: Valor residual (año 20) - fase 1 | C29: =IF(AND(C$23=20,$E$18>1),$E$5*(1+Supuestos!$B$5)^MAX($E$6-1,0)*MAX(0,1-(20-$E$6)/$E$18),0) | D29: =IF(AND(D$23=20,$E$18>1),$E$5*(1+Supuestos!$B$5)^MAX($E$6-1,0)*MAX(0,1-(20-$E$6)/$E$18),0) | E29: =IF(AND(E$23=20,$E$18>1),$E$5*(1+Supuestos!$B$5)^MAX($E$6-1,0)*MAX(0,1-(20-$E$6)/$E$18),0) | F29: =IF(AND(F$23=20,$E$18>1),$E$5*(1+Supuestos!$B$5)^MAX($E$6-1,0)*MAX(0,1-(20-$E$6)/$E$18),0) | G29: =IF(AND(G$23=20,$E$18>1),$E$5*(1+Supuestos!$B$5)^MAX($E$6-1,0)*MAX(0,1-(20-$E$6)/$E$18),0) | H29: =IF(AND(H$23=20,$E$18>1),$E$5*(1+Supuestos!$B$5)^MAX($E$6-1,0)*MAX(0,1-(20-$E$6)/$E$18),0) | I29: =IF(AND(I$23=20,$E$18>1),$E$5*(1+Supuestos!$B$5)^MAX($E$6-1,0)*MAX(0,1-(20-$E$6)/$E$18),0) | J29: =IF(AND(J$23=20,$E$18>1),$E$5*(1+Supuestos!$B$5)^MAX($E$6-1,0)*MAX(0,1-(20-$E$6)/$E$18),0) | ... W29: =IF(AND(W$23=20,$E$18>1),$E$5*(1+Supuestos!$B$5)^MAX($E$6-1,0)*MAX(0,1-(20-$E$6)/$E$18),0)
A30: Inversión | C30: =C24 | D30: =D24 | E30: =E24 | F30: =F24 | G30: =G24 | H30: =H24 | I30: =I24 | J30: =J24 | ... W30: =W24
A31: Ingresos cobrados | C31: =C25 | D31: =D25 | E31: =E25 | F31: =F25 | G31: =G25 | H31: =H25 | I31: =I25 | J31: =J25 | ... W31: =W25
A32: Gastos | C32: =C26 | D32: =D26 | E32: =E26 | F32: =F26 | G32: =G26 | H32: =H26 | I32: =I26 | J32: =J26 | ... W32: =W26
A33: Impuestos | C33: =C27 | D33: =D27 | E33: =E27 | F33: =F27 | G33: =G27 | H33: =H27 | I33: =I27 | J33: =J27 | ... W33: =W27
A34: Reposiciones | C34: =C28 | D34: =D28 | E34: =E28 | F34: =F28 | G34: =G28 | H34: =H28 | I34: =I28 | J34: =J28 | ... W34: =W28
A35: Valor residual (año 20) | C35: =C29 | D35: =D29 | E35: =E29 | F35: =F29 | G35: =G29 | H35: =H29 | I35: =I29 | J35: =J29 | ... W35: =W29
A36: FLUJO NETO | C36: =C30+C31+C32+C33+C34+C35 | D36: =D30+D31+D32+D33+D34+D35 | E36: =E30+E31+E32+E33+E34+E35 | F36: =F30+F31+F32+F33+F34+F35 | G36: =G30+G31+G32+G33+G34+G35 | H36: =H30+H31+H32+H33+H34+H35 | I36: =I30+I31+I32+I33+I34+I35 | J36: =J30+J31+J32+J33+J34+J35 | ... W36: =W30+W31+W32+W33+W34+W35
A37: Caja acumulada (sin valor residual) | C37: =C36-C35 | D37: =C37+D36-D35 | E37: =D37+E36-E35 | F37: =E37+F36-F35 | G37: =F37+G36-G35 | H37: =G37+H36-H35 | I37: =H37+I36-I35 | J37: =I37+J36-J35 | K37: =J37+K36-K35 | ... W37: =V37+W36-W35
A38: Flujo del propietario contando el terreno (lo aporta hoy y lo recupera valorizado) | C38: =C36-Supuestos!$B$21 | D38: =D36 | E38: =E36 | F38: =F36 | G38: =G36 | H38: =H36 | I38: =I36 | J38: =J36 | K38: =K36 | ... V38: =V36 | W38: =W36+Supuestos!$B$21*(1+Supuestos!$B$23)^20
A40: Inversión total | C40: =-SUM(C30:W30)
A41: VAN al 10% | C41: =C36+NPV(Supuestos!$B$4,D36:W36)
A42: TIR | C42: =IFERROR(IRR(C36:W36),IFERROR(IRR(C36:W36,-0.05),"no aplica"))
A43: Año en que se recupera la inversión (acumulado ≥ 0) | C43: =IF(-SUM(C30:W30)=0,"sin inversión",IFERROR(INDEX(C23:W23,MATCH(TRUE,INDEX(C37:W37>=0,0),0)),"no en 20 años"))
A44: Caja neta del año 5 sin inversiones (S/ nominales) | C44: =H36-H30
A45: TIR contando el terreno | C45: =IFERROR(IRR(C38:W38),"no aplica")

Sheet F Cancha techada
A1: F. Cancha sintética techada (fulbito)
A2: Cancha recreativa de 25 × 15 m (sin franja de seguridad; con franja de 1 m ≈ 25 × 14), techada por la lluvia, con vestuarios y caseta.
A4: Fase 1: Cancha sintética techada
A5: Partida | B5: Und. | C5: Cantidad | D5: P. unitario | E5: Parcial
A6: Base granular, losa de nivelación y drenaje | B6: m² | C6: 450 | D6: 70 | E6: =C6*D6
A7: Grass sintético instalado (25 × 15 m + bandas) | B7: m² | C7: 400 | D7: 115 | E7: =C7*D7
A8: Estructura metálica y cobertura TR-4 sobre la cancha | B8: m² | C8: 570 | D8: 330 | E8: =C8*D8
A9: Mallas perimetrales, arcos y redes | B9: glb | C9: 1 | D9: 9000 | E9: =C9*D9
A10: Iluminación LED (8 kW) | B10: glb | C10: 1 | D10: 14000 | E10: =C10*D10
A11: Vestuarios, SS.HH. y caseta (albañilería) | B11: m² | C11: 40 | D11: 1300 | E11: =C11*D11
A12: Cerco de albañilería en frentes y portones | B12: ml | C12: 50 | D12: 330 | E12: =C12*D12
A13: Expediente y licencias | B13: glb | C13: 1 | D13: 15000 | E13: =C13*D13
D14: Inversión (con imprevistos y factor de escenario) | E14: =SUM(E6:E13)*(1+Supuestos!$B$6)*Supuestos!$B$22
D15: Año de inversión (opera desde el año siguiente) | E15: 0
D16: Ingreso bruto potencial S/ por mes - pesimista | E16: 2700
D17: Ingreso bruto potencial S/ por mes - base | E17: 3750
D18: Ingreso bruto potencial S/ por mes - optimista | E18: 5775
D19: Ocupación cobrada - pesimista | E19: 1
D20: Ocupación cobrada - base | E20: 1
D21: Ocupación cobrada - optimista | E21: 1
D22: Gastos fijos S/ por año (personal, energía, mantenimiento, seguro, predial) | E22: 30645.4
D23: Gastos variables (% del ingreso cobrado) | E23: 0
D24: Impuestos (% del ingreso cobrado) | E24: 0
D25: Ingreso relativo 1.er año de operación | E25: 0.7
D26: Ingreso relativo 2.º año de operación | E26: 0.9
... D31: Reposición 2: monto a precios de hoy | E31: 50600
A33: FLUJO DE CAJA (S/ nominales)
A34: Concepto / año | C34: 0 | D34: 1 | E34: 2 | F34: 3 | G34: 4 | H34: 5 | I34: 6 | J34: 7 | K34: 8 | L34: 9 | M34: 10 | N34: 11 | O34: 12 | P34: 13 | Q34: 14 | R34: 15 | S34: 16 | T34: 17 | U34: 18 | V34: 19 | W34: 20
A35: Inversión - fase 1 | C35: =IF(C$34=$E$15,-$E$14*(1+Supuestos!$B$5)^MAX($E$15-1,0),0) | D35: =IF(D$34=$E$15,-$E$14*(1+Supuestos!$B$5)^MAX($E$15-1,0),0) | E35: =IF(E$34=$E$15,-$E$14*(1+Supuestos!$B$5)^MAX($E$15-1,0),0) | F35: =IF(F$34=$E$15,-$E$14*(1+Supuestos!$B$5)^MAX($E$15-1,0),0) | G35: =IF(G$34=$E$15,-$E$14*(1+Supuestos!$B$5)^MAX($E$15-1,0),0) | H35: =IF(H$34=$E$15,-$E$14*(1+Supuestos!$B$5)^MAX($E$15-1,0),0) | I35: =IF(I$34=$E$15,-$E$14*(1+Supuestos!$B$5)^MAX($E$15-1,0),0) | J35: =IF(J$34=$E$15,-$E$14*(1+Supuestos!$B$5)^MAX($E$15-1,0),0) | ... W35: =IF(W$34=$E$15,-$E$14*(1+Supuestos!$B$5)^MAX($E$15-1,0),0)
A36: Ingresos cobrados - fase 1 | C36: =IF((C$34-$E$15)>=1,CHOOSE(Supuestos!$B$3,$E$16,$E$17,$E$18)*12*CHOOSE(Supuestos!$B$3,$E$19,$E$20,$E$21)*IF((C$34-$E$15)=1,$E$25,IF((C$34-$E$15)=2,$E$26,1))*(1+Supuestos!$B$5)^MAX(C$34-1,0),0) | D36: =IF((D$34-$E$15)>=1,CHOOSE(Supuestos!$B$3,$E$16,$E$17,$E$18)*12*CHOOSE(Supuestos!$B$3,$E$19,$E$20,$E$21)*IF((D$34-$E$15)=1,$E$25,IF((D$34-$E$15)=2,$E$26,1))*(1+Supuestos!$B$5)^MAX(D$34-1,0),0) | E36: =IF((E$34-$E$15)>=1,CHOOSE(Supuestos!$B$3,$E$16,$E$17,$E$18)*12*CHOOSE(Supuestos!$B$3,$E$19,$E$20,$E$21)*IF((E$34-$E$15)=1,$E$25,IF((E$34-$E$15)=2,$E$26,1))*(1+Supuestos!$B$5)^MAX(E$34-1,0),0) | F36: =IF((F$34-$E$15)>=1,CHOOSE(Supuestos!$B$3,$E$16,$E$17,$E$18)*12*CHOOSE(Supuestos!$B$3,$E$19,$E$20,$E$21)*IF((F$34-$E$15)=1,$E$25,IF((F$34-$E$15)=2,$E$26,1))*(1+Supuestos!$B$5)^MAX(F$34-1,0),0) | G36: =IF((G$34-$E$15)>=1,CHOOSE(Supuestos!$B$3,$E$16,$E$17,$E$18)*12*CHOOSE(Supuestos!$B$3,$E$19,$E$20,$E$21)*IF((G$34-$E$15)=1,$E$25,IF((G$34-$E$15)=2,$E$26,1))*(1+Supuestos!$B$5)^MAX(G$34-1,0),0) | H36: =IF((H$34-$E$15)>=1,CHOOSE(Supuestos!$B$3,$E$16,$E$17,$E$18)*12*CHOOSE(Supuestos!$B$3,$E$19,$E$20,$E$21)*IF((H$34-$E$15)=1,$E$25,IF((H$34-$E$15)=2,$E$26,1))*(1+Supuestos!$B$5)^MAX(H$34-1,0),0) | I36: =IF((I$34-$E$15)>=1,CHOOSE(Supuestos!$B$3,$E$16,$E$17,$E$18)*12*CHOOSE(Supuestos!$B$3,$E$19,$E$20,$E$21)*IF((I$34-$E$15)=1,$E$25,IF((I$34-$E$15)=2,$E$26,1))*(1+Supuestos!$B$5)^MAX(I$34-1,0),0) | J36: =IF((J$34-$E$15)>=1,CHOOSE(Supuestos!$B$3,$E$16,$E$17,$E$18)*12*CHOOSE(Supuestos!$B$3,$E$19,$E$20,$E$21)*IF((J$34-$E$15)=1,$E$25,IF((J$34-$E$15)=2,$E$26,1))*(1+Supuestos!$B$5)^MAX(J$34-1,0),0) | ... W36: =IF((W$34-$E$15)>=1,CHOOSE(Supuestos!$B$3,$E$16,$E$17,$E$18)*12*CHOOSE(Supuestos!$B$3,$E$19,$E$20,$E$21)*IF((W$34-$E$15)=1,$E$25,IF((W$34-$E$15)=2,$E$26,1))*(1+Supuestos!$B$5)^MAX(W$34-1,0),0)
A37: Gastos - fase 1 | C37: =IF((C$34-$E$15)>=1,-$E$22*(1+Supuestos!$B$5)^MAX(C$34-1,0)-$E$23*C36,0) | D37: =IF((D$34-$E$15)>=1,-$E$22*(1+Supuestos!$B$5)^MAX(D$34-1,0)-$E$23*D36,0) | E37: =IF((E$34-$E$15)>=1,-$E$22*(1+Supuestos!$B$5)^MAX(E$34-1,0)-$E$23*E36,0) | F37: =IF((F$34-$E$15)>=1,-$E$22*(1+Supuestos!$B$5)^MAX(F$34-1,0)-$E$23*F36,0) | G37: =IF((G$34-$E$15)>=1,-$E$22*(1+Supuestos!$B$5)^MAX(G$34-1,0)-$E$23*G36,0) | H37: =IF((H$34-$E$15)>=1,-$E$22*(1+Supuestos!$B$5)^MAX(H$34-1,0)-$E$23*H36,0) | I37: =IF((I$34-$E$15)>=1,-$E$22*(1+Supuestos!$B$5)^MAX(I$34-1,0)-$E$23*I36,0) | J37: =IF((J$34-$E$15)>=1,-$E$22*(1+Supuestos!$B$5)^MAX(J$34-1,0)-$E$23*J36,0) | ... W37: =IF((W$34-$E$15)>=1,-$E$22*(1+Supuestos!$B$5)^MAX(W$34-1,0)-$E$23*W36,0)
A38: Impuestos - fase 1 | C38: =-$E$24*C36 | D38: =-$E$24*D36 | E38: =-$E$24*E36 | F38: =-$E$24*F36 | G38: =-$E$24*G36 | H38: =-$E$24*H36 | I38: =-$E$24*I36 | J38: =-$E$24*J36 | ... W38: =-$E$24*W36
A39: Reposiciones - fase 1 | C39: =IF((C$34-$E$15)=$E$28,-$E$29*(1+Supuestos!$B$5)^MAX(C$34-1,0)*Supuestos!$B$22,0)+IF((C$34-$E$15)=$E$30,-$E$31*(1+Supuestos!$B$5)^MAX(C$34-1,0)*Supuestos!$B$22,0) | D39: =IF((D$34-$E$15)=$E$28,-$E$29*(1+Supuestos!$B$5)^MAX(D$34-1,0)*Supuestos!$B$22,0)+IF((D$34-$E$15)=$E$30,-$E$31*(1+Supuestos!$B$5)^MAX(D$34-1,0)*Supuestos!$B$22,0) | E39: =IF((E$34-$E$15)=$E$28,-$E$29*(1+Supuestos!$B$5)^MAX(E$34-1,0)*Supuestos!$B$22,0)+IF((E$34-$E$15)=$E$30,-$E$31*(1+Supuestos!$B$5)^MAX(E$34-1,0)*Supuestos!$B$22,0) | F39: =IF((F$34-$E$15)=$E$28,-$E$29*(1+Supuestos!$B$5)^MAX(F$34-1,0)*Supuestos!$B$22,0)+IF((F$34-$E$15)=$E$30,-$E$31*(1+Supuestos!$B$5)^MAX(F$34-1,0)*Supuestos!$B$22,0) | G39: =IF((G$34-$E$15)=$E$28,-$E$29*(1+Supuestos!$B$5)^MAX(G$34-1,0)*Supuestos!$B$22,0)+IF((G$34-$E$15)=$E$30,-$E$31*(1+Supuestos!$B$5)^MAX(G$34-1,0)*Supuestos!$B$22,0) | H39: =IF((H$34-$E$15)=$E$28,-$E$29*(1+Supuestos!$B$5)^MAX(H$34-1,0)*Supuestos!$B$22,0)+IF((H$34-$E$15)=$E$30,-$E$31*(1+Supuestos!$B$5)^MAX(H$34-1,0)*Supuestos!$B$22,0) | I39: =IF((I$34-$E$15)=$E$28,-$E$29*(1+Supuestos!$B$5)^MAX(I$34-1,0)*Supuestos!$B$22,0)+IF((I$34-$E$15)=$E$30,-$E$31*(1+Supuestos!$B$5)^MAX(I$34-1,0)*Supuestos!$B$22,0) | J39: =IF((J$34-$E$15)=$E$28,-$E$29*(1+Supuestos!$B$5)^MAX(J$34-1,0)*Supuestos!$B$22,0)+IF((J$34-$E$15)=$E$30,-$E$31*(1+Supuestos!$B$5)^MAX(J$34-1,0)*Supuestos!$B$22,0) | ... W39: =IF((W$34-$E$15)=$E$28,-$E$29*(1+Supuestos!$B$5)^MAX(W$34-1,0)*Supuestos!$B$22,0)+IF((W$34-$E$15)=$E$30,-$E$31*(1+Supuestos!$B$5)^MAX(W$34-1,0)*Supuestos!$B$22,0)
A40: Valor residual (año 20) - fase 1 | C40: =IF(AND(C$34=20,$E$27>1),$E$14*(1+Supuestos!$B$5)^MAX($E$15-1,0)*MAX(0,1-(20-$E$15)/$E$27),0) | D40: =IF(AND(D$34=20,$E$27>1),$E$14*(1+Supuestos!$B$5)^MAX($E$15-1,0)*MAX(0,1-(20-$E$15)/$E$27),0) | E40: =IF(AND(E$34=20,$E$27>1),$E$14*(1+Supuestos!$B$5)^MAX($E$15-1,0)*MAX(0,1-(20-$E$15)/$E$27),0) | F40: =IF(AND(F$34=20,$E$27>1),$E$14*(1+Supuestos!$B$5)^MAX($E$15-1,0)*MAX(0,1-(20-$E$15)/$E$27),0) | G40: =IF(AND(G$34=20,$E$27>1),$E$14*(1+Supuestos!$B$5)^MAX($E$15-1,0)*MAX(0,1-(20-$E$15)/$E$27),0) | H40: =IF(AND(H$34=20,$E$27>1),$E$14*(1+Supuestos!$B$5)^MAX($E$15-1,0)*MAX(0,1-(20-$E$15)/$E$27),0) | I40: =IF(AND(I$34=20,$E$27>1),$E$14*(1+Supuestos!$B$5)^MAX($E$15-1,0)*MAX(0,1-(20-$E$15)/$E$27),0) | J40: =IF(AND(J$34=20,$E$27>1),$E$14*(1+Supuestos!$B$5)^MAX($E$15-1,0)*MAX(0,1-(20-$E$15)/$E$27),0) | ... W40: =IF(AND(W$34=20,$E$27>1),$E$14*(1+Supuestos!$B$5)^MAX($E$15-1,0)*MAX(0,1-(20-$E$15)/$E$27),0)
A41: Inversión | C41: =C35 | D41: =D35 | E41: =E35 | F41: =F35 | G41: =G35 | H41: =H35 | I41: =I35 | J41: =J35 | ... W41: =W35
A42: Ingresos cobrados | C42: =C36 | D42: =D36 | E42: =E36 | F42: =F36 | G42: =G36 | H42: =H36 | I42: =I36 | J42: =J36 | ... W42: =W36
A43: Gastos | C43: =C37 | D43: =D37 | E43: =E37 | F43: =F37 | G43: =G37 | H43: =H37 | I43: =I37 | J43: =J37 | ... W43: =W37
A44: Impuestos | C44: =C38 | D44: =D38 | E44: =E38 | F44: =F38 | G44: =G38 | H44: =H38 | I44: =I38 | J44: =J38 | ... W44: =W38
A45: Reposiciones | C45: =C39 | D45: =D39 | E45: =E39 | F45: =F39 | G45: =G39 | H45: =H39 | I45: =I39 | J45: =J39 | ... W45: =W39
A46: Valor residual (año 20) | C46: =C40 | D46: =D40 | E46: =E40 | F46: =F40 | G46: =G40 | H46: =H40 | I46: =I40 | J46: =J40 | ... W46: =W40
A47: FLUJO NETO | C47: =C41+C42+C43+C44+C45+C46 | D47: =D41+D42+D43+D44+D45+D46 | E47: =E41+E42+E43+E44+E45+E46 | F47: =F41+F42+F43+F44+F45+F46 | G47: =G41+G42+G43+G44+G45+G46 | H47: =H41+H42+H43+H44+H45+H46 | I47: =I41+I42+I43+I44+I45+I46 | J47: =J41+J42+J43+J44+J45+J46 | ... W47: =W41+W42+W43+W44+W45+W46
A48: Caja acumulada (sin valor residual) | C48: =C47-C46 | D48: =C48+D47-D46 | E48: =D48+E47-E46 | F48: =E48+F47-F46 | G48: =F48+G47-G46 | H48: =G48+H47-H46 | I48: =H48+I47-I46 | J48: =I48+J47-J46 | K48: =J48+K47-K46 | ... W48: =V48+W47-W46
A49: Flujo del propietario contando el terreno (lo aporta hoy y lo recupera valorizado) | C49: =C47-Supuestos!$B$21 | D49: =D47 | E49: =E47 | F49: =F47 | G49: =G47 | H49: =H47 | I49: =I47 | J49: =J47 | K49: =K47 | ... V49: =V47 | W49: =W47+Supuestos!$B$21*(1+Supuestos!$B$23)^20
A51: Inversión total | C51: =-SUM(C41:W41)
A52: VAN al 10% | C52: =C47+NPV(Supuestos!$B$4,D47:W47)
A53: TIR | C53: =IFERROR(IRR(C47:W47),IFERROR(IRR(C47:W47,-0.05),"no aplica"))
A54: Año en que se recupera la inversión (acumulado ≥ 0) | C54: =IF(-SUM(C41:W41)=0,"sin inversión",IFERROR(INDEX(C34:W34,MATCH(TRUE,INDEX(C48:W48>=0,0),0)),"no en 20 años"))
A55: Caja neta del año 5 sin inversiones (S/ nominales) | C55: =H47-H41
A56: TIR contando el terreno | C56: =IFERROR(IRR(C49:W49),"no aplica")

Sheet G Local de eventos
A1: G. Local de eventos (salón de recepciones)
A2: Salón techado de 420 m² con cocina de servicio, SS.HH., mobiliario y patio de ingreso.
A4: Fase 1: Local de eventos
A5: Partida | B5: Und. | C5: Cantidad | D5: P. unitario | E5: Parcial
A6: Salón de 420 m²: estructura metálica, muros, piso cerámico, cielo raso y acústica básica | B6: m² | C6: 420 | D6: 950 | E6: =C6*D6
A7: Cocina de servicio, SS.HH. y depósito | B7: m² | C7: 50 | D7: 1400 | E7: =C7*D7
A8: Mobiliario, sonido e iluminación decorativa | B8: glb | C8: 1 | D8: 30000 | E8: =C8*D8
A9: Patio de ingreso afirmado | B9: m² | C9: 300 | D9: 40 | E9: =C9*D9
A10: Expediente, licencias, ITSE previa y aforo | B10: glb | C10: 1 | D10: 18000 | E10: =C10*D10
D11: Inversión (con imprevistos y factor de escenario) | E11: =SUM(E6:E10)*(1+Supuestos!$B$6)*Supuestos!$B$22
D12: Año de inversión (opera desde el año siguiente) | E12: 0
D13: Ingreso bruto potencial S/ por mes - pesimista | E13: 1200
D14: Ingreso bruto potencial S/ por mes - base | E14: 3000
D15: Ingreso bruto potencial S/ por mes - optimista | E15: 6000
D16: Ocupación cobrada - pesimista | E16: 1
D17: Ocupación cobrada - base | E17: 1
D18: Ocupación cobrada - optimista | E18: 1
D19: Gastos fijos S/ por año (personal, energía, mantenimiento, seguro, predial) | E19: 22300
D20: Gastos variables (% del ingreso cobrado) | E20: 0.2
D21: Impuestos (% del ingreso cobrado) | E21: 0.1
D22: Ingreso relativo 1.er año de operación | E22: 0.6
D23: Ingreso relativo 2.º año de operación | E23: 0.85
D24: Vida útil para valor residual (años) | E24: 40
A26: FLUJO DE CAJA (S/ nominales)
A27: Concepto / año | C27: 0 | D27: 1 | E27: 2 | F27: 3 | G27: 4 | H27: 5 | I27: 6 | J27: 7 | K27: 8 | L27: 9 | M27: 10 | N27: 11 | O27: 12 | P27: 13 | Q27: 14 | R27: 15 | S27: 16 | T27: 17 | U27: 18 | V27: 19 | W27: 20
A28: Inversión - fase 1 | C28: =IF(C$27=$E$12,-$E$11*(1+Supuestos!$B$5)^MAX($E$12-1,0),0) | D28: =IF(D$27=$E$12,-$E$11*(1+Supuestos!$B$5)^MAX($E$12-1,0),0) | E28: =IF(E$27=$E$12,-$E$11*(1+Supuestos!$B$5)^MAX($E$12-1,0),0) | F28: =IF(F$27=$E$12,-$E$11*(1+Supuestos!$B$5)^MAX($E$12-1,0),0) | G28: =IF(G$27=$E$12,-$E$11*(1+Supuestos!$B$5)^MAX($E$12-1,0),0) | H28: =IF(H$27=$E$12,-$E$11*(1+Supuestos!$B$5)^MAX($E$12-1,0),0) | I28: =IF(I$27=$E$12,-$E$11*(1+Supuestos!$B$5)^MAX($E$12-1,0),0) | J28: =IF(J$27=$E$12,-$E$11*(1+Supuestos!$B$5)^MAX($E$12-1,0),0) | ... W28: =IF(W$27=$E$12,-$E$11*(1+Supuestos!$B$5)^MAX($E$12-1,0),0)
A29: Ingresos cobrados - fase 1 | C29: =IF((C$27-$E$12)>=1,CHOOSE(Supuestos!$B$3,$E$13,$E$14,$E$15)*12*CHOOSE(Supuestos!$B$3,$E$16,$E$17,$E$18)*IF((C$27-$E$12)=1,$E$22,IF((C$27-$E$12)=2,$E$23,1))*(1+Supuestos!$B$5)^MAX(C$27-1,0),0) | D29: =IF((D$27-$E$12)>=1,CHOOSE(Supuestos!$B$3,$E$13,$E$14,$E$15)*12*CHOOSE(Supuestos!$B$3,$E$16,$E$17,$E$18)*IF((D$27-$E$12)=1,$E$22,IF((D$27-$E$12)=2,$E$23,1))*(1+Supuestos!$B$5)^MAX(D$27-1,0),0) | E29: =IF((E$27-$E$12)>=1,CHOOSE(Supuestos!$B$3,$E$13,$E$14,$E$15)*12*CHOOSE(Supuestos!$B$3,$E$16,$E$17,$E$18)*IF((E$27-$E$12)=1,$E$22,IF((E$27-$E$12)=2,$E$23,1))*(1+Supuestos!$B$5)^MAX(E$27-1,0),0) | F29: =IF((F$27-$E$12)>=1,CHOOSE(Supuestos!$B$3,$E$13,$E$14,$E$15)*12*CHOOSE(Supuestos!$B$3,$E$16,$E$17,$E$18)*IF((F$27-$E$12)=1,$E$22,IF((F$27-$E$12)=2,$E$23,1))*(1+Supuestos!$B$5)^MAX(F$27-1,0),0) | G29: =IF((G$27-$E$12)>=1,CHOOSE(Supuestos!$B$3,$E$13,$E$14,$E$15)*12*CHOOSE(Supuestos!$B$3,$E$16,$E$17,$E$18)*IF((G$27-$E$12)=1,$E$22,IF((G$27-$E$12)=2,$E$23,1))*(1+Supuestos!$B$5)^MAX(G$27-1,0),0) | H29: =IF((H$27-$E$12)>=1,CHOOSE(Supuestos!$B$3,$E$13,$E$14,$E$15)*12*CHOOSE(Supuestos!$B$3,$E$16,$E$17,$E$18)*IF((H$27-$E$12)=1,$E$22,IF((H$27-$E$12)=2,$E$23,1))*(1+Supuestos!$B$5)^MAX(H$27-1,0),0) | I29: =IF((I$27-$E$12)>=1,CHOOSE(Supuestos!$B$3,$E$13,$E$14,$E$15)*12*CHOOSE(Supuestos!$B$3,$E$16,$E$17,$E$18)*IF((I$27-$E$12)=1,$E$22,IF((I$27-$E$12)=2,$E$23,1))*(1+Supuestos!$B$5)^MAX(I$27-1,0),0) | J29: =IF((J$27-$E$12)>=1,CHOOSE(Supuestos!$B$3,$E$13,$E$14,$E$15)*12*CHOOSE(Supuestos!$B$3,$E$16,$E$17,$E$18)*IF((J$27-$E$12)=1,$E$22,IF((J$27-$E$12)=2,$E$23,1))*(1+Supuestos!$B$5)^MAX(J$27-1,0),0) | ... W29: =IF((W$27-$E$12)>=1,CHOOSE(Supuestos!$B$3,$E$13,$E$14,$E$15)*12*CHOOSE(Supuestos!$B$3,$E$16,$E$17,$E$18)*IF((W$27-$E$12)=1,$E$22,IF((W$27-$E$12)=2,$E$23,1))*(1+Supuestos!$B$5)^MAX(W$27-1,0),0)
A30: Gastos - fase 1 | C30: =IF((C$27-$E$12)>=1,-$E$19*(1+Supuestos!$B$5)^MAX(C$27-1,0)-$E$20*C29,0) | D30: =IF((D$27-$E$12)>=1,-$E$19*(1+Supuestos!$B$5)^MAX(D$27-1,0)-$E$20*D29,0) | E30: =IF((E$27-$E$12)>=1,-$E$19*(1+Supuestos!$B$5)^MAX(E$27-1,0)-$E$20*E29,0) | F30: =IF((F$27-$E$12)>=1,-$E$19*(1+Supuestos!$B$5)^MAX(F$27-1,0)-$E$20*F29,0) | G30: =IF((G$27-$E$12)>=1,-$E$19*(1+Supuestos!$B$5)^MAX(G$27-1,0)-$E$20*G29,0) | H30: =IF((H$27-$E$12)>=1,-$E$19*(1+Supuestos!$B$5)^MAX(H$27-1,0)-$E$20*H29,0) | I30: =IF((I$27-$E$12)>=1,-$E$19*(1+Supuestos!$B$5)^MAX(I$27-1,0)-$E$20*I29,0) | J30: =IF((J$27-$E$12)>=1,-$E$19*(1+Supuestos!$B$5)^MAX(J$27-1,0)-$E$20*J29,0) | ... W30: =IF((W$27-$E$12)>=1,-$E$19*(1+Supuestos!$B$5)^MAX(W$27-1,0)-$E$20*W29,0)
A31: Impuestos - fase 1 | C31: =-$E$21*C29 | D31: =-$E$21*D29 | E31: =-$E$21*E29 | F31: =-$E$21*F29 | G31: =-$E$21*G29 | H31: =-$E$21*H29 | I31: =-$E$21*I29 | J31: =-$E$21*J29 | ... W31: =-$E$21*W29
A32: Reposiciones - fase 1 | C32: =0 | D32: =0 | E32: =0 | F32: =0 | G32: =0 | H32: =0 | I32: =0 | J32: =0 | ... W32: =0
A33: Valor residual (año 20) - fase 1 | C33: =IF(AND(C$27=20,$E$24>1),$E$11*(1+Supuestos!$B$5)^MAX($E$12-1,0)*MAX(0,1-(20-$E$12)/$E$24),0) | D33: =IF(AND(D$27=20,$E$24>1),$E$11*(1+Supuestos!$B$5)^MAX($E$12-1,0)*MAX(0,1-(20-$E$12)/$E$24),0) | E33: =IF(AND(E$27=20,$E$24>1),$E$11*(1+Supuestos!$B$5)^MAX($E$12-1,0)*MAX(0,1-(20-$E$12)/$E$24),0) | F33: =IF(AND(F$27=20,$E$24>1),$E$11*(1+Supuestos!$B$5)^MAX($E$12-1,0)*MAX(0,1-(20-$E$12)/$E$24),0) | G33: =IF(AND(G$27=20,$E$24>1),$E$11*(1+Supuestos!$B$5)^MAX($E$12-1,0)*MAX(0,1-(20-$E$12)/$E$24),0) | H33: =IF(AND(H$27=20,$E$24>1),$E$11*(1+Supuestos!$B$5)^MAX($E$12-1,0)*MAX(0,1-(20-$E$12)/$E$24),0) | I33: =IF(AND(I$27=20,$E$24>1),$E$11*(1+Supuestos!$B$5)^MAX($E$12-1,0)*MAX(0,1-(20-$E$12)/$E$24),0) | J33: =IF(AND(J$27=20,$E$24>1),$E$11*(1+Supuestos!$B$5)^MAX($E$12-1,0)*MAX(0,1-(20-$E$12)/$E$24),0) | ... W33: =IF(AND(W$27=20,$E$24>1),$E$11*(1+Supuestos!$B$5)^MAX($E$12-1,0)*MAX(0,1-(20-$E$12)/$E$24),0)
A34: Inversión | C34: =C28 | D34: =D28 | E34: =E28 | F34: =F28 | G34: =G28 | H34: =H28 | I34: =I28 | J34: =J28 | ... W34: =W28
A35: Ingresos cobrados | C35: =C29 | D35: =D29 | E35: =E29 | F35: =F29 | G35: =G29 | H35: =H29 | I35: =I29 | J35: =J29 | ... W35: =W29
A36: Gastos | C36: =C30 | D36: =D30 | E36: =E30 | F36: =F30 | G36: =G30 | H36: =H30 | I36: =I30 | J36: =J30 | ... W36: =W30
A37: Impuestos | C37: =C31 | D37: =D31 | E37: =E31 | F37: =F31 | G37: =G31 | H37: =H31 | I37: =I31 | J37: =J31 | ... W37: =W31
A38: Reposiciones | C38: =C32 | D38: =D32 | E38: =E32 | F38: =F32 | G38: =G32 | H38: =H32 | I38: =I32 | J38: =J32 | ... W38: =W32
A39: Valor residual (año 20) | C39: =C33 | D39: =D33 | E39: =E33 | F39: =F33 | G39: =G33 | H39: =H33 | I39: =I33 | J39: =J33 | ... W39: =W33
A40: FLUJO NETO | C40: =C34+C35+C36+C37+C38+C39 | D40: =D34+D35+D36+D37+D38+D39 | E40: =E34+E35+E36+E37+E38+E39 | F40: =F34+F35+F36+F37+F38+F39 | G40: =G34+G35+G36+G37+G38+G39 | H40: =H34+H35+H36+H37+H38+H39 | I40: =I34+I35+I36+I37+I38+I39 | J40: =J34+J35+J36+J37+J38+J39 | ... W40: =W34+W35+W36+W37+W38+W39
A41: Caja acumulada (sin valor residual) | C41: =C40-C39 | D41: =C41+D40-D39 | E41: =D41+E40-E39 | F41: =E41+F40-F39 | G41: =F41+G40-G39 | H41: =G41+H40-H39 | I41: =H41+I40-I39 | J41: =I41+J40-J39 | K41: =J41+K40-K39 | ... W41: =V41+W40-W39
A42: Flujo del propietario contando el terreno (lo aporta hoy y lo recupera valorizado) | C42: =C40-Supuestos!$B$21 | D42: =D40 | E42: =E40 | F42: =F40 | G42: =G40 | H42: =H40 | I42: =I40 | J42: =J40 | K42: =K40 | ... V42: =V40 | W42: =W40+Supuestos!$B$21*(1+Supuestos!$B$23)^20
A44: Inversión total | C44: =-SUM(C34:W34)
A45: VAN al 10% | C45: =C40+NPV(Supuestos!$B$4,D40:W40)
A46: TIR | C46: =IFERROR(IRR(C40:W40),IFERROR(IRR(C40:W40,-0.05),"no aplica"))
A47: Año en que se recupera la inversión (acumulado ≥ 0) | C47: =IF(-SUM(C34:W34)=0,"sin inversión",IFERROR(INDEX(C27:W27,MATCH(TRUE,INDEX(C41:W41>=0,0),0)),"no en 20 años"))
A48: Caja neta del año 5 sin inversiones (S/ nominales) | C48: =H40-H34
A49: TIR contando el terreno | C49: =IFERROR(IRR(C42:W42),"no aplica")

Sheet E C + consultorios
A1: E. C + 1 piso de consultorios (año 2)
A2: Fase 1 igual a C. En el año 2, un piso con 7 consultorios, ascensor y SS.HH. accesible para médicos, odontólogos, laboratorio u óptica.
A4: Fase 1: Local de esquina (100 m²)
A5: Partida | B5: Und. | C5: Cantidad | D5: P. unitario | E5: Parcial
A6: Local de esquina de 100 m² en pórticos de C.A. diseñados para 3 pisos, puertas enrollables y SS.HH. | B6: m² | C6: 100 | D6: 1500 | E6: =C6*D6
A7: Estudio de suelos, proyecto y licencia | B7: glb | C7: 1 | D7: 20000 | E7: =C7*D7
D8: Inversión (con imprevistos y factor de escenario) | E8: =SUM(E6:E7)*(1+Supuestos!$B$6)*Supuestos!$B$22
D9: Año de inversión (opera desde el año siguiente) | E9: 0
D10: Ingreso bruto potencial S/ por mes - pesimista | E10: 1000
D11: Ingreso bruto potencial S/ por mes - base | E11: 1300
D12: Ingreso bruto potencial S/ por mes - optimista | E12: 2000
D13: Ocupación cobrada - pesimista | E13: 0.7
D14: Ocupación cobrada - base | E14: 0.8
D15: Ocupación cobrada - optimista | E15: 0.9
D16: Gastos fijos S/ por año (personal, energía, mantenimiento, seguro, predial) | E16: 2500
D17: Gastos variables (% del ingreso cobrado) | E17: 0
D18: Impuestos (% del ingreso cobrado) | E18: 0.05
D19: Ingreso relativo 1.er año de operación | E19: 0.5
D20: Ingreso relativo 2.º año de operación | E20: 0.8
D21: Vida útil para valor residual (años) | E21: 50
A23: Fase 2: 3 locales al jirón + núcleo de escalera
A24: Partida | B24: Und. | C24: Cantidad | D24: P. unitario | E24: Parcial
A25: 3 locales de 39-48 m² (134.7 m²) y núcleo de escalera, SS.HH. y depósito de 26 m² junto a B, en pórticos de C.A. diseñados para 3 pisos | B25: m² | C25: 160.6 | D25: 1500 | E25: =C25*D25
A26: Ampliación del proyecto y licencia | B26: glb | C26: 1 | D26: 12000 | E26: =C26*D26
D27: Inversión (con imprevistos y factor de escenario) | E27: =SUM(E25:E26)*(1+Supuestos!$B$6)*Supuestos!$B$22
D28: Año de inversión (opera desde el año siguiente) | E28: 0
D29: Ingreso bruto potencial S/ por mes - pesimista | E29: 1616.4
D30: Ingreso bruto potencial S/ por mes - base | E30: 2020.5
D31: Ingreso bruto potencial S/ por mes - optimista | E31: 2424.6
D32: Ocupación cobrada - pesimista | E32: 0.7
D33: Ocupación cobrada - base | E33: 0.8
D34: Ocupación cobrada - optimista | E34: 0.9
D35: Gastos fijos S/ por año (personal, energía, mantenimiento, seguro, predial) | E35: 3600
D36: Gastos variables (% del ingreso cobrado) | E36: 0
D37: Impuestos (% del ingreso cobrado) | E37: 0.05
D38: Ingreso relativo 1.er año de operación | E38: 0.5
D39: Ingreso relativo 2.º año de operación | E39: 0.8
D40: Vida útil para valor residual (años) | E40: 50
A42: Fase 3: Cochera de abonados (fondo, descubierta)
A43: Partida | B43: Und. | C43: Cantidad | D43: P. unitario | E43: Parcial
A44: Afirmado compactado e=0.20 m con bombeo | B44: m² | C44: 540 | D44: 40 | E44: =C44*D44
A45: Drenaje del patio | B45: ml | C45: 20 | D45: 220 | E45: =C45*D45
A46: Portón telescópico automatizado de 6.5 m con 40 controles + puerta peatonal | B46: glb | C46: 1 | D46: 15500 | E46: =C46*D46
A47: Cerco de albañilería en el fondo C-D | B47: ml | C47: 30 | D47: 330 | E47: =C47*D47
A48: Iluminación LED y CCTV de 4 cámaras | B48: glb | C48: 1 | D48: 7500 | E48: =C48*D48
A49: Señalización, numeración y topellantas | B49: glb | C49: 1 | D49: 2400 | E49: =C49*D49
D50: Inversión (con imprevistos y factor de escenario) | E50: =SUM(E44:E49)*(1+Supuestos!$B$6)*Supuestos!$B$22
D51: Año de inversión (opera desde el año siguiente) | E51: 0
D52: Ingreso bruto potencial S/ por mes - pesimista | E52: 480
D53: Ingreso bruto potencial S/ por mes - base | E53: 900
D54: Ingreso bruto potencial S/ por mes - optimista | E54: 1080
D55: Ocupación cobrada - pesimista | E55: 0.6
D56: Ocupación cobrada - base | E56: 0.7
D57: Ocupación cobrada - optimista | E57: 0.8
D58: Gastos fijos S/ por año (personal, energía, mantenimiento, seguro, predial) | E58: 3200
D59: Gastos variables (% del ingreso cobrado) | E59: 0
D60: Impuestos (% del ingreso cobrado) | E60: 0
D61: Ingreso relativo 1.er año de operación | E61: 0.6
D62: Ingreso relativo 2.º año de operación | E62: 0.85
... D65: Reposición 1: monto a precios de hoy | E65: 33330
A67: Fase 4: 1 piso de consultorios
A68: Partida | B68: Und. | C68: Cantidad | D68: P. unitario | E68: Parcial
A69: 1 piso sobre los locales: 7 consultorios de 15-20 m² con lavatorio, sala de espera y SS.HH. accesible | B69: m² | C69: 260.6 | D69: 1650 | E69: =C69*D69
A70: Ascensor de 2 paradas con pozo | B70: glb | C70: 1 | D70: 85000 | E70: =C70*D70
A71: Proyecto y licencia (Modalidad D por uso salud) | B71: glb | C71: 1 | D71: 18000 | E71: =C71*D71
D72: Inversión (con imprevistos y factor de escenario) | E72: =SUM(E69:E71)*(1+Supuestos!$B$6)*Supuestos!$B$22
D73: Año de inversión (opera desde el año siguiente) | E73: 2
D74: Ingreso bruto potencial S/ por mes - pesimista | E74: 2100
D75: Ingreso bruto potencial S/ por mes - base | E75: 2800
D76: Ingreso bruto potencial S/ por mes - optimista | E76: 3500
D77: Ocupación cobrada - pesimista | E77: 0.6
D78: Ocupación cobrada - base | E78: 0.7
D79: Ocupación cobrada - optimista | E79: 0.85
D80: Gastos fijos S/ por año (personal, energía, mantenimiento, seguro, predial) | E80: 11600
D81: Gastos variables (% del ingreso cobrado) | E81: 0
D82: Impuestos (% del ingreso cobrado) | E82: 0.05
D83: Ingreso relativo 1.er año de operación | E83: 0.5
D84: Ingreso relativo 2.º año de operación | E84: 0.85
D85: Vida útil para valor residual (años) | E85: 50
A87: FLUJO DE CAJA (S/ nominales)
A88: Concepto / año | C88: 0 | D88: 1 | E88: 2 | F88: 3 | G88: 4 | H88: 5 | I88: 6 | J88: 7 | K88: 8 | L88: 9 | M88: 10 | N88: 11 | O88: 12 | P88: 13 | Q88: 14 | R88: 15 | S88: 16 | T88: 17 | U88: 18 | V88: 19 | W88: 20
A89: Inversión - fase 1 | C89: =IF(C$88=$E$9,-$E$8*(1+Supuestos!$B$5)^MAX($E$9-1,0),0) | D89: =IF(D$88=$E$9,-$E$8*(1+Supuestos!$B$5)^MAX($E$9-1,0),0) | E89: =IF(E$88=$E$9,-$E$8*(1+Supuestos!$B$5)^MAX($E$9-1,0),0) | F89: =IF(F$88=$E$9,-$E$8*(1+Supuestos!$B$5)^MAX($E$9-1,0),0) | G89: =IF(G$88=$E$9,-$E$8*(1+Supuestos!$B$5)^MAX($E$9-1,0),0) | H89: =IF(H$88=$E$9,-$E$8*(1+Supuestos!$B$5)^MAX($E$9-1,0),0) | I89: =IF(I$88=$E$9,-$E$8*(1+Supuestos!$B$5)^MAX($E$9-1,0),0) | J89: =IF(J$88=$E$9,-$E$8*(1+Supuestos!$B$5)^MAX($E$9-1,0),0) | ... W89: =IF(W$88=$E$9,-$E$8*(1+Supuestos!$B$5)^MAX($E$9-1,0),0)
A90: Ingresos cobrados - fase 1 | C90: =IF((C$88-$E$9)>=1,CHOOSE(Supuestos!$B$3,$E$10,$E$11,$E$12)*12*CHOOSE(Supuestos!$B$3,$E$13,$E$14,$E$15)*IF((C$88-$E$9)=1,$E$19,IF((C$88-$E$9)=2,$E$20,1))*(1+Supuestos!$B$5)^MAX(C$88-1,0),0) | D90: =IF((D$88-$E$9)>=1,CHOOSE(Supuestos!$B$3,$E$10,$E$11,$E$12)*12*CHOOSE(Supuestos!$B$3,$E$13,$E$14,$E$15)*IF((D$88-$E$9)=1,$E$19,IF((D$88-$E$9)=2,$E$20,1))*(1+Supuestos!$B$5)^MAX(D$88-1,0),0) | E90: =IF((E$88-$E$9)>=1,CHOOSE(Supuestos!$B$3,$E$10,$E$11,$E$12)*12*CHOOSE(Supuestos!$B$3,$E$13,$E$14,$E$15)*IF((E$88-$E$9)=1,$E$19,IF((E$88-$E$9)=2,$E$20,1))*(1+Supuestos!$B$5)^MAX(E$88-1,0),0) | F90: =IF((F$88-$E$9)>=1,CHOOSE(Supuestos!$B$3,$E$10,$E$11,$E$12)*12*CHOOSE(Supuestos!$B$3,$E$13,$E$14,$E$15)*IF((F$88-$E$9)=1,$E$19,IF((F$88-$E$9)=2,$E$20,1))*(1+Supuestos!$B$5)^MAX(F$88-1,0),0) | G90: =IF((G$88-$E$9)>=1,CHOOSE(Supuestos!$B$3,$E$10,$E$11,$E$12)*12*CHOOSE(Supuestos!$B$3,$E$13,$E$14,$E$15)*IF((G$88-$E$9)=1,$E$19,IF((G$88-$E$9)=2,$E$20,1))*(1+Supuestos!$B$5)^MAX(G$88-1,0),0) | H90: =IF((H$88-$E$9)>=1,CHOOSE(Supuestos!$B$3,$E$10,$E$11,$E$12)*12*CHOOSE(Supuestos!$B$3,$E$13,$E$14,$E$15)*IF((H$88-$E$9)=1,$E$19,IF((H$88-$E$9)=2,$E$20,1))*(1+Supuestos!$B$5)^MAX(H$88-1,0),0) | I90: =IF((I$88-$E$9)>=1,CHOOSE(Supuestos!$B$3,$E$10,$E$11,$E$12)*12*CHOOSE(Supuestos!$B$3,$E$13,$E$14,$E$15)*IF((I$88-$E$9)=1,$E$19,IF((I$88-$E$9)=2,$E$20,1))*(1+Supuestos!$B$5)^MAX(I$88-1,0),0) | J90: =IF((J$88-$E$9)>=1,CHOOSE(Supuestos!$B$3,$E$10,$E$11,$E$12)*12*CHOOSE(Supuestos!$B$3,$E$13,$E$14,$E$15)*IF((J$88-$E$9)=1,$E$19,IF((J$88-$E$9)=2,$E$20,1))*(1+Supuestos!$B$5)^MAX(J$88-1,0),0) | ... W90: =IF((W$88-$E$9)>=1,CHOOSE(Supuestos!$B$3,$E$10,$E$11,$E$12)*12*CHOOSE(Supuestos!$B$3,$E$13,$E$14,$E$15)*IF((W$88-$E$9)=1,$E$19,IF((W$88-$E$9)=2,$E$20,1))*(1+Supuestos!$B$5)^MAX(W$88-1,0),0)
A91: Gastos - fase 1 | C91: =IF((C$88-$E$9)>=1,-$E$16*(1+Supuestos!$B$5)^MAX(C$88-1,0)-$E$17*C90,0) | D91: =IF((D$88-$E$9)>=1,-$E$16*(1+Supuestos!$B$5)^MAX(D$88-1,0)-$E$17*D90,0) | E91: =IF((E$88-$E$9)>=1,-$E$16*(1+Supuestos!$B$5)^MAX(E$88-1,0)-$E$17*E90,0) | F91: =IF((F$88-$E$9)>=1,-$E$16*(1+Supuestos!$B$5)^MAX(F$88-1,0)-$E$17*F90,0) | G91: =IF((G$88-$E$9)>=1,-$E$16*(1+Supuestos!$B$5)^MAX(G$88-1,0)-$E$17*G90,0) | H91: =IF((H$88-$E$9)>=1,-$E$16*(1+Supuestos!$B$5)^MAX(H$88-1,0)-$E$17*H90,0) | I91: =IF((I$88-$E$9)>=1,-$E$16*(1+Supuestos!$B$5)^MAX(I$88-1,0)-$E$17*I90,0) | J91: =IF((J$88-$E$9)>=1,-$E$16*(1+Supuestos!$B$5)^MAX(J$88-1,0)-$E$17*J90,0) | ... W91: =IF((W$88-$E$9)>=1,-$E$16*(1+Supuestos!$B$5)^MAX(W$88-1,0)-$E$17*W90,0)
A92: Impuestos - fase 1 | C92: =-$E$18*C90 | D92: =-$E$18*D90 | E92: =-$E$18*E90 | F92: =-$E$18*F90 | G92: =-$E$18*G90 | H92: =-$E$18*H90 | I92: =-$E$18*I90 | J92: =-$E$18*J90 | ... W92: =-$E$18*W90
A93: Reposiciones - fase 1 | C93: =0 | D93: =0 | E93: =0 | F93: =0 | G93: =0 | H93: =0 | I93: =0 | J93: =0 | ... W93: =0
A94: Valor residual (año 20) - fase 1 | C94: =IF(AND(C$88=20,$E$21>1),$E$8*(1+Supuestos!$B$5)^MAX($E$9-1,0)*MAX(0,1-(20-$E$9)/$E$21),0) | D94: =IF(AND(D$88=20,$E$21>1),$E$8*(1+Supuestos!$B$5)^MAX($E$9-1,0)*MAX(0,1-(20-$E$9)/$E$21),0) | E94: =IF(AND(E$88=20,$E$21>1),$E$8*(1+Supuestos!$B$5)^MAX($E$9-1,0)*MAX(0,1-(20-$E$9)/$E$21),0) | F94: =IF(AND(F$88=20,$E$21>1),$E$8*(1+Supuestos!$B$5)^MAX($E$9-1,0)*MAX(0,1-(20-$E$9)/$E$21),0) | G94: =IF(AND(G$88=20,$E$21>1),$E$8*(1+Supuestos!$B$5)^MAX($E$9-1,0)*MAX(0,1-(20-$E$9)/$E$21),0) | H94: =IF(AND(H$88=20,$E$21>1),$E$8*(1+Supuestos!$B$5)^MAX($E$9-1,0)*MAX(0,1-(20-$E$9)/$E$21),0) | I94: =IF(AND(I$88=20,$E$21>1),$E$8*(1+Supuestos!$B$5)^MAX($E$9-1,0)*MAX(0,1-(20-$E$9)/$E$21),0) | J94: =IF(AND(J$88=20,$E$21>1),$E$8*(1+Supuestos!$B$5)^MAX($E$9-1,0)*MAX(0,1-(20-$E$9)/$E$21),0) | ... W94: =IF(AND(W$88=20,$E$21>1),$E$8*(1+Supuestos!$B$5)^MAX($E$9-1,0)*MAX(0,1-(20-$E$9)/$E$21),0)
A95: Inversión - fase 2 | C95: =IF(C$88=$E$28,-$E$27*(1+Supuestos!$B$5)^MAX($E$28-1,0),0) | D95: =IF(D$88=$E$28,-$E$27*(1+Supuestos!$B$5)^MAX($E$28-1,0),0) | E95: =IF(E$88=$E$28,-$E$27*(1+Supuestos!$B$5)^MAX($E$28-1,0),0) | F95: =IF(F$88=$E$28,-$E$27*(1+Supuestos!$B$5)^MAX($E$28-1,0),0) | G95: =IF(G$88=$E$28,-$E$27*(1+Supuestos!$B$5)^MAX($E$28-1,0),0) | H95: =IF(H$88=$E$28,-$E$27*(1+Supuestos!$B$5)^MAX($E$28-1,0),0) | I95: =IF(I$88=$E$28,-$E$27*(1+Supuestos!$B$5)^MAX($E$28-1,0),0) | J95: =IF(J$88=$E$28,-$E$27*(1+Supuestos!$B$5)^MAX($E$28-1,0),0) | ... W95: =IF(W$88=$E$28,-$E$27*(1+Supuestos!$B$5)^MAX($E$28-1,0),0)
A96: Ingresos cobrados - fase 2 | C96: =IF((C$88-$E$28)>=1,CHOOSE(Supuestos!$B$3,$E$29,$E$30,$E$31)*12*CHOOSE(Supuestos!$B$3,$E$32,$E$33,$E$34)*IF((C$88-$E$28)=1,$E$38,IF((C$88-$E$28)=2,$E$39,1))*(1+Supuestos!$B$5)^MAX(C$88-1,0),0) | D96: =IF((D$88-$E$28)>=1,CHOOSE(Supuestos!$B$3,$E$29,$E$30,$E$31)*12*CHOOSE(Supuestos!$B$3,$E$32,$E$33,$E$34)*IF((D$88-$E$28)=1,$E$38,IF((D$88-$E$28)=2,$E$39,1))*(1+Supuestos!$B$5)^MAX(D$88-1,0),0) | E96: =IF((E$88-$E$28)>=1,CHOOSE(Supuestos!$B$3,$E$29,$E$30,$E$31)*12*CHOOSE(Supuestos!$B$3,$E$32,$E$33,$E$34)*IF((E$88-$E$28)=1,$E$38,IF((E$88-$E$28)=2,$E$39,1))*(1+Supuestos!$B$5)^MAX(E$88-1,0),0) | F96: =IF((F$88-$E$28)>=1,CHOOSE(Supuestos!$B$3,$E$29,$E$30,$E$31)*12*CHOOSE(Supuestos!$B$3,$E$32,$E$33,$E$34)*IF((F$88-$E$28)=1,$E$38,IF((F$88-$E$28)=2,$E$39,1))*(1+Supuestos!$B$5)^MAX(F$88-1,0),0) | G96: =IF((G$88-$E$28)>=1,CHOOSE(Supuestos!$B$3,$E$29,$E$30,$E$31)*12*CHOOSE(Supuestos!$B$3,$E$32,$E$33,$E$34)*IF((G$88-$E$28)=1,$E$38,IF((G$88-$E$28)=2,$E$39,1))*(1+Supuestos!$B$5)^MAX(G$88-1,0),0) | H96: =IF((H$88-$E$28)>=1,CHOOSE(Supuestos!$B$3,$E$29,$E$30,$E$31)*12*CHOOSE(Supuestos!$B$3,$E$32,$E$33,$E$34)*IF((H$88-$E$28)=1,$E$38,IF((H$88-$E$28)=2,$E$39,1))*(1+Supuestos!$B$5)^MAX(H$88-1,0),0) | I96: =IF((I$88-$E$28)>=1,CHOOSE(Supuestos!$B$3,$E$29,$E$30,$E$31)*12*CHOOSE(Supuestos!$B$3,$E$32,$E$33,$E$34)*IF((I$88-$E$28)=1,$E$38,IF((I$88-$E$28)=2,$E$39,1))*(1+Supuestos!$B$5)^MAX(I$88-1,0),0) | J96: =IF((J$88-$E$28)>=1,CHOOSE(Supuestos!$B$3,$E$29,$E$30,$E$31)*12*CHOOSE(Supuestos!$B$3,$E$32,$E$33,$E$34)*IF((J$88-$E$28)=1,$E$38,IF((J$88-$E$28)=2,$E$39,1))*(1+Supuestos!$B$5)^MAX(J$88-1,0),0) | ... W96: =IF((W$88-$E$28)>=1,CHOOSE(Supuestos!$B$3,$E$29,$E$30,$E$31)*12*CHOOSE(Supuestos!$B$3,$E$32,$E$33,$E$34)*IF((W$88-$E$28)=1,$E$38,IF((W$88-$E$28)=2,$E$39,1))*(1+Supuestos!$B$5)^MAX(W$88-1,0),0)
A97: Gastos - fase 2 | C97: =IF((C$88-$E$28)>=1,-$E$35*(1+Supuestos!$B$5)^MAX(C$88-1,0)-$E$36*C96,0) | D97: =IF((D$88-$E$28)>=1,-$E$35*(1+Supuestos!$B$5)^MAX(D$88-1,0)-$E$36*D96,0) | E97: =IF((E$88-$E$28)>=1,-$E$35*(1+Supuestos!$B$5)^MAX(E$88-1,0)-$E$36*E96,0) | F97: =IF((F$88-$E$28)>=1,-$E$35*(1+Supuestos!$B$5)^MAX(F$88-1,0)-$E$36*F96,0) | G97: =IF((G$88-$E$28)>=1,-$E$35*(1+Supuestos!$B$5)^MAX(G$88-1,0)-$E$36*G96,0) | H97: =IF((H$88-$E$28)>=1,-$E$35*(1+Supuestos!$B$5)^MAX(H$88-1,0)-$E$36*H96,0) | I97: =IF((I$88-$E$28)>=1,-$E$35*(1+Supuestos!$B$5)^MAX(I$88-1,0)-$E$36*I96,0) | J97: =IF((J$88-$E$28)>=1,-$E$35*(1+Supuestos!$B$5)^MAX(J$88-1,0)-$E$36*J96,0) | ... W97: =IF((W$88-$E$28)>=1,-$E$35*(1+Supuestos!$B$5)^MAX(W$88-1,0)-$E$36*W96,0)
A98: Impuestos - fase 2 | C98: =-$E$37*C96 | D98: =-$E$37*D96 | E98: =-$E$37*E96 | F98: =-$E$37*F96 | G98: =-$E$37*G96 | H98: =-$E$37*H96 | I98: =-$E$37*I96 | J98: =-$E$37*J96 | ... W98: =-$E$37*W96
A99: Reposiciones - fase 2 | C99: =0 | D99: =0 | E99: =0 | F99: =0 | G99: =0 | H99: =0 | I99: =0 | J99: =0 | ... W99: =0
A100: Valor residual (año 20) - fase 2 | C100: =IF(AND(C$88=20,$E$40>1),$E$27*(1+Supuestos!$B$5)^MAX($E$28-1,0)*MAX(0,1-(20-$E$28)/$E$40),0) | D100: =IF(AND(D$88=20,$E$40>1),$E$27*(1+Supuestos!$B$5)^MAX($E$28-1,0)*MAX(0,1-(20-$E$28)/$E$40),0) | E100: =IF(AND(E$88=20,$E$40>1),$E$27*(1+Supuestos!$B$5)^MAX($E$28-1,0)*MAX(0,1-(20-$E$28)/$E$40),0) | F100: =IF(AND(F$88=20,$E$40>1),$E$27*(1+Supuestos!$B$5)^MAX($E$28-1,0)*MAX(0,1-(20-$E$28)/$E$40),0) | G100: =IF(AND(G$88=20,$E$40>1),$E$27*(1+Supuestos!$B$5)^MAX($E$28-1,0)*MAX(0,1-(20-$E$28)/$E$40),0) | H100: =IF(AND(H$88=20,$E$40>1),$E$27*(1+Supuestos!$B$5)^MAX($E$28-1,0)*MAX(0,1-(20-$E$28)/$E$40),0) | I100: =IF(AND(I$88=20,$E$40>1),$E$27*(1+Supuestos!$B$5)^MAX($E$28-1,0)*MAX(0,1-(20-$E$28)/$E$40),0) | J100: =IF(AND(J$88=20,$E$40>1),$E$27*(1+Supuestos!$B$5)^MAX($E$28-1,0)*MAX(0,1-(20-$E$28)/$E$40),0) | ... W100: =IF(AND(W$88=20,$E$40>1),$E$27*(1+Supuestos!$B$5)^MAX($E$28-1,0)*MAX(0,1-(20-$E$28)/$E$40),0)
A101: Inversión - fase 3 | C101: =IF(C$88=$E$51,-$E$50*(1+Supuestos!$B$5)^MAX($E$51-1,0),0) | D101: =IF(D$88=$E$51,-$E$50*(1+Supuestos!$B$5)^MAX($E$51-1,0),0) | E101: =IF(E$88=$E$51,-$E$50*(1+Supuestos!$B$5)^MAX($E$51-1,0),0) | F101: =IF(F$88=$E$51,-$E$50*(1+Supuestos!$B$5)^MAX($E$51-1,0),0) | G101: =IF(G$88=$E$51,-$E$50*(1+Supuestos!$B$5)^MAX($E$51-1,0),0) | H101: =IF(H$88=$E$51,-$E$50*(1+Supuestos!$B$5)^MAX($E$51-1,0),0) | I101: =IF(I$88=$E$51,-$E$50*(1+Supuestos!$B$5)^MAX($E$51-1,0),0) | J101: =IF(J$88=$E$51,-$E$50*(1+Supuestos!$B$5)^MAX($E$51-1,0),0) | ... W101: =IF(W$88=$E$51,-$E$50*(1+Supuestos!$B$5)^MAX($E$51-1,0),0)
A102: Ingresos cobrados - fase 3 | C102: =IF((C$88-$E$51)>=1,CHOOSE(Supuestos!$B$3,$E$52,$E$53,$E$54)*12*CHOOSE(Supuestos!$B$3,$E$55,$E$56,$E$57)*IF((C$88-$E$51)=1,$E$61,IF((C$88-$E$51)=2,$E$62,1))*(1+Supuestos!$B$5)^MAX(C$88-1,0),0) | D102: =IF((D$88-$E$51)>=1,CHOOSE(Supuestos!$B$3,$E$52,$E$53,$E$54)*12*CHOOSE(Supuestos!$B$3,$E$55,$E$56,$E$57)*IF((D$88-$E$51)=1,$E$61,IF((D$88-$E$51)=2,$E$62,1))*(1+Supuestos!$B$5)^MAX(D$88-1,0),0) | E102: =IF((E$88-$E$51)>=1,CHOOSE(Supuestos!$B$3,$E$52,$E$53,$E$54)*12*CHOOSE(Supuestos!$B$3,$E$55,$E$56,$E$57)*IF((E$88-$E$51)=1,$E$61,IF((E$88-$E$51)=2,$E$62,1))*(1+Supuestos!$B$5)^MAX(E$88-1,0),0) | F102: =IF((F$88-$E$51)>=1,CHOOSE(Supuestos!$B$3,$E$52,$E$53,$E$54)*12*CHOOSE(Supuestos!$B$3,$E$55,$E$56,$E$57)*IF((F$88-$E$51)=1,$E$61,IF((F$88-$E$51)=2,$E$62,1))*(1+Supuestos!$B$5)^MAX(F$88-1,0),0) | G102: =IF((G$88-$E$51)>=1,CHOOSE(Supuestos!$B$3,$E$52,$E$53,$E$54)*12*CHOOSE(Supuestos!$B$3,$E$55,$E$56,$E$57)*IF((G$88-$E$51)=1,$E$61,IF((G$88-$E$51)=2,$E$62,1))*(1+Supuestos!$B$5)^MAX(G$88-1,0),0) | H102: =IF((H$88-$E$51)>=1,CHOOSE(Supuestos!$B$3,$E$52,$E$53,$E$54)*12*CHOOSE(Supuestos!$B$3,$E$55,$E$56,$E$57)*IF((H$88-$E$51)=1,$E$61,IF((H$88-$E$51)=2,$E$62,1))*(1+Supuestos!$B$5)^MAX(H$88-1,0),0) | I102: =IF((I$88-$E$51)>=1,CHOOSE(Supuestos!$B$3,$E$52,$E$53,$E$54)*12*CHOOSE(Supuestos!$B$3,$E$55,$E$56,$E$57)*IF((I$88-$E$51)=1,$E$61,IF((I$88-$E$51)=2,$E$62,1))*(1+Supuestos!$B$5)^MAX(I$88-1,0),0) | J102: =IF((J$88-$E$51)>=1,CHOOSE(Supuestos!$B$3,$E$52,$E$53,$E$54)*12*CHOOSE(Supuestos!$B$3,$E$55,$E$56,$E$57)*IF((J$88-$E$51)=1,$E$61,IF((J$88-$E$51)=2,$E$62,1))*(1+Supuestos!$B$5)^MAX(J$88-1,0),0) | ... W102: =IF((W$88-$E$51)>=1,CHOOSE(Supuestos!$B$3,$E$52,$E$53,$E$54)*12*CHOOSE(Supuestos!$B$3,$E$55,$E$56,$E$57)*IF((W$88-$E$51)=1,$E$61,IF((W$88-$E$51)=2,$E$62,1))*(1+Supuestos!$B$5)^MAX(W$88-1,0),0)
A103: Gastos - fase 3 | C103: =IF((C$88-$E$51)>=1,-$E$58*(1+Supuestos!$B$5)^MAX(C$88-1,0)-$E$59*C102,0) | D103: =IF((D$88-$E$51)>=1,-$E$58*(1+Supuestos!$B$5)^MAX(D$88-1,0)-$E$59*D102,0) | E103: =IF((E$88-$E$51)>=1,-$E$58*(1+Supuestos!$B$5)^MAX(E$88-1,0)-$E$59*E102,0) | F103: =IF((F$88-$E$51)>=1,-$E$58*(1+Supuestos!$B$5)^MAX(F$88-1,0)-$E$59*F102,0) | G103: =IF((G$88-$E$51)>=1,-$E$58*(1+Supuestos!$B$5)^MAX(G$88-1,0)-$E$59*G102,0) | H103: =IF((H$88-$E$51)>=1,-$E$58*(1+Supuestos!$B$5)^MAX(H$88-1,0)-$E$59*H102,0) | I103: =IF((I$88-$E$51)>=1,-$E$58*(1+Supuestos!$B$5)^MAX(I$88-1,0)-$E$59*I102,0) | J103: =IF((J$88-$E$51)>=1,-$E$58*(1+Supuestos!$B$5)^MAX(J$88-1,0)-$E$59*J102,0) | ... W103: =IF((W$88-$E$51)>=1,-$E$58*(1+Supuestos!$B$5)^MAX(W$88-1,0)-$E$59*W102,0)
A104: Impuestos - fase 3 | C104: =-$E$60*C102 | D104: =-$E$60*D102 | E104: =-$E$60*E102 | F104: =-$E$60*F102 | G104: =-$E$60*G102 | H104: =-$E$60*H102 | I104: =-$E$60*I102 | J104: =-$E$60*J102 | ... W104: =-$E$60*W102
A105: Reposiciones - fase 3 | C105: =IF((C$88-$E$51)=$E$64,-$E$65*(1+Supuestos!$B$5)^MAX(C$88-1,0)*Supuestos!$B$22,0) | D105: =IF((D$88-$E$51)=$E$64,-$E$65*(1+Supuestos!$B$5)^MAX(D$88-1,0)*Supuestos!$B$22,0) | E105: =IF((E$88-$E$51)=$E$64,-$E$65*(1+Supuestos!$B$5)^MAX(E$88-1,0)*Supuestos!$B$22,0) | F105: =IF((F$88-$E$51)=$E$64,-$E$65*(1+Supuestos!$B$5)^MAX(F$88-1,0)*Supuestos!$B$22,0) | G105: =IF((G$88-$E$51)=$E$64,-$E$65*(1+Supuestos!$B$5)^MAX(G$88-1,0)*Supuestos!$B$22,0) | H105: =IF((H$88-$E$51)=$E$64,-$E$65*(1+Supuestos!$B$5)^MAX(H$88-1,0)*Supuestos!$B$22,0) | I105: =IF((I$88-$E$51)=$E$64,-$E$65*(1+Supuestos!$B$5)^MAX(I$88-1,0)*Supuestos!$B$22,0) | J105: =IF((J$88-$E$51)=$E$64,-$E$65*(1+Supuestos!$B$5)^MAX(J$88-1,0)*Supuestos!$B$22,0) | ... W105: =IF((W$88-$E$51)=$E$64,-$E$65*(1+Supuestos!$B$5)^MAX(W$88-1,0)*Supuestos!$B$22,0)
A106: Valor residual (año 20) - fase 3 | C106: =IF(AND(C$88=20,$E$63>1),$E$50*(1+Supuestos!$B$5)^MAX($E$51-1,0)*MAX(0,1-(20-$E$51)/$E$63),0) | D106: =IF(AND(D$88=20,$E$63>1),$E$50*(1+Supuestos!$B$5)^MAX($E$51-1,0)*MAX(0,1-(20-$E$51)/$E$63),0) | E106: =IF(AND(E$88=20,$E$63>1),$E$50*(1+Supuestos!$B$5)^MAX($E$51-1,0)*MAX(0,1-(20-$E$51)/$E$63),0) | F106: =IF(AND(F$88=20,$E$63>1),$E$50*(1+Supuestos!$B$5)^MAX($E$51-1,0)*MAX(0,1-(20-$E$51)/$E$63),0) | G106: =IF(AND(G$88=20,$E$63>1),$E$50*(1+Supuestos!$B$5)^MAX($E$51-1,0)*MAX(0,1-(20-$E$51)/$E$63),0) | H106: =IF(AND(H$88=20,$E$63>1),$E$50*(1+Supuestos!$B$5)^MAX($E$51-1,0)*MAX(0,1-(20-$E$51)/$E$63),0) | I106: =IF(AND(I$88=20,$E$63>1),$E$50*(1+Supuestos!$B$5)^MAX($E$51-1,0)*MAX(0,1-(20-$E$51)/$E$63),0) | J106: =IF(AND(J$88=20,$E$63>1),$E$50*(1+Supuestos!$B$5)^MAX($E$51-1,0)*MAX(0,1-(20-$E$51)/$E$63),0) | ... W106: =IF(AND(W$88=20,$E$63>1),$E$50*(1+Supuestos!$B$5)^MAX($E$51-1,0)*MAX(0,1-(20-$E$51)/$E$63),0)
A107: Inversión - fase 4 | C107: =IF(C$88=$E$73,-$E$72*(1+Supuestos!$B$5)^MAX($E$73-1,0),0) | D107: =IF(D$88=$E$73,-$E$72*(1+Supuestos!$B$5)^MAX($E$73-1,0),0) | E107: =IF(E$88=$E$73,-$E$72*(1+Supuestos!$B$5)^MAX($E$73-1,0),0) | F107: =IF(F$88=$E$73,-$E$72*(1+Supuestos!$B$5)^MAX($E$73-1,0),0) | G107: =IF(G$88=$E$73,-$E$72*(1+Supuestos!$B$5)^MAX($E$73-1,0),0) | H107: =IF(H$88=$E$73,-$E$72*(1+Supuestos!$B$5)^MAX($E$73-1,0),0) | I107: =IF(I$88=$E$73,-$E$72*(1+Supuestos!$B$5)^MAX($E$73-1,0),0) | J107: =IF(J$88=$E$73,-$E$72*(1+Supuestos!$B$5)^MAX($E$73-1,0),0) | ... W107: =IF(W$88=$E$73,-$E$72*(1+Supuestos!$B$5)^MAX($E$73-1,0),0)
...

Sheet D C + minideptos
A1: D. C + 2 pisos de minidepartamentos (año 3)
A2: Fase 1 igual a C. En el año 3, 2 pisos con 8 minidepartamentos de 1 dormitorio para personal de salud y del sector público.
A4: Fase 1: Local de esquina (100 m²)
A5: Partida | B5: Und. | C5: Cantidad | D5: P. unitario | E5: Parcial
A6: Local de esquina de 100 m² en pórticos de C.A. diseñados para 3 pisos, puertas enrollables y SS.HH. | B6: m² | C6: 100 | D6: 1500 | E6: =C6*D6
A7: Estudio de suelos, proyecto y licencia | B7: glb | C7: 1 | D7: 20000 | E7: =C7*D7
D8: Inversión (con imprevistos y factor de escenario) | E8: =SUM(E6:E7)*(1+Supuestos!$B$6)*Supuestos!$B$22
D9: Año de inversión (opera desde el año siguiente) | E9: 0
D10: Ingreso bruto potencial S/ por mes - pesimista | E10: 1000
D11: Ingreso bruto potencial S/ por mes - base | E11: 1300
D12: Ingreso bruto potencial S/ por mes - optimista | E12: 2000
D13: Ocupación cobrada - pesimista | E13: 0.7
D14: Ocupación cobrada - base | E14: 0.8
D15: Ocupación cobrada - optimista | E15: 0.9
D16: Gastos fijos S/ por año (personal, energía, mantenimiento, seguro, predial) | E16: 2500
D17: Gastos variables (% del ingreso cobrado) | E17: 0
D18: Impuestos (% del ingreso cobrado) | E18: 0.05
D19: Ingreso relativo 1.er año de operación | E19: 0.5
D20: Ingreso relativo 2.º año de operación | E20: 0.8
D21: Vida útil para valor residual (años) | E21: 50
A23: Fase 2: 3 locales al jirón + núcleo de escalera
A24: Partida | B24: Und. | C24: Cantidad | D24: P. unitario | E24: Parcial
A25: 3 locales de 39-48 m² (134.7 m²) y núcleo de escalera, SS.HH. y depósito de 26 m² junto a B, en pórticos de C.A. diseñados para 3 pisos | B25: m² | C25: 160.6 | D25: 1500 | E25: =C25*D25
A26: Ampliación del proyecto y licencia | B26: glb | C26: 1 | D26: 12000 | E26: =C26*D26
D27: Inversión (con imprevistos y factor de escenario) | E27: =SUM(E25:E26)*(1+Supuestos!$B$6)*Supuestos!$B$22
D28: Año de inversión (opera desde el año siguiente) | E28: 0
D29: Ingreso bruto potencial S/ por mes - pesimista | E29: 1616.4
D30: Ingreso bruto potencial S/ por mes - base | E30: 2020.5
D31: Ingreso bruto potencial S/ por mes - optimista | E31: 2424.6
D32: Ocupación cobrada - pesimista | E32: 0.7
D33: Ocupación cobrada - base | E33: 0.8
D34: Ocupación cobrada - optimista | E34: 0.9
D35: Gastos fijos S/ por año (personal, energía, mantenimiento, seguro, predial) | E35: 3600
D36: Gastos variables (% del ingreso cobrado) | E36: 0
D37: Impuestos (% del ingreso cobrado) | E37: 0.05
D38: Ingreso relativo 1.er año de operación | E38: 0.5
D39: Ingreso relativo 2.º año de operación | E39: 0.8
D40: Vida útil para valor residual (años) | E40: 50
A42: Fase 3: Cochera de abonados (fondo, descubierta)
A43: Partida | B43: Und. | C43: Cantidad | D43: P. unitario | E43: Parcial
A44: Afirmado compactado e=0.20 m con bombeo | B44: m² | C44: 540 | D44: 40 | E44: =C44*D44
A45: Drenaje del patio | B45: ml | C45: 20 | D45: 220 | E45: =C45*D45
A46: Portón telescópico automatizado de 6.5 m con 40 controles + puerta peatonal | B46: glb | C46: 1 | D46: 15500 | E46: =C46*D46
A47: Cerco de albañilería en el fondo C-D | B47: ml | C47: 30 | D47: 330 | E47: =C47*D47
A48: Iluminación LED y CCTV de 4 cámaras | B48: glb | C48: 1 | D48: 7500 | E48: =C48*D48
A49: Señalización, numeración y topellantas | B49: glb | C49: 1 | D49: 2400 | E49: =C49*D49
D50: Inversión (con imprevistos y factor de escenario) | E50: =SUM(E44:E49)*(1+Supuestos!$B$6)*Supuestos!$B$22
D51: Año de inversión (opera desde el año siguiente) | E51: 0
D52: Ingreso bruto potencial S/ por mes - pesimista | E52: 480
D53: Ingreso bruto potencial S/ por mes - base | E53: 900
D54: Ingreso bruto potencial S/ por mes - optimista | E54: 1080
D55: Ocupación cobrada - pesimista | E55: 0.6
D56: Ocupación cobrada - base | E56: 0.7
D57: Ocupación cobrada - optimista | E57: 0.8
D58: Gastos fijos S/ por año (personal, energía, mantenimiento, seguro, predial) | E58: 3200
D59: Gastos variables (% del ingreso cobrado) | E59: 0
D60: Impuestos (% del ingreso cobrado) | E60: 0
D61: Ingreso relativo 1.er año de operación | E61: 0.6
D62: Ingreso relativo 2.º año de operación | E62: 0.85
... D65: Reposición 1: monto a precios de hoy | E65: 33330
A67: Fase 4: 2 pisos de minidepartamentos
A68: Partida | B68: Und. | C68: Cantidad | D68: P. unitario | E68: Parcial
A69: 2 pisos sobre los locales: 8 minidepartamentos de 1 dormitorio (≈ 45 m² útiles), escalera y pasillo | B69: m² | C69: 521 | D69: 1650 | E69: =C69*D69
A70: Expediente y licencia de ampliación | B70: glb | C70: 1 | D70: 15000 | E70: =C70*D70
D71: Inversión (con imprevistos y factor de escenario) | E71: =SUM(E69:E70)*(1+Supuestos!$B$6)*Supuestos!$B$22
D72: Año de inversión (opera desde el año siguiente) | E72: 3
D73: Ingreso bruto potencial S/ por mes - pesimista | E73: 3200
D74: Ingreso bruto potencial S/ por mes - base | E74: 4000
D75: Ingreso bruto potencial S/ por mes - optimista | E75: 4800
D76: Ocupación cobrada - pesimista | E76: 0.7
D77: Ocupación cobrada - base | E77: 0.85
D78: Ocupación cobrada - optimista | E78: 0.92
D79: Gastos fijos S/ por año (personal, energía, mantenimiento, seguro, predial) | E79: 15600
D80: Gastos variables (% del ingreso cobrado) | E80: 0
D81: Impuestos (% del ingreso cobrado) | E81: 0.05
D82: Ingreso relativo 1.er año de operación | E82: 0.6
D83: Ingreso relativo 2.º año de operación | E83: 0.9
D84: Vida útil para valor residual (años) | E84: 50
A86: FLUJO DE CAJA (S/ nominales)
A87: Concepto / año | C87: 0 | D87: 1 | E87: 2 | F87: 3 | G87: 4 | H87: 5 | I87: 6 | J87: 7 | K87: 8 | L87: 9 | M87: 10 | N87: 11 | O87: 12 | P87: 13 | Q87: 14 | R87: 15 | S87: 16 | T87: 17 | U87: 18 | V87: 19 | W87: 20
A88: Inversión - fase 1 | C88: =IF(C$87=$E$9,-$E$8*(1+Supuestos!$B$5)^MAX($E$9-1,0),0) | D88: =IF(D$87=$E$9,-$E$8*(1+Supuestos!$B$5)^MAX($E$9-1,0),0) | E88: =IF(E$87=$E$9,-$E$8*(1+Supuestos!$B$5)^MAX($E$9-1,0),0) | F88: =IF(F$87=$E$9,-$E$8*(1+Supuestos!$B$5)^MAX($E$9-1,0),0) | G88: =IF(G$87=$E$9,-$E$8*(1+Supuestos!$B$5)^MAX($E$9-1,0),0) | H88: =IF(H$87=$E$9,-$E$8*(1+Supuestos!$B$5)^MAX($E$9-1,0),0) | I88: =IF(I$87=$E$9,-$E$8*(1+Supuestos!$B$5)^MAX($E$9-1,0),0) | J88: =IF(J$87=$E$9,-$E$8*(1+Supuestos!$B$5)^MAX($E$9-1,0),0) | ... W88: =IF(W$87=$E$9,-$E$8*(1+Supuestos!$B$5)^MAX($E$9-1,0),0)
A89: Ingresos cobrados - fase 1 | C89: =IF((C$87-$E$9)>=1,CHOOSE(Supuestos!$B$3,$E$10,$E$11,$E$12)*12*CHOOSE(Supuestos!$B$3,$E$13,$E$14,$E$15)*IF((C$87-$E$9)=1,$E$19,IF((C$87-$E$9)=2,$E$20,1))*(1+Supuestos!$B$5)^MAX(C$87-1,0),0) | D89: =IF((D$87-$E$9)>=1,CHOOSE(Supuestos!$B$3,$E$10,$E$11,$E$12)*12*CHOOSE(Supuestos!$B$3,$E$13,$E$14,$E$15)*IF((D$87-$E$9)=1,$E$19,IF((D$87-$E$9)=2,$E$20,1))*(1+Supuestos!$B$5)^MAX(D$87-1,0),0) | E89: =IF((E$87-$E$9)>=1,CHOOSE(Supuestos!$B$3,$E$10,$E$11,$E$12)*12*CHOOSE(Supuestos!$B$3,$E$13,$E$14,$E$15)*IF((E$87-$E$9)=1,$E$19,IF((E$87-$E$9)=2,$E$20,1))*(1+Supuestos!$B$5)^MAX(E$87-1,0),0) | F89: =IF((F$87-$E$9)>=1,CHOOSE(Supuestos!$B$3,$E$10,$E$11,$E$12)*12*CHOOSE(Supuestos!$B$3,$E$13,$E$14,$E$15)*IF((F$87-$E$9)=1,$E$19,IF((F$87-$E$9)=2,$E$20,1))*(1+Supuestos!$B$5)^MAX(F$87-1,0),0) | G89: =IF((G$87-$E$9)>=1,CHOOSE(Supuestos!$B$3,$E$10,$E$11,$E$12)*12*CHOOSE(Supuestos!$B$3,$E$13,$E$14,$E$15)*IF((G$87-$E$9)=1,$E$19,IF((G$87-$E$9)=2,$E$20,1))*(1+Supuestos!$B$5)^MAX(G$87-1,0),0) | H89: =IF((H$87-$E$9)>=1,CHOOSE(Supuestos!$B$3,$E$10,$E$11,$E$12)*12*CHOOSE(Supuestos!$B$3,$E$13,$E$14,$E$15)*IF((H$87-$E$9)=1,$E$19,IF((H$87-$E$9)=2,$E$20,1))*(1+Supuestos!$B$5)^MAX(H$87-1,0),0) | I89: =IF((I$87-$E$9)>=1,CHOOSE(Supuestos!$B$3,$E$10,$E$11,$E$12)*12*CHOOSE(Supuestos!$B$3,$E$13,$E$14,$E$15)*IF((I$87-$E$9)=1,$E$19,IF((I$87-$E$9)=2,$E$20,1))*(1+Supuestos!$B$5)^MAX(I$87-1,0),0) | J89: =IF((J$87-$E$9)>=1,CHOOSE(Supuestos!$B$3,$E$10,$E$11,$E$12)*12*CHOOSE(Supuestos!$B$3,$E$13,$E$14,$E$15)*IF((J$87-$E$9)=1,$E$19,IF((J$87-$E$9)=2,$E$20,1))*(1+Supuestos!$B$5)^MAX(J$87-1,0),0) | ... W89: =IF((W$87-$E$9)>=1,CHOOSE(Supuestos!$B$3,$E$10,$E$11,$E$12)*12*CHOOSE(Supuestos!$B$3,$E$13,$E$14,$E$15)*IF((W$87-$E$9)=1,$E$19,IF((W$87-$E$9)=2,$E$20,1))*(1+Supuestos!$B$5)^MAX(W$87-1,0),0)
A90: Gastos - fase 1 | C90: =IF((C$87-$E$9)>=1,-$E$16*(1+Supuestos!$B$5)^MAX(C$87-1,0)-$E$17*C89,0) | D90: =IF((D$87-$E$9)>=1,-$E$16*(1+Supuestos!$B$5)^MAX(D$87-1,0)-$E$17*D89,0) | E90: =IF((E$87-$E$9)>=1,-$E$16*(1+Supuestos!$B$5)^MAX(E$87-1,0)-$E$17*E89,0) | F90: =IF((F$87-$E$9)>=1,-$E$16*(1+Supuestos!$B$5)^MAX(F$87-1,0)-$E$17*F89,0) | G90: =IF((G$87-$E$9)>=1,-$E$16*(1+Supuestos!$B$5)^MAX(G$87-1,0)-$E$17*G89,0) | H90: =IF((H$87-$E$9)>=1,-$E$16*(1+Supuestos!$B$5)^MAX(H$87-1,0)-$E$17*H89,0) | I90: =IF((I$87-$E$9)>=1,-$E$16*(1+Supuestos!$B$5)^MAX(I$87-1,0)-$E$17*I89,0) | J90: =IF((J$87-$E$9)>=1,-$E$16*(1+Supuestos!$B$5)^MAX(J$87-1,0)-$E$17*J89,0) | ... W90: =IF((W$87-$E$9)>=1,-$E$16*(1+Supuestos!$B$5)^MAX(W$87-1,0)-$E$17*W89,0)
A91: Impuestos - fase 1 | C91: =-$E$18*C89 | D91: =-$E$18*D89 | E91: =-$E$18*E89 | F91: =-$E$18*F89 | G91: =-$E$18*G89 | H91: =-$E$18*H89 | I91: =-$E$18*I89 | J91: =-$E$18*J89 | ... W91: =-$E$18*W89
A92: Reposiciones - fase 1 | C92: =0 | D92: =0 | E92: =0 | F92: =0 | G92: =0 | H92: =0 | I92: =0 | J92: =0 | ... W92: =0
A93: Valor residual (año 20) - fase 1 | C93: =IF(AND(C$87=20,$E$21>1),$E$8*(1+Supuestos!$B$5)^MAX($E$9-1,0)*MAX(0,1-(20-$E$9)/$E$21),0) | D93: =IF(AND(D$87=20,$E$21>1),$E$8*(1+Supuestos!$B$5)^MAX($E$9-1,0)*MAX(0,1-(20-$E$9)/$E$21),0) | E93: =IF(AND(E$87=20,$E$21>1),$E$8*(1+Supuestos!$B$5)^MAX($E$9-1,0)*MAX(0,1-(20-$E$9)/$E$21),0) | F93: =IF(AND(F$87=20,$E$21>1),$E$8*(1+Supuestos!$B$5)^MAX($E$9-1,0)*MAX(0,1-(20-$E$9)/$E$21),0) | G93: =IF(AND(G$87=20,$E$21>1),$E$8*(1+Supuestos!$B$5)^MAX($E$9-1,0)*MAX(0,1-(20-$E$9)/$E$21),0) | H93: =IF(AND(H$87=20,$E$21>1),$E$8*(1+Supuestos!$B$5)^MAX($E$9-1,0)*MAX(0,1-(20-$E$9)/$E$21),0) | I93: =IF(AND(I$87=20,$E$21>1),$E$8*(1+Supuestos!$B$5)^MAX($E$9-1,0)*MAX(0,1-(20-$E$9)/$E$21),0) | J93: =IF(AND(J$87=20,$E$21>1),$E$8*(1+Supuestos!$B$5)^MAX($E$9-1,0)*MAX(0,1-(20-$E$9)/$E$21),0) | ... W93: =IF(AND(W$87=20,$E$21>1),$E$8*(1+Supuestos!$B$5)^MAX($E$9-1,0)*MAX(0,1-(20-$E$9)/$E$21),0)
A94: Inversión - fase 2 | C94: =IF(C$87=$E$28,-$E$27*(1+Supuestos!$B$5)^MAX($E$28-1,0),0) | D94: =IF(D$87=$E$28,-$E$27*(1+Supuestos!$B$5)^MAX($E$28-1,0),0) | E94: =IF(E$87=$E$28,-$E$27*(1+Supuestos!$B$5)^MAX($E$28-1,0),0) | F94: =IF(F$87=$E$28,-$E$27*(1+Supuestos!$B$5)^MAX($E$28-1,0),0) | G94: =IF(G$87=$E$28,-$E$27*(1+Supuestos!$B$5)^MAX($E$28-1,0),0) | H94: =IF(H$87=$E$28,-$E$27*(1+Supuestos!$B$5)^MAX($E$28-1,0),0) | I94: =IF(I$87=$E$28,-$E$27*(1+Supuestos!$B$5)^MAX($E$28-1,0),0) | J94: =IF(J$87=$E$28,-$E$27*(1+Supuestos!$B$5)^MAX($E$28-1,0),0) | ... W94: =IF(W$87=$E$28,-$E$27*(1+Supuestos!$B$5)^MAX($E$28-1,0),0)
A95: Ingresos cobrados - fase 2 | C95: =IF((C$87-$E$28)>=1,CHOOSE(Supuestos!$B$3,$E$29,$E$30,$E$31)*12*CHOOSE(Supuestos!$B$3,$E$32,$E$33,$E$34)*IF((C$87-$E$28)=1,$E$38,IF((C$87-$E$28)=2,$E$39,1))*(1+Supuestos!$B$5)^MAX(C$87-1,0),0) | D95: =IF((D$87-$E$28)>=1,CHOOSE(Supuestos!$B$3,$E$29,$E$30,$E$31)*12*CHOOSE(Supuestos!$B$3,$E$32,$E$33,$E$34)*IF((D$87-$E$28)=1,$E$38,IF((D$87-$E$28)=2,$E$39,1))*(1+Supuestos!$B$5)^MAX(D$87-1,0),0) | E95: =IF((E$87-$E$28)>=1,CHOOSE(Supuestos!$B$3,$E$29,$E$30,$E$31)*12*CHOOSE(Supuestos!$B$3,$E$32,$E$33,$E$34)*IF((E$87-$E$28)=1,$E$38,IF((E$87-$E$28)=2,$E$39,1))*(1+Supuestos!$B$5)^MAX(E$87-1,0),0) | F95: =IF((F$87-$E$28)>=1,CHOOSE(Supuestos!$B$3,$E$29,$E$30,$E$31)*12*CHOOSE(Supuestos!$B$3,$E$32,$E$33,$E$34)*IF((F$87-$E$28)=1,$E$38,IF((F$87-$E$28)=2,$E$39,1))*(1+Supuestos!$B$5)^MAX(F$87-1,0),0) | G95: =IF((G$87-$E$28)>=1,CHOOSE(Supuestos!$B$3,$E$29,$E$30,$E$31)*12*CHOOSE(Supuestos!$B$3,$E$32,$E$33,$E$34)*IF((G$87-$E$28)=1,$E$38,IF((G$87-$E$28)=2,$E$39,1))*(1+Supuestos!$B$5)^MAX(G$87-1,0),0) | H95: =IF((H$87-$E$28)>=1,CHOOSE(Supuestos!$B$3,$E$29,$E$30,$E$31)*12*CHOOSE(Supuestos!$B$3,$E$32,$E$33,$E$34)*IF((H$87-$E$28)=1,$E$38,IF((H$87-$E$28)=2,$E$39,1))*(1+Supuestos!$B$5)^MAX(H$87-1,0),0) | I95: =IF((I$87-$E$28)>=1,CHOOSE(Supuestos!$B$3,$E$29,$E$30,$E$31)*12*CHOOSE(Supuestos!$B$3,$E$32,$E$33,$E$34)*IF((I$87-$E$28)=1,$E$38,IF((I$87-$E$28)=2,$E$39,1))*(1+Supuestos!$B$5)^MAX(I$87-1,0),0) | J95: =IF((J$87-$E$28)>=1,CHOOSE(Supuestos!$B$3,$E$29,$E$30,$E$31)*12*CHOOSE(Supuestos!$B$3,$E$32,$E$33,$E$34)*IF((J$87-$E$28)=1,$E$38,IF((J$87-$E$28)=2,$E$39,1))*(1+Supuestos!$B$5)^MAX(J$87-1,0),0) | ... W95: =IF((W$87-$E$28)>=1,CHOOSE(Supuestos!$B$3,$E$29,$E$30,$E$31)*12*CHOOSE(Supuestos!$B$3,$E$32,$E$33,$E$34)*IF((W$87-$E$28)=1,$E$38,IF((W$87-$E$28)=2,$E$39,1))*(1+Supuestos!$B$5)^MAX(W$87-1,0),0)
A96: Gastos - fase 2 | C96: =IF((C$87-$E$28)>=1,-$E$35*(1+Supuestos!$B$5)^MAX(C$87-1,0)-$E$36*C95,0) | D96: =IF((D$87-$E$28)>=1,-$E$35*(1+Supuestos!$B$5)^MAX(D$87-1,0)-$E$36*D95,0) | E96: =IF((E$87-$E$28)>=1,-$E$35*(1+Supuestos!$B$5)^MAX(E$87-1,0)-$E$36*E95,0) | F96: =IF((F$87-$E$28)>=1,-$E$35*(1+Supuestos!$B$5)^MAX(F$87-1,0)-$E$36*F95,0) | G96: =IF((G$87-$E$28)>=1,-$E$35*(1+Supuestos!$B$5)^MAX(G$87-1,0)-$E$36*G95,0) | H96: =IF((H$87-$E$28)>=1,-$E$35*(1+Supuestos!$B$5)^MAX(H$87-1,0)-$E$36*H95,0) | I96: =IF((I$87-$E$28)>=1,-$E$35*(1+Supuestos!$B$5)^MAX(I$87-1,0)-$E$36*I95,0) | J96: =IF((J$87-$E$28)>=1,-$E$35*(1+Supuestos!$B$5)^MAX(J$87-1,0)-$E$36*J95,0) | ... W96: =IF((W$87-$E$28)>=1,-$E$35*(1+Supuestos!$B$5)^MAX(W$87-1,0)-$E$36*W95,0)
A97: Impuestos - fase 2 | C97: =-$E$37*C95 | D97: =-$E$37*D95 | E97: =-$E$37*E95 | F97: =-$E$37*F95 | G97: =-$E$37*G95 | H97: =-$E$37*H95 | I97: =-$E$37*I95 | J97: =-$E$37*J95 | ... W97: =-$E$37*W95
A98: Reposiciones - fase 2 | C98: =0 | D98: =0 | E98: =0 | F98: =0 | G98: =0 | H98: =0 | I98: =0 | J98: =0 | ... W98: =0
A99: Valor residual (año 20) - fase 2 | C99: =IF(AND(C$87=20,$E$40>1),$E$27*(1+Supuestos!$B$5)^MAX($E$28-1,0)*MAX(0,1-(20-$E$28)/$E$40),0) | D99: =IF(AND(D$87=20,$E$40>1),$E$27*(1+Supuestos!$B$5)^MAX($E$28-1,0)*MAX(0,1-(20-$E$28)/$E$40),0) | E99: =IF(AND(E$87=20,$E$40>1),$E$27*(1+Supuestos!$B$5)^MAX($E$28-1,0)*MAX(0,1-(20-$E$28)/$E$40),0) | F99: =IF(AND(F$87=20,$E$40>1),$E$27*(1+Supuestos!$B$5)^MAX($E$28-1,0)*MAX(0,1-(20-$E$28)/$E$40),0) | G99: =IF(AND(G$87=20,$E$40>1),$E$27*(1+Supuestos!$B$5)^MAX($E$28-1,0)*MAX(0,1-(20-$E$28)/$E$40),0) | H99: =IF(AND(H$87=20,$E$40>1),$E$27*(1+Supuestos!$B$5)^MAX($E$28-1,0)*MAX(0,1-(20-$E$28)/$E$40),0) | I99: =IF(AND(I$87=20,$E$40>1),$E$27*(1+Supuestos!$B$5)^MAX($E$28-1,0)*MAX(0,1-(20-$E$28)/$E$40),0) | J99: =IF(AND(J$87=20,$E$40>1),$E$27*(1+Supuestos!$B$5)^MAX($E$28-1,0)*MAX(0,1-(20-$E$28)/$E$40),0) | ... W99: =IF(AND(W$87=20,$E$40>1),$E$27*(1+Supuestos!$B$5)^MAX($E$28-1,0)*MAX(0,1-(20-$E$28)/$E$40),0)
A100: Inversión - fase 3 | C100: =IF(C$87=$E$51,-$E$50*(1+Supuestos!$B$5)^MAX($E$51-1,0),0) | D100: =IF(D$87=$E$51,-$E$50*(1+Supuestos!$B$5)^MAX($E$51-1,0),0) | E100: =IF(E$87=$E$51,-$E$50*(1+Supuestos!$B$5)^MAX($E$51-1,0),0) | F100: =IF(F$87=$E$51,-$E$50*(1+Supuestos!$B$5)^MAX($E$51-1,0),0) | G100: =IF(G$87=$E$51,-$E$50*(1+Supuestos!$B$5)^MAX($E$51-1,0),0) | H100: =IF(H$87=$E$51,-$E$50*(1+Supuestos!$B$5)^MAX($E$51-1,0),0) | I100: =IF(I$87=$E$51,-$E$50*(1+Supuestos!$B$5)^MAX($E$51-1,0),0) | J100: =IF(J$87=$E$51,-$E$50*(1+Supuestos!$B$5)^MAX($E$51-1,0),0) | ... W100: =IF(W$87=$E$51,-$E$50*(1+Supuestos!$B$5)^MAX($E$51-1,0),0)
A101: Ingresos cobrados - fase 3 | C101: =IF((C$87-$E$51)>=1,CHOOSE(Supuestos!$B$3,$E$52,$E$53,$E$54)*12*CHOOSE(Supuestos!$B$3,$E$55,$E$56,$E$57)*IF((C$87-$E$51)=1,$E$61,IF((C$87-$E$51)=2,$E$62,1))*(1+Supuestos!$B$5)^MAX(C$87-1,0),0) | D101: =IF((D$87-$E$51)>=1,CHOOSE(Supuestos!$B$3,$E$52,$E$53,$E$54)*12*CHOOSE(Supuestos!$B$3,$E$55,$E$56,$E$57)*IF((D$87-$E$51)=1,$E$61,IF((D$87-$E$51)=2,$E$62,1))*(1+Supuestos!$B$5)^MAX(D$87-1,0),0) | E101: =IF((E$87-$E$51)>=1,CHOOSE(Supuestos!$B$3,$E$52,$E$53,$E$54)*12*CHOOSE(Supuestos!$B$3,$E$55,$E$56,$E$57)*IF((E$87-$E$51)=1,$E$61,IF((E$87-$E$51)=2,$E$62,1))*(1+Supuestos!$B$5)^MAX(E$87-1,0),0) | F101: =IF((F$87-$E$51)>=1,CHOOSE(Supuestos!$B$3,$E$52,$E$53,$E$54)*12*CHOOSE(Supuestos!$B$3,$E$55,$E$56,$E$57)*IF((F$87-$E$51)=1,$E$61,IF((F$87-$E$51)=2,$E$62,1))*(1+Supuestos!$B$5)^MAX(F$87-1,0),0) | G101: =IF((G$87-$E$51)>=1,CHOOSE(Supuestos!$B$3,$E$52,$E$53,$E$54)*12*CHOOSE(Supuestos!$B$3,$E$55,$E$56,$E$57)*IF((G$87-$E$51)=1,$E$61,IF((G$87-$E$51)=2,$E$62,1))*(1+Supuestos!$B$5)^MAX(G$87-1,0),0) | H101: =IF((H$87-$E$51)>=1,CHOOSE(Supuestos!$B$3,$E$52,$E$53,$E$54)*12*CHOOSE(Supuestos!$B$3,$E$55,$E$56,$E$57)*IF((H$87-$E$51)=1,$E$61,IF((H$87-$E$51)=2,$E$62,1))*(1+Supuestos!$B$5)^MAX(H$87-1,0),0) | I101: =IF((I$87-$E$51)>=1,CHOOSE(Supuestos!$B$3,$E$52,$E$53,$E$54)*12*CHOOSE(Supuestos!$B$3,$E$55,$E$56,$E$57)*IF((I$87-$E$51)=1,$E$61,IF((I$87-$E$51)=2,$E$62,1))*(1+Supuestos!$B$5)^MAX(I$87-1,0),0) | J101: =IF((J$87-$E$51)>=1,CHOOSE(Supuestos!$B$3,$E$52,$E$53,$E$54)*12*CHOOSE(Supuestos!$B$3,$E$55,$E$56,$E$57)*IF((J$87-$E$51)=1,$E$61,IF((J$87-$E$51)=2,$E$62,1))*(1+Supuestos!$B$5)^MAX(J$87-1,0),0) | ... W101: =IF((W$87-$E$51)>=1,CHOOSE(Supuestos!$B$3,$E$52,$E$53,$E$54)*12*CHOOSE(Supuestos!$B$3,$E$55,$E$56,$E$57)*IF((W$87-$E$51)=1,$E$61,IF((W$87-$E$51)=2,$E$62,1))*(1+Supuestos!$B$5)^MAX(W$87-1,0),0)
A102: Gastos - fase 3 | C102: =IF((C$87-$E$51)>=1,-$E$58*(1+Supuestos!$B$5)^MAX(C$87-1,0)-$E$59*C101,0) | D102: =IF((D$87-$E$51)>=1,-$E$58*(1+Supuestos!$B$5)^MAX(D$87-1,0)-$E$59*D101,0) | E102: =IF((E$87-$E$51)>=1,-$E$58*(1+Supuestos!$B$5)^MAX(E$87-1,0)-$E$59*E101,0) | F102: =IF((F$87-$E$51)>=1,-$E$58*(1+Supuestos!$B$5)^MAX(F$87-1,0)-$E$59*F101,0) | G102: =IF((G$87-$E$51)>=1,-$E$58*(1+Supuestos!$B$5)^MAX(G$87-1,0)-$E$59*G101,0) | H102: =IF((H$87-$E$51)>=1,-$E$58*(1+Supuestos!$B$5)^MAX(H$87-1,0)-$E$59*H101,0) | I102: =IF((I$87-$E$51)>=1,-$E$58*(1+Supuestos!$B$5)^MAX(I$87-1,0)-$E$59*I101,0) | J102: =IF((J$87-$E$51)>=1,-$E$58*(1+Supuestos!$B$5)^MAX(J$87-1,0)-$E$59*J101,0) | ... W102: =IF((W$87-$E$51)>=1,-$E$58*(1+Supuestos!$B$5)^MAX(W$87-1,0)-$E$59*W101,0)
A103: Impuestos - fase 3 | C103: =-$E$60*C101 | D103: =-$E$60*D101 | E103: =-$E$60*E101 | F103: =-$E$60*F101 | G103: =-$E$60*G101 | H103: =-$E$60*H101 | I103: =-$E$60*I101 | J103: =-$E$60*J101 | ... W103: =-$E$60*W101
A104: Reposiciones - fase 3 | C104: =IF((C$87-$E$51)=$E$64,-$E$65*(1+Supuestos!$B$5)^MAX(C$87-1,0)*Supuestos!$B$22,0) | D104: =IF((D$87-$E$51)=$E$64,-$E$65*(1+Supuestos!$B$5)^MAX(D$87-1,0)*Supuestos!$B$22,0) | E104: =IF((E$87-$E$51)=$E$64,-$E$65*(1+Supuestos!$B$5)^MAX(E$87-1,0)*Supuestos!$B$22,0) | F104: =IF((F$87-$E$51)=$E$64,-$E$65*(1+Supuestos!$B$5)^MAX(F$87-1,0)*Supuestos!$B$22,0) | G104: =IF((G$87-$E$51)=$E$64,-$E$65*(1+Supuestos!$B$5)^MAX(G$87-1,0)*Supuestos!$B$22,0) | H104: =IF((H$87-$E$51)=$E$64,-$E$65*(1+Supuestos!$B$5)^MAX(H$87-1,0)*Supuestos!$B$22,0) | I104: =IF((I$87-$E$51)=$E$64,-$E$65*(1+Supuestos!$B$5)^MAX(I$87-1,0)*Supuestos!$B$22,0) | J104: =IF((J$87-$E$51)=$E$64,-$E$65*(1+Supuestos!$B$5)^MAX(J$87-1,0)*Supuestos!$B$22,0) | ... W104: =IF((W$87-$E$51)=$E$64,-$E$65*(1+Supuestos!$B$5)^MAX(W$87-1,0)*Supuestos!$B$22,0)
A105: Valor residual (año 20) - fase 3 | C105: =IF(AND(C$87=20,$E$63>1),$E$50*(1+Supuestos!$B$5)^MAX($E$51-1,0)*MAX(0,1-(20-$E$51)/$E$63),0) | D105: =IF(AND(D$87=20,$E$63>1),$E$50*(1+Supuestos!$B$5)^MAX($E$51-1,0)*MAX(0,1-(20-$E$51)/$E$63),0) | E105: =IF(AND(E$87=20,$E$63>1),$E$50*(1+Supuestos!$B$5)^MAX($E$51-1,0)*MAX(0,1-(20-$E$51)/$E$63),0) | F105: =IF(AND(F$87=20,$E$63>1),$E$50*(1+Supuestos!$B$5)^MAX($E$51-1,0)*MAX(0,1-(20-$E$51)/$E$63),0) | G105: =IF(AND(G$87=20,$E$63>1),$E$50*(1+Supuestos!$B$5)^MAX($E$51-1,0)*MAX(0,1-(20-$E$51)/$E$63),0) | H105: =IF(AND(H$87=20,$E$63>1),$E$50*(1+Supuestos!$B$5)^MAX($E$51-1,0)*MAX(0,1-(20-$E$51)/$E$63),0) | I105: =IF(AND(I$87=20,$E$63>1),$E$50*(1+Supuestos!$B$5)^MAX($E$51-1,0)*MAX(0,1-(20-$E$51)/$E$63),0) | J105: =IF(AND(J$87=20,$E$63>1),$E$50*(1+Supuestos!$B$5)^MAX($E$51-1,0)*MAX(0,1-(20-$E$51)/$E$63),0) | ... W105: =IF(AND(W$87=20,$E$63>1),$E$50*(1+Supuestos!$B$5)^MAX($E$51-1,0)*MAX(0,1-(20-$E$51)/$E$63),0)
A106: Inversión - fase 4 | C106: =IF(C$87=$E$72,-$E$71*(1+Supuestos!$B$5)^MAX($E$72-1,0),0) | D106: =IF(D$87=$E$72,-$E$71*(1+Supuestos!$B$5)^MAX($E$72-1,0),0) | E106: =IF(E$87=$E$72,-$E$71*(1+Supuestos!$B$5)^MAX($E$72-1,0),0) | F106: =IF(F$87=$E$72,-$E$71*(1+Supuestos!$B$5)^MAX($E$72-1,0),0) | G106: =IF(G$87=$E$72,-$E$71*(1+Supuestos!$B$5)^MAX($E$72-1,0),0) | H106: =IF(H$87=$E$72,-$E$71*(1+Supuestos!$B$5)^MAX($E$72-1,0),0) | I106: =IF(I$87=$E$72,-$E$71*(1+Supuestos!$B$5)^MAX($E$72-1,0),0) | J106: =IF(J$87=$E$72,-$E$71*(1+Supuestos!$B$5)^MAX($E$72-1,0),0) | ... W106: =IF(W$87=$E$72,-$E$71*(1+Supuestos!$B$5)^MAX($E$72-1,0),0)
A107: Ingresos cobrados - fase 4 | C107: =IF((C$87-$E$72)>=1,CHOOSE(Supuestos!$B$3,$E$73,$E$74,$E$75)*12*CHOOSE(Supuestos!$B$3,$E$76,$E$77,$E$78)*IF((C$87-$E$72)=1,$E$82,IF((C$87-$E$72)=2,$E$83,1))*(1+Supuestos!$B$5)^MAX(C$87-1,0),0) | D107: =IF((D$87-$E$72)>=1,CHOOSE(Supuestos!$B$3,$E$73,$E$74,$E$75)*12*CHOOSE(Supuestos!$B$3,$E$76,$E$77,$E$78)*IF((D$87-$E$72)=1,$E$82,IF((D$87-$E$72)=2,$E$83,1))*(1+Supuestos!$B$5)^MAX(D$87-1,0),0) | E107: =IF((E$87-$E$72)>=1,CHOOSE(Supuestos!$B$3,$E$73,$E$74,$E$75)*12*CHOOSE(Supuestos!$B$3,$E$76,$E$77,$E$78)*IF((E$87-$E$72)=1,$E$82,IF((E$87-$E$72)=2,$E$83,1))*(1+Supuestos!$B$5)^MAX(E$87-1,0),0) | F107: =IF((F$87-$E$72)>=1,CHOOSE(Supuestos!$B$3,$E$73,$E$74,$E$75)*12*CHOOSE(Supuestos!$B$3,$E$76,$E$77,$E$78)*IF((F$87-$E$72)=1,$E$82,IF((F$87-$E$72)=2,$E$83,1))*(1+Supuestos!$B$5)^MAX(F$87-1,0),0) | G107: =IF((G$87-$E$72)>=1,CHOOSE(Supuestos!$B$3,$E$73,$E$74,$E$75)*12*CHOOSE(Supuestos!$B$3,$E$76,$E$77,$E$78)*IF((G$87-$E$72)=1,$E$82,IF((G$87-$E$72)=2,$E$83,1))*(1+Supuestos!$B$5)^MAX(G$87-1,0),0) | H107: =IF((H$87-$E$72)>=1,CHOOSE(Supuestos!$B$3,$E$73,$E$74,$E$75)*12*CHOOSE(Supuestos!$B$3,$E$76,$E$77,$E$78)*IF((H$87-$E$72)=1,$E$82,IF((H$87-$E$72)=2,$E$83,1))*(1+Supuestos!$B$5)^MAX(H$87-1,0),0) | I107: =IF((I$87-$E$72)>=1,CHOOSE(Supuestos!$B$3,$E$73,$E$74,$E$75)*12*CHOOSE(Supuestos!$B$3,$E$76,$E$77,$E$78)*IF((I$87-$E$72)=1,$E$82,IF((I$87-$E$72)=2,$E$83,1))*(1+Supuestos!$B$5)^MAX(I$87-1,0),0) | J107: =IF((J$87-$E$72)>=1,CHOOSE(Supuestos!$B$3,$E$73,$E$74,$E$75)*12*CHOOSE(Supuestos!$B$3,$E$76,$E$77,$E$78)*IF((J$87-$E$72)=1,$E$82,IF((J$87-$E$72)=2,$E$83,1))*(1+Supuestos!$B$5)^MAX(J$87-1,0),0) | ... W107: =IF((W$87-$E$72)>=1,CHOOSE(Supuestos!$B$3,$E$73,$E$74,$E$75)*12*CHOOSE(Supuestos!$B$3,$E$76,$E$77,$E$78)*IF((W$87-$E$72)=1,$E$82,IF((W$87-$E$72)=2,$E$83,1))*(1+Supuestos!$B$5)^MAX(W$87-1,0),0)
...

Sheet H Hostal
A1: H. Hostal de 16 habitaciones (3 pisos)
A2: Edificio de 3 pisos con 16 habitaciones con baño y recepción.
A4: Fase 1: Hostal
A5: Partida | B5: Und. | C5: Cantidad | D5: P. unitario | E5: Parcial
A6: Edificio de 3 pisos para hostal (750 m² techados) | B6: m² | C6: 750 | D6: 1700 | E6: =C6*D6
A7: Equipamiento de habitaciones y recepción | B7: und | C7: 16 | D7: 6000 | E7: =C7*D7
A8: Expediente, licencia (Modalidad D) y categorización MINCETUR | B8: glb | C8: 1 | D8: 30000 | E8: =C8*D8
D9: Inversión (con imprevistos y factor de escenario) | E9: =SUM(E6:E8)*(1+Supuestos!$B$6)*Supuestos!$B$22
D10: Año de inversión (opera desde el año siguiente) | E10: 0
D11: Ingreso bruto potencial S/ por mes - pesimista | E11: 31200
D12: Ingreso bruto potencial S/ por mes - base | E12: 36000
D13: Ingreso bruto potencial S/ por mes - optimista | E13: 40800
D14: Ocupación cobrada - pesimista | E14: 0.25
D15: Ocupación cobrada - base | E15: 0.35
D16: Ocupación cobrada - optimista | E16: 0.45
D17: Gastos fijos S/ por año (personal, energía, mantenimiento, seguro, predial) | E17: 94436.2
D18: Gastos variables (% del ingreso cobrado) | E18: 0.25
D19: Impuestos (% del ingreso cobrado) | E19: 0.15
D20: Ingreso relativo 1.er año de operación | E20: 0.5
D21: Ingreso relativo 2.º año de operación | E21: 0.8
D22: Vida útil para valor residual (años) | E22: 50
A24: FLUJO DE CAJA (S/ nominales)
A25: Concepto / año | C25: 0 | D25: 1 | E25: 2 | F25: 3 | G25: 4 | H25: 5 | I25: 6 | J25: 7 | K25: 8 | L25: 9 | M25: 10 | N25: 11 | O25: 12 | P25: 13 | Q25: 14 | R25: 15 | S25: 16 | T25: 17 | U25: 18 | V25: 19 | W25: 20
A26: Inversión - fase 1 | C26: =IF(C$25=$E$10,-$E$9*(1+Supuestos!$B$5)^MAX($E$10-1,0),0) | D26: =IF(D$25=$E$10,-$E$9*(1+Supuestos!$B$5)^MAX($E$10-1,0),0) | E26: =IF(E$25=$E$10,-$E$9*(1+Supuestos!$B$5)^MAX($E$10-1,0),0) | F26: =IF(F$25=$E$10,-$E$9*(1+Supuestos!$B$5)^MAX($E$10-1,0),0) | G26: =IF(G$25=$E$10,-$E$9*(1+Supuestos!$B$5)^MAX($E$10-1,0),0) | H26: =IF(H$25=$E$10,-$E$9*(1+Supuestos!$B$5)^MAX($E$10-1,0),0) | I26: =IF(I$25=$E$10,-$E$9*(1+Supuestos!$B$5)^MAX($E$10-1,0),0) | J26: =IF(J$25=$E$10,-$E$9*(1+Supuestos!$B$5)^MAX($E$10-1,0),0) | ... W26: =IF(W$25=$E$10,-$E$9*(1+Supuestos!$B$5)^MAX($E$10-1,0),0)
A27: Ingresos cobrados - fase 1 | C27: =IF((C$25-$E$10)>=1,CHOOSE(Supuestos!$B$3,$E$11,$E$12,$E$13)*12*CHOOSE(Supuestos!$B$3,$E$14,$E$15,$E$16)*IF((C$25-$E$10)=1,$E$20,IF((C$25-$E$10)=2,$E$21,1))*(1+Supuestos!$B$5)^MAX(C$25-1,0),0) | D27: =IF((D$25-$E$10)>=1,CHOOSE(Supuestos!$B$3,$E$11,$E$12,$E$13)*12*CHOOSE(Supuestos!$B$3,$E$14,$E$15,$E$16)*IF((D$25-$E$10)=1,$E$20,IF((D$25-$E$10)=2,$E$21,1))*(1+Supuestos!$B$5)^MAX(D$25-1,0),0) | E27: =IF((E$25-$E$10)>=1,CHOOSE(Supuestos!$B$3,$E$11,$E$12,$E$13)*12*CHOOSE(Supuestos!$B$3,$E$14,$E$15,$E$16)*IF((E$25-$E$10)=1,$E$20,IF((E$25-$E$10)=2,$E$21,1))*(1+Supuestos!$B$5)^MAX(E$25-1,0),0) | F27: =IF((F$25-$E$10)>=1,CHOOSE(Supuestos!$B$3,$E$11,$E$12,$E$13)*12*CHOOSE(Supuestos!$B$3,$E$14,$E$15,$E$16)*IF((F$25-$E$10)=1,$E$20,IF((F$25-$E$10)=2,$E$21,1))*(1+Supuestos!$B$5)^MAX(F$25-1,0),0) | G27: =IF((G$25-$E$10)>=1,CHOOSE(Supuestos!$B$3,$E$11,$E$12,$E$13)*12*CHOOSE(Supuestos!$B$3,$E$14,$E$15,$E$16)*IF((G$25-$E$10)=1,$E$20,IF((G$25-$E$10)=2,$E$21,1))*(1+Supuestos!$B$5)^MAX(G$25-1,0),0) | H27: =IF((H$25-$E$10)>=1,CHOOSE(Supuestos!$B$3,$E$11,$E$12,$E$13)*12*CHOOSE(Supuestos!$B$3,$E$14,$E$15,$E$16)*IF((H$25-$E$10)=1,$E$20,IF((H$25-$E$10)=2,$E$21,1))*(1+Supuestos!$B$5)^MAX(H$25-1,0),0) | I27: =IF((I$25-$E$10)>=1,CHOOSE(Supuestos!$B$3,$E$11,$E$12,$E$13)*12*CHOOSE(Supuestos!$B$3,$E$14,$E$15,$E$16)*IF((I$25-$E$10)=1,$E$20,IF((I$25-$E$10)=2,$E$21,1))*(1+Supuestos!$B$5)^MAX(I$25-1,0),0) | J27: =IF((J$25-$E$10)>=1,CHOOSE(Supuestos!$B$3,$E$11,$E$12,$E$13)*12*CHOOSE(Supuestos!$B$3,$E$14,$E$15,$E$16)*IF((J$25-$E$10)=1,$E$20,IF((J$25-$E$10)=2,$E$21,1))*(1+Supuestos!$B$5)^MAX(J$25-1,0),0) | ... W27: =IF((W$25-$E$10)>=1,CHOOSE(Supuestos!$B$3,$E$11,$E$12,$E$13)*12*CHOOSE(Supuestos!$B$3,$E$14,$E$15,$E$16)*IF((W$25-$E$10)=1,$E$20,IF((W$25-$E$10)=2,$E$21,1))*(1+Supuestos!$B$5)^MAX(W$25-1,0),0)
A28: Gastos - fase 1 | C28: =IF((C$25-$E$10)>=1,-$E$17*(1+Supuestos!$B$5)^MAX(C$25-1,0)-$E$18*C27,0) | D28: =IF((D$25-$E$10)>=1,-$E$17*(1+Supuestos!$B$5)^MAX(D$25-1,0)-$E$18*D27,0) | E28: =IF((E$25-$E$10)>=1,-$E$17*(1+Supuestos!$B$5)^MAX(E$25-1,0)-$E$18*E27,0) | F28: =IF((F$25-$E$10)>=1,-$E$17*(1+Supuestos!$B$5)^MAX(F$25-1,0)-$E$18*F27,0) | G28: =IF((G$25-$E$10)>=1,-$E$17*(1+Supuestos!$B$5)^MAX(G$25-1,0)-$E$18*G27,0) | H28: =IF((H$25-$E$10)>=1,-$E$17*(1+Supuestos!$B$5)^MAX(H$25-1,0)-$E$18*H27,0) | I28: =IF((I$25-$E$10)>=1,-$E$17*(1+Supuestos!$B$5)^MAX(I$25-1,0)-$E$18*I27,0) | J28: =IF((J$25-$E$10)>=1,-$E$17*(1+Supuestos!$B$5)^MAX(J$25-1,0)-$E$18*J27,0) | ... W28: =IF((W$25-$E$10)>=1,-$E$17*(1+Supuestos!$B$5)^MAX(W$25-1,0)-$E$18*W27,0)
A29: Impuestos - fase 1 | C29: =-$E$19*C27 | D29: =-$E$19*D27 | E29: =-$E$19*E27 | F29: =-$E$19*F27 | G29: =-$E$19*G27 | H29: =-$E$19*H27 | I29: =-$E$19*I27 | J29: =-$E$19*J27 | ... W29: =-$E$19*W27
A30: Reposiciones - fase 1 | C30: =0 | D30: =0 | E30: =0 | F30: =0 | G30: =0 | H30: =0 | I30: =0 | J30: =0 | ... W30: =0
A31: Valor residual (año 20) - fase 1 | C31: =IF(AND(C$25=20,$E$22>1),$E$9*(1+Supuestos!$B$5)^MAX($E$10-1,0)*MAX(0,1-(20-$E$10)/$E$22),0) | D31: =IF(AND(D$25=20,$E$22>1),$E$9*(1+Supuestos!$B$5)^MAX($E$10-1,0)*MAX(0,1-(20-$E$10)/$E$22),0) | E31: =IF(AND(E$25=20,$E$22>1),$E$9*(1+Supuestos!$B$5)^MAX($E$10-1,0)*MAX(0,1-(20-$E$10)/$E$22),0) | F31: =IF(AND(F$25=20,$E$22>1),$E$9*(1+Supuestos!$B$5)^MAX($E$10-1,0)*MAX(0,1-(20-$E$10)/$E$22),0) | G31: =IF(AND(G$25=20,$E$22>1),$E$9*(1+Supuestos!$B$5)^MAX($E$10-1,0)*MAX(0,1-(20-$E$10)/$E$22),0) | H31: =IF(AND(H$25=20,$E$22>1),$E$9*(1+Supuestos!$B$5)^MAX($E$10-1,0)*MAX(0,1-(20-$E$10)/$E$22),0) | I31: =IF(AND(I$25=20,$E$22>1),$E$9*(1+Supuestos!$B$5)^MAX($E$10-1,0)*MAX(0,1-(20-$E$10)/$E$22),0) | J31: =IF(AND(J$25=20,$E$22>1),$E$9*(1+Supuestos!$B$5)^MAX($E$10-1,0)*MAX(0,1-(20-$E$10)/$E$22),0) | ... W31: =IF(AND(W$25=20,$E$22>1),$E$9*(1+Supuestos!$B$5)^MAX($E$10-1,0)*MAX(0,1-(20-$E$10)/$E$22),0)
A32: Inversión | C32: =C26 | D32: =D26 | E32: =E26 | F32: =F26 | G32: =G26 | H32: =H26 | I32: =I26 | J32: =J26 | ... W32: =W26
A33: Ingresos cobrados | C33: =C27 | D33: =D27 | E33: =E27 | F33: =F27 | G33: =G27 | H33: =H27 | I33: =I27 | J33: =J27 | ... W33: =W27
A34: Gastos | C34: =C28 | D34: =D28 | E34: =E28 | F34: =F28 | G34: =G28 | H34: =H28 | I34: =I28 | J34: =J28 | ... W34: =W28
A35: Impuestos | C35: =C29 | D35: =D29 | E35: =E29 | F35: =F29 | G35: =G29 | H35: =H29 | I35: =I29 | J35: =J29 | ... W35: =W29
A36: Reposiciones | C36: =C30 | D36: =D30 | E36: =E30 | F36: =F30 | G36: =G30 | H36: =H30 | I36: =I30 | J36: =J30 | ... W36: =W30
A37: Valor residual (año 20) | C37: =C31 | D37: =D31 | E37: =E31 | F37: =F31 | G37: =G31 | H37: =H31 | I37: =I31 | J37: =J31 | ... W37: =W31
A38: FLUJO NETO | C38: =C32+C33+C34+C35+C36+C37 | D38: =D32+D33+D34+D35+D36+D37 | E38: =E32+E33+E34+E35+E36+E37 | F38: =F32+F33+F34+F35+F36+F37 | G38: =G32+G33+G34+G35+G36+G37 | H38: =H32+H33+H34+H35+H36+H37 | I38: =I32+I33+I34+I35+I36+I37 | J38: =J32+J33+J34+J35+J36+J37 | ... W38: =W32+W33+W34+W35+W36+W37
A39: Caja acumulada (sin valor residual) | C39: =C38-C37 | D39: =C39+D38-D37 | E39: =D39+E38-E37 | F39: =E39+F38-F37 | G39: =F39+G38-G37 | H39: =G39+H38-H37 | I39: =H39+I38-I37 | J39: =I39+J38-J37 | K39: =J39+K38-K37 | ... W39: =V39+W38-W37
A40: Flujo del propietario contando el terreno (lo aporta hoy y lo recupera valorizado) | C40: =C38-Supuestos!$B$21 | D40: =D38 | E40: =E38 | F40: =F38 | G40: =G38 | H40: =H38 | I40: =I38 | J40: =J38 | K40: =K38 | ... V40: =V38 | W40: =W38+Supuestos!$B$21*(1+Supuestos!$B$23)^20
A42: Inversión total | C42: =-SUM(C32:W32)
A43: VAN al 10% | C43: =C38+NPV(Supuestos!$B$4,D38:W38)
A44: TIR | C44: =IFERROR(IRR(C38:W38),IFERROR(IRR(C38:W38,-0.05),"no aplica"))
A45: Año en que se recupera la inversión (acumulado ≥ 0) | C45: =IF(-SUM(C32:W32)=0,"sin inversión",IFERROR(INDEX(C25:W25,MATCH(TRUE,INDEX(C39:W39>=0,0),0)),"no en 20 años"))
A46: Caja neta del año 5 sin inversiones (S/ nominales) | C46: =H38-H32
A47: TIR contando el terreno | C47: =IFERROR(IRR(C40:W40),"no aplica")

Sheet Fuentes
A1: DATOS DE MERCADO Y FUENTES (investigación oct-2026)
A3: Tema | B3: Dato | C3: Fuente | D3: Fecha | E3: Confianza
A4: Población | B4: Ciudad de Mendoza: 5,130 hab. (Censo 2017) y 3,356 en 2007; provincia: 29,998 hab. (2017); la provincia creció 1.3 % anual entre 2017 y 2025 (Censos 2025). Estimado 2026: 6,100-6,700 hab. en la ciudad. | C4: INEI (citypopulation.de); INEI, nota de prensa de los Censos 2025 | D4: 2017 / 2026 | E4: media
A5: Eje comercial | B5: Agencia del Banco de la Nación en Jr. Toribio Rodríguez de Mendoza N.º 309: el jirón es el eje comercial e institucional. | C5: Banco de la Nación (ubicador de agencias) | D5: 2025 | E5: alta
A6: Hospital | B6: Nuevo local del Hospital María Auxiliadora II-1 (CUI 2195952, «Mejoramiento»): reemplaza al hospital que ya funciona en San Nicolás, con 26-54 camas; 96 % de avance hacia ago-2026, apertura probable en 2027; ubicación del nuevo sitio por verificar. | C6: MEF (DS 016-2017-EF), Contraloría, GORE Amazonas, prensa local | D6: 2026 | E6: media
A7: Carretera | B7: PE-8B Chachapoyas–Rodríguez de Mendoza: 76.9 km asfaltados y 10 puentes (≈ S/ 369 MM), aún en estudio definitivo. | C7: MTC / Provías Nacional (CUI 2546400) | D7: 2023-2025 | E7: alta
A8: Turismo | B8: El 94 % de los visitantes de la provincia son de la misma provincia y el 91 % se aloja con familiares; ocupación de hospedajes de Amazonas ≈ 19-23 %; arribos 2024: 382,622 (−10.8 %). | C8: Tesis UNALM; MINCETUR | D8: 2023-2025 | E8: media
A9: Transporte | B9: 4 empresas autorizadas por la DRTC en rutas Mendoza–Chachapoyas; no se halló terminal formal. | C9: DRTC Amazonas (resoluciones de autorización) | D9: 2022-2024 | E9: alta
A10: Alquiler de locales | B10: Chachapoyas, Jr. Amazonas: S/ 54-98 por m² al mes en locales de 25-55 m² y S/ 24 en 127 m²; Moyobamba: S/ 29-40; Tarapoto: S/ 28 (466 m² para financieras). | C10: Avisos en portales inmobiliarios | D10: oct-2026 | E10: media
A11: Alquiler de locales (Mendoza) | B11: Estimado: S/ 12-18 por m² al mes para locales de 40-50 m² en el jirón y S/ 10-20 para un local de 100 m² sin contrato (la renta por m² baja con el tamaño). Bagua Grande: S/ 600 por un local de 1.er piso. Sin avisos publicados en Mendoza. | C11: Estimación por comparables | D11: oct-2026 | E11: baja
A12: Cuartos y departamentos | B12: Chachapoyas: cuarto con baño S/ 380-480; departamento de 2 dormitorios S/ 1,100-1,400. Estimado para Mendoza: minidepartamento S/ 400-650. | C12: Avisos; estimación por comparables | D12: oct-2026 | E12: baja
A13: Valor del terreno | B13: Chachapoyas: lote céntrico de 204 m² a ≈ S/ 955 por m² (precio pedido); tasación en Huambo (misma provincia) ≈ S/ 680 por m² en 2019. Los lotes grandes se venden 20-40 % más baratos por m²: estimado para el lote S/ 400-850 por m². | C13: Avisos; tasación REPEV | D13: 2019-2026 | E13: baja
A14: Costo de construcción | B14: Albañilería confinada S/ 1,200-1,800 por m² (referencia nacional 2026); estimado para Mendoza: local de 1 piso S/ 950-1,250 y 2-3 pisos S/ 1,100-1,750 según acabados. | C14: Guías de costos 2026; RM 277-2025-VIVIENDA (valores unitarios) | D14: 2026 | E14: baja
... A20: Estacionamientos exigidos | B20: La A.070 exige estacionamiento dentro del lote para comercio; sin PDU la cantidad la fija el certificado de parámetros (≈ 5-6 plazas para 235 m² de locales, más 1 accesible). | C20: RNE A.070 (RM 060-2021-VIVIENDA) | D20: 2021 | E20: media
A23: QUÉ VALIDAR EN CAMPO ANTES DE INVERTIR
A24: Alquiler real de locales en el Jr. Rodríguez de Mendoza | B24: Recorrer 2-3 cuadras, anotar carteles «se alquila» y preguntar a 8-10 inquilinos cuánto pagan, cuántos m² tienen y qué garantía dejaron. Es el dato que más cambia el resultado.
A25: Interés de un inquilino ancla para la esquina | B25: Conversar con farmacias de cadena, cajas municipales (Piura, Sullana, Trujillo, Arequipa), Mibanco, cooperativas cafetaleras y ferreterías; pedir una carta de intención antes de construir.
A26: Certificado de Parámetros Urbanísticos y Edificatorios | B26: Pedirlo a la Municipalidad Provincial de Rodríguez de Mendoza: confirma usos permitidos, altura máxima, retiros o ensanche del jirón y estacionamientos exigidos a los locales (decide cuántas plazas quedan para abonados y si caben 3 pisos).
A27: Abonados de cochera | B27: Antes de habilitar la cochera, inscribir al menos 10-12 abonados con 3 meses pagados por adelantado.
A28: Ubicación del nuevo local del hospital y su personal adicional | B28: Es un reemplazo del hospital actual: averiguar en la DIRESA o en la obra (CUI 2195952) dónde queda, cuándo abre y cuánto personal nuevo llega. Si queda lejos, las boticas y consultorios se moverán hacia allá.
A29: Interés por arrendar el lote o la esquina | B29: Ofrecer el lote completo y la esquina (derecho de superficie o build-to-suit) a ferreterías, concesionarios de motos, empresas de transporte, cajas, farmacias y cooperativas antes de construir: una oferta seria cambia la decisión.
A30: Tasación del terreno | B30: Pedir una tasación a un perito REPEV (≈ S/ 500-1,000) y revisar compraventas recientes en notarías o SUNARP.
A31: Costo real de obra | B31: Pedir 2-3 cotizaciones a contratistas de Mendoza o Chachapoyas para casco y acabado económico.
A32: Zona sísmica y estudio de suelos | B32: Confirmar en la E.030 vigente si Rodríguez de Mendoza es zona 2 o 3 y hacer el estudio de mecánica de suelos antes de dimensionar zapatas para 3 pisos.
